{
  "batting": [
    {
      "Player": "Todd Hundley",
      "G": 3,
      "PA": 12,
      "AB": 10,
      "R": 1,
      "H": 3,
      "2B": 1,
      "3B": 0,
      "HR": 1,
      "RBI": 2,
      "SB": 0,
      "CS": 0,
      "BB": 2,
      "SO": 1,
      "GIDP": 0,
      "HBP": 0,
      "SH": 0,
      "SF": 0,
      "IBB": 0,
      "Current Streak": 3,
      "Longest Streak": 3,
      "BA": 0.3,
      "OBP": 0.4166666666666667,
      "SLG": 0.7,
      "OPS": 1.1166666666666667,
      "TB": 7
    },
    {
      "Player": "Eric Karros",
      "G": 3,
      "PA": 12,
      "AB": 12,
      "R": 3,
      "H": 4,
      "2B": 3,
      "3B": 0,
      "HR": 0,
      "RBI": 0,
      "SB": 0,
      "CS": 0,
      "BB": 0,
      "SO": 2,
      "GIDP": 0,
      "HBP": 0,
      "SH": 0,
      "SF": 0,
      "IBB": 0,
      "Current Streak": 2,
      "Longest Streak": 2,
      "BA": 0.3333333333333333,
      "OBP": 0.3333333333333333,
      "SLG": 0.5833333333333334,
      "OPS": 0.9166666666666667,
      "TB": 7
    },
    {
      "Player": "Eric Young",
      "G": 3,
      "PA": 14,
      "AB": 13,
      "R": 3,
      "H": 6,
      "2B": 2,
      "3B": 1,
      "HR": 0,
      "RBI": 3,
      "SB": 1,
      "CS": 2,
      "BB": 0,
      "SO": 3,
      "GIDP": 0,
      "HBP": 1,
      "SH": 0,
      "SF": 0,
      "IBB": 0,
      "Current Streak": 2,
      "Longest Streak": 2,
      "BA": 0.46153846153846156,
      "OBP": 0.5,
      "SLG": 0.7692307692307693,
      "OPS": 1.2692307692307692,
      "TB": 10
    },
    {
      "Player": "Adrian Beltre",
      "G": 3,
      "PA": 11,
      "AB": 9,
      "R": 2,
      "H": 4,
      "2B": 0,
      "3B": 0,
      "HR": 0,
      "RBI": 2,
      "SB": 0,
      "CS": 0,
      "BB": 0,
      "SO": 3,
      "GIDP": 0,
      "HBP": 2,
      "SH": 0,
      "SF": 0,
      "IBB": 0,
      "Current Streak": 3,
      "Longest Streak": 3,
      "BA": 0.4444444444444444,
      "OBP": 0.5454545454545454,
      "SLG": 0.4444444444444444,
      "OPS": 0.9898989898989898,
      "TB": 4
    },
    {
      "Player": "Mark Grudzielanek",
      "G": 3,
      "PA": 12,
      "AB": 12,
      "R": 1,
      "H": 5,
      "2B": 2,
      "3B": 0,
      "HR": 0,
      "RBI": 1,
      "SB": 0,
      "CS": 0,
      "BB": 0,
      "SO": 3,
      "GIDP": 0,
      "HBP": 0,
      "SH": 0,
      "SF": 0,
      "IBB": 0,
      "Current Streak": 1,
      "Longest Streak": 1,
      "BA": 0.4166666666666667,
      "OBP": 0.4166666666666667,
      "SLG": 0.5833333333333334,
      "OPS": 1.0,
      "TB": 7
    },
    {
      "Player": "Gary Sheffield",
      "G": 3,
      "PA": 13,
      "AB": 11,
      "R": 0,
      "H": 2,
      "2B": 0,
      "3B": 0,
      "HR": 0,
      "RBI": 0,
      "SB": 0,
      "CS": 0,
      "BB": 1,
      "SO": 4,
      "GIDP": 0,
      "HBP": 1,
      "SH": 0,
      "SF": 0,
      "IBB": 0,
      "Current Streak": 1,
      "Longest Streak": 1,
      "BA": 0.18181818181818182,
      "OBP": 0.3076923076923077,
      "SLG": 0.18181818181818182,
      "OPS": 0.48951048951048953,
      "TB": 2
    },
    {
      "Player": "Devon White",
      "G": 3,
      "PA": 13,
      "AB": 13,
      "R": 2,
      "H": 3,
      "2B": 2,
      "3B": 0,
      "HR": 1,
      "RBI": 3,
      "SB": 0,
      "CS": 0,
      "BB": 0,
      "SO": 4,
      "GIDP": 0,
      "HBP": 0,
      "SH": 0,
      "SF": 0,
      "IBB": 0,
      "Current Streak": 1,
      "Longest Streak": 1,
      "BA": 0.23076923076923078,
      "OBP": 0.23076923076923078,
      "SLG": 0.6153846153846154,
      "OPS": 0.8461538461538463,
      "TB": 8
    },
    {
      "Player": "Raul Mondesi",
      "G": 3,
      "PA": 13,
      "AB": 13,
      "R": 0,
      "H": 1,
      "2B": 0,
      "3B": 0,
      "HR": 0,
      "RBI": 1,
      "SB": 0,
      "CS": 1,
      "BB": 0,
      "SO": 3,
      "GIDP": 0,
      "HBP": 0,
      "SH": 0,
      "SF": 0,
      "IBB": 0,
      "Current Streak": 1,
      "Longest Streak": 1,
      "BA": 0.07692307692307693,
      "OBP": 0.07692307692307693,
      "SLG": 0.07692307692307693,
      "OPS": 0.15384615384615385,
      "TB": 1
    },
    {
      "Player": "Jose Vizcaino",
      "G": 3,
      "PA": 3,
      "AB": 3,
      "R": 0,
      "H": 1,
      "2B": 0,
      "3B": 0,
      "HR": 0,
      "RBI": 0,
      "SB": 0,
      "CS": 0,
      "BB": 0,
      "SO": 0,
      "GIDP": 0,
      "HBP": 0,
      "SH": 0,
      "SF": 0,
      "IBB": 0,
      "Current Streak": 0,
      "Longest Streak": 1,
      "BA": 0.3333333333333333,
      "OBP": 0.3333333333333333,
      "SLG": 0.3333333333333333,
      "OPS": 0.6666666666666666,
      "TB": 1
    },
    {
      "Player": "Todd Hollandsworth",
      "G": 0,
      "PA": 0,
      "AB": 0,
      "R": 0,
      "H": 0,
      "2B": 0,
      "3B": 0,
      "HR": 0,
      "RBI": 0,
      "SB": 0,
      "CS": 0,
      "BB": 0,
      "SO": 0,
      "GIDP": 0,
      "HBP": 0,
      "SH": 0,
      "SF": 0,
      "IBB": 0,
      "Current Streak": 0,
      "Longest Streak": 0,
      "BA": 0.0,
      "OBP": 0.0,
      "SLG": 0.0,
      "OPS": 0.0,
      "TB": 0
    },
    {
      "Player": "Angel Pena",
      "G": 0,
      "PA": 0,
      "AB": 0,
      "R": 0,
      "H": 0,
      "2B": 0,
      "3B": 0,
      "HR": 0,
      "RBI": 0,
      "SB": 0,
      "CS": 0,
      "BB": 0,
      "SO": 0,
      "GIDP": 0,
      "HBP": 0,
      "SH": 0,
      "SF": 0,
      "IBB": 0,
      "Current Streak": 0,
      "Longest Streak": 0,
      "BA": 0.0,
      "OBP": 0.0,
      "SLG": 0.0,
      "OPS": 0.0,
      "TB": 0
    },
    {
      "Player": "Craig Counsell",
      "G": 0,
      "PA": 0,
      "AB": 0,
      "R": 0,
      "H": 0,
      "2B": 0,
      "3B": 0,
      "HR": 0,
      "RBI": 0,
      "SB": 0,
      "CS": 0,
      "BB": 0,
      "SO": 0,
      "GIDP": 0,
      "HBP": 0,
      "SH": 0,
      "SF": 0,
      "IBB": 0,
      "Current Streak": 0,
      "Longest Streak": 0,
      "BA": 0.0,
      "OBP": 0.0,
      "SLG": 0.0,
      "OPS": 0.0,
      "TB": 0
    },
    {
      "Player": "Dave Hansen",
      "G": 2,
      "PA": 1,
      "AB": 1,
      "R": 0,
      "H": 0,
      "2B": 0,
      "3B": 0,
      "HR": 0,
      "RBI": 0,
      "SB": 0,
      "CS": 0,
      "BB": 0,
      "SO": 0,
      "GIDP": 0,
      "HBP": 0,
      "SH": 0,
      "SF": 0,
      "IBB": 0,
      "Current Streak": 0,
      "Longest Streak": 0,
      "BA": 0.0,
      "OBP": 0.0,
      "SLG": 0.0,
      "OPS": 0.0,
      "TB": 0
    },
    {
      "Player": "Trent Hubbard",
      "G": 0,
      "PA": 0,
      "AB": 0,
      "R": 0,
      "H": 0,
      "2B": 0,
      "3B": 0,
      "HR": 0,
      "RBI": 0,
      "SB": 0,
      "CS": 0,
      "BB": 0,
      "SO": 0,
      "GIDP": 0,
      "HBP": 0,
      "SH": 0,
      "SF": 0,
      "IBB": 0,
      "Current Streak": 0,
      "Longest Streak": 0,
      "BA": 0.0,
      "OBP": 0.0,
      "SLG": 0.0,
      "OPS": 0.0,
      "TB": 0
    },
    {
      "Player": "Paul Lo Duca",
      "G": 1,
      "PA": 1,
      "AB": 1,
      "R": 0,
      "H": 0,
      "2B": 0,
      "3B": 0,
      "HR": 0,
      "RBI": 0,
      "SB": 0,
      "CS": 0,
      "BB": 0,
      "SO": 0,
      "GIDP": 0,
      "HBP": 0,
      "SH": 0,
      "SF": 0,
      "IBB": 0,
      "Current Streak": 0,
      "Longest Streak": 0,
      "BA": 0.0,
      "OBP": 0.0,
      "SLG": 0.0,
      "OPS": 0.0,
      "TB": 0
    },
    {
      "Player": "Tripp Cromer",
      "G": 1,
      "PA": 1,
      "AB": 1,
      "R": 0,
      "H": 1,
      "2B": 0,
      "3B": 0,
      "HR": 0,
      "RBI": 0,
      "SB": 0,
      "CS": 0,
      "BB": 0,
      "SO": 0,
      "GIDP": 0,
      "HBP": 0,
      "SH": 0,
      "SF": 0,
      "IBB": 0,
      "Current Streak": 1,
      "Longest Streak": 1,
      "BA": 1.0,
      "OBP": 1.0,
      "SLG": 1.0,
      "OPS": 2.0,
      "TB": 1
    },
    {
      "Player": "Alex Cora",
      "G": 0,
      "PA": 0,
      "AB": 0,
      "R": 0,
      "H": 0,
      "2B": 0,
      "3B": 0,
      "HR": 0,
      "RBI": 0,
      "SB": 0,
      "CS": 0,
      "BB": 0,
      "SO": 0,
      "GIDP": 0,
      "HBP": 0,
      "SH": 0,
      "SF": 0,
      "IBB": 0,
      "Current Streak": 0,
      "Longest Streak": 0,
      "BA": 0.0,
      "OBP": 0.0,
      "SLG": 0.0,
      "OPS": 0.0,
      "TB": 0
    },
    {
      "Player": "Jacob Brumfield",
      "G": 1,
      "PA": 0,
      "AB": 0,
      "R": 1,
      "H": 0,
      "2B": 0,
      "3B": 0,
      "HR": 0,
      "RBI": 0,
      "SB": 1,
      "CS": 0,
      "BB": 0,
      "SO": 0,
      "GIDP": 0,
      "HBP": 0,
      "SH": 0,
      "SF": 0,
      "IBB": 0,
      "Current Streak": 0,
      "Longest Streak": 0,
      "BA": 0.0,
      "OBP": 0.0,
      "SLG": 0.0,
      "OPS": 0.0,
      "TB": 0
    },
    {
      "Player": "Chance Sanford",
      "G": 0,
      "PA": 0,
      "AB": 0,
      "R": 0,
      "H": 0,
      "2B": 0,
      "3B": 0,
      "HR": 0,
      "RBI": 0,
      "SB": 0,
      "CS": 0,
      "BB": 0,
      "SO": 0,
      "GIDP": 0,
      "HBP": 0,
      "SH": 0,
      "SF": 0,
      "IBB": 0,
      "Current Streak": 0,
      "Longest Streak": 0,
      "BA": 0.0,
      "OBP": 0.0,
      "SLG": 0.0,
      "OPS": 0.0,
      "TB": 0
    },
    {
      "Player": "Brent Cookson",
      "G": 0,
      "PA": 0,
      "AB": 0,
      "R": 0,
      "H": 0,
      "2B": 0,
      "3B": 0,
      "HR": 0,
      "RBI": 0,
      "SB": 0,
      "CS": 0,
      "BB": 0,
      "SO": 0,
      "GIDP": 0,
      "HBP": 0,
      "SH": 0,
      "SF": 0,
      "IBB": 0,
      "Current Streak": 0,
      "Longest Streak": 0,
      "BA": 0.0,
      "OBP": 0.0,
      "SLG": 0.0,
      "OPS": 0.0,
      "TB": 0
    },
    {
      "Player": "Rick Wilkins",
      "G": 1,
      "PA": 1,
      "AB": 1,
      "R": 0,
      "H": 1,
      "2B": 0,
      "3B": 0,
      "HR": 0,
      "RBI": 0,
      "SB": 0,
      "CS": 0,
      "BB": 0,
      "SO": 0,
      "GIDP": 0,
      "HBP": 0,
      "SH": 0,
      "SF": 0,
      "IBB": 0,
      "Current Streak": 1,
      "Longest Streak": 1,
      "BA": 1.0,
      "OBP": 1.0,
      "SLG": 1.0,
      "OPS": 2.0,
      "TB": 1
    },
    {
      "Player": "Juan Castro",
      "G": 0,
      "PA": 0,
      "AB": 0,
      "R": 0,
      "H": 0,
      "2B": 0,
      "3B": 0,
      "HR": 0,
      "RBI": 0,
      "SB": 0,
      "CS": 0,
      "BB": 0,
      "SO": 0,
      "GIDP": 0,
      "HBP": 0,
      "SH": 0,
      "SF": 0,
      "IBB": 0,
      "Current Streak": 0,
      "Longest Streak": 0,
      "BA": 0.0,
      "OBP": 0.0,
      "SLG": 0.0,
      "OPS": 0.0,
      "TB": 0
    },
    {
      "Player": "Kevin Brown",
      "G": 1,
      "PA": 2,
      "AB": 1,
      "R": 0,
      "H": 0,
      "2B": 0,
      "3B": 0,
      "HR": 0,
      "RBI": 0,
      "SB": 0,
      "CS": 0,
      "BB": 0,
      "SO": 0,
      "GIDP": 0,
      "HBP": 0,
      "SH": 1,
      "SF": 0,
      "IBB": 0,
      "Current Streak": 0,
      "Longest Streak": 0,
      "BA": 0.0,
      "OBP": 0.0,
      "SLG": 0.0,
      "OPS": 0.0,
      "TB": 0
    },
    {
      "Player": "Darren Dreifort",
      "G": 0,
      "PA": 0,
      "AB": 0,
      "R": 0,
      "H": 0,
      "2B": 0,
      "3B": 0,
      "HR": 0,
      "RBI": 0,
      "SB": 0,
      "CS": 0,
      "BB": 0,
      "SO": 0,
      "GIDP": 0,
      "HBP": 0,
      "SH": 0,
      "SF": 0,
      "IBB": 0,
      "Current Streak": 0,
      "Longest Streak": 0,
      "BA": 0.0,
      "OBP": 0.0,
      "SLG": 0.0,
      "OPS": 0.0,
      "TB": 0
    },
    {
      "Player": "Chan Ho Park",
      "G": 1,
      "PA": 1,
      "AB": 1,
      "R": 0,
      "H": 0,
      "2B": 0,
      "3B": 0,
      "HR": 0,
      "RBI": 0,
      "SB": 0,
      "CS": 0,
      "BB": 0,
      "SO": 1,
      "GIDP": 0,
      "HBP": 0,
      "SH": 0,
      "SF": 0,
      "IBB": 0,
      "Current Streak": 0,
      "Longest Streak": 0,
      "BA": 0.0,
      "OBP": 0.0,
      "SLG": 0.0,
      "OPS": 0.0,
      "TB": 0
    },
    {
      "Player": "Ismael Valdez",
      "G": 1,
      "PA": 3,
      "AB": 3,
      "R": 0,
      "H": 0,
      "2B": 0,
      "3B": 0,
      "HR": 0,
      "RBI": 0,
      "SB": 0,
      "CS": 0,
      "BB": 0,
      "SO": 1,
      "GIDP": 0,
      "HBP": 0,
      "SH": 0,
      "SF": 0,
      "IBB": 0,
      "Current Streak": 0,
      "Longest Streak": 0,
      "BA": 0.0,
      "OBP": 0.0,
      "SLG": 0.0,
      "OPS": 0.0,
      "TB": 0
    },
    {
      "Player": "Carlos Perez",
      "G": 0,
      "PA": 0,
      "AB": 0,
      "R": 0,
      "H": 0,
      "2B": 0,
      "3B": 0,
      "HR": 0,
      "RBI": 0,
      "SB": 0,
      "CS": 0,
      "BB": 0,
      "SO": 0,
      "GIDP": 0,
      "HBP": 0,
      "SH": 0,
      "SF": 0,
      "IBB": 0,
      "Current Streak": 0,
      "Longest Streak": 0,
      "BA": 0.0,
      "OBP": 0.0,
      "SLG": 0.0,
      "OPS": 0.0,
      "TB": 0
    },
    {
      "Player": "Jamie Arnold",
      "G": 0,
      "PA": 0,
      "AB": 0,
      "R": 0,
      "H": 0,
      "2B": 0,
      "3B": 0,
      "HR": 0,
      "RBI": 0,
      "SB": 0,
      "CS": 0,
      "BB": 0,
      "SO": 0,
      "GIDP": 0,
      "HBP": 0,
      "SH": 0,
      "SF": 0,
      "IBB": 0,
      "Current Streak": 0,
      "Longest Streak": 0,
      "BA": 0.0,
      "OBP": 0.0,
      "SLG": 0.0,
      "OPS": 0.0,
      "TB": 0
    },
    {
      "Player": "Eric Gagne",
      "G": 0,
      "PA": 0,
      "AB": 0,
      "R": 0,
      "H": 0,
      "2B": 0,
      "3B": 0,
      "HR": 0,
      "RBI": 0,
      "SB": 0,
      "CS": 0,
      "BB": 0,
      "SO": 0,
      "GIDP": 0,
      "HBP": 0,
      "SH": 0,
      "SF": 0,
      "IBB": 0,
      "Current Streak": 0,
      "Longest Streak": 0,
      "BA": 0.0,
      "OBP": 0.0,
      "SLG": 0.0,
      "OPS": 0.0,
      "TB": 0
    },
    {
      "Player": "Mike Judd",
      "G": 0,
      "PA": 0,
      "AB": 0,
      "R": 0,
      "H": 0,
      "2B": 0,
      "3B": 0,
      "HR": 0,
      "RBI": 0,
      "SB": 0,
      "CS": 0,
      "BB": 0,
      "SO": 0,
      "GIDP": 0,
      "HBP": 0,
      "SH": 0,
      "SF": 0,
      "IBB": 0,
      "Current Streak": 0,
      "Longest Streak": 0,
      "BA": 0.0,
      "OBP": 0.0,
      "SLG": 0.0,
      "OPS": 0.0,
      "TB": 0
    },
    {
      "Player": "Jeff Williams",
      "G": 0,
      "PA": 0,
      "AB": 0,
      "R": 0,
      "H": 0,
      "2B": 0,
      "3B": 0,
      "HR": 0,
      "RBI": 0,
      "SB": 0,
      "CS": 0,
      "BB": 0,
      "SO": 0,
      "GIDP": 0,
      "HBP": 0,
      "SH": 0,
      "SF": 0,
      "IBB": 0,
      "Current Streak": 0,
      "Longest Streak": 0,
      "BA": 0.0,
      "OBP": 0.0,
      "SLG": 0.0,
      "OPS": 0.0,
      "TB": 0
    },
    {
      "Player": "Onan Masaoka",
      "G": 2,
      "PA": 0,
      "AB": 0,
      "R": 0,
      "H": 0,
      "2B": 0,
      "3B": 0,
      "HR": 0,
      "RBI": 0,
      "SB": 0,
      "CS": 0,
      "BB": 0,
      "SO": 0,
      "GIDP": 0,
      "HBP": 0,
      "SH": 0,
      "SF": 0,
      "IBB": 0,
      "Current Streak": 0,
      "Longest Streak": 0,
      "BA": 0.0,
      "OBP": 0.0,
      "SLG": 0.0,
      "OPS": 0.0,
      "TB": 0
    },
    {
      "Player": "Robinson Checo",
      "G": 0,
      "PA": 0,
      "AB": 0,
      "R": 0,
      "H": 0,
      "2B": 0,
      "3B": 0,
      "HR": 0,
      "RBI": 0,
      "SB": 0,
      "CS": 0,
      "BB": 0,
      "SO": 0,
      "GIDP": 0,
      "HBP": 0,
      "SH": 0,
      "SF": 0,
      "IBB": 0,
      "Current Streak": 0,
      "Longest Streak": 0,
      "BA": 0.0,
      "OBP": 0.0,
      "SLG": 0.0,
      "OPS": 0.0,
      "TB": 0
    },
    {
      "Player": "Alan Mills",
      "G": 2,
      "PA": 0,
      "AB": 0,
      "R": 0,
      "H": 0,
      "2B": 0,
      "3B": 0,
      "HR": 0,
      "RBI": 0,
      "SB": 0,
      "CS": 0,
      "BB": 0,
      "SO": 0,
      "GIDP": 0,
      "HBP": 0,
      "SH": 0,
      "SF": 0,
      "IBB": 0,
      "Current Streak": 0,
      "Longest Streak": 0,
      "BA": 0.0,
      "OBP": 0.0,
      "SLG": 0.0,
      "OPS": 0.0,
      "TB": 0
    },
    {
      "Player": "Pedro Borbon",
      "G": 2,
      "PA": 0,
      "AB": 0,
      "R": 0,
      "H": 0,
      "2B": 0,
      "3B": 0,
      "HR": 0,
      "RBI": 0,
      "SB": 0,
      "CS": 0,
      "BB": 0,
      "SO": 0,
      "GIDP": 0,
      "HBP": 0,
      "SH": 0,
      "SF": 0,
      "IBB": 0,
      "Current Streak": 0,
      "Longest Streak": 0,
      "BA": 0.0,
      "OBP": 0.0,
      "SLG": 0.0,
      "OPS": 0.0,
      "TB": 0
    },
    {
      "Player": "Matt Herges",
      "G": 0,
      "PA": 0,
      "AB": 0,
      "R": 0,
      "H": 0,
      "2B": 0,
      "3B": 0,
      "HR": 0,
      "RBI": 0,
      "SB": 0,
      "CS": 0,
      "BB": 0,
      "SO": 0,
      "GIDP": 0,
      "HBP": 0,
      "SH": 0,
      "SF": 0,
      "IBB": 0,
      "Current Streak": 0,
      "Longest Streak": 0,
      "BA": 0.0,
      "OBP": 0.0,
      "SLG": 0.0,
      "OPS": 0.0,
      "TB": 0
    },
    {
      "Player": "Jeff Kubenka",
      "G": 0,
      "PA": 0,
      "AB": 0,
      "R": 0,
      "H": 0,
      "2B": 0,
      "3B": 0,
      "HR": 0,
      "RBI": 0,
      "SB": 0,
      "CS": 0,
      "BB": 0,
      "SO": 0,
      "GIDP": 0,
      "HBP": 0,
      "SH": 0,
      "SF": 0,
      "IBB": 0,
      "Current Streak": 0,
      "Longest Streak": 0,
      "BA": 0.0,
      "OBP": 0.0,
      "SLG": 0.0,
      "OPS": 0.0,
      "TB": 0
    },
    {
      "Player": "Dave Mlicki",
      "G": 2,
      "PA": 0,
      "AB": 0,
      "R": 0,
      "H": 0,
      "2B": 0,
      "3B": 0,
      "HR": 0,
      "RBI": 0,
      "SB": 0,
      "CS": 0,
      "BB": 0,
      "SO": 0,
      "GIDP": 0,
      "HBP": 0,
      "SH": 0,
      "SF": 0,
      "IBB": 0,
      "Current Streak": 0,
      "Longest Streak": 0,
      "BA": 0.0,
      "OBP": 0.0,
      "SLG": 0.0,
      "OPS": 0.0,
      "TB": 0
    },
    {
      "Player": "Jeff Shaw",
      "G": 1,
      "PA": 0,
      "AB": 0,
      "R": 0,
      "H": 0,
      "2B": 0,
      "3B": 0,
      "HR": 0,
      "RBI": 0,
      "SB": 0,
      "CS": 0,
      "BB": 0,
      "SO": 0,
      "GIDP": 0,
      "HBP": 0,
      "SH": 0,
      "SF": 0,
      "IBB": 0,
      "Current Streak": 0,
      "Longest Streak": 0,
      "BA": 0.0,
      "OBP": 0.0,
      "SLG": 0.0,
      "OPS": 0.0,
      "TB": 0
    },
    {
      "Player": "Mike Maddux",
      "G": 0,
      "PA": 0,
      "AB": 0,
      "R": 0,
      "H": 0,
      "2B": 0,
      "3B": 0,
      "HR": 0,
      "RBI": 0,
      "SB": 0,
      "CS": 0,
      "BB": 0,
      "SO": 0,
      "GIDP": 0,
      "HBP": 0,
      "SH": 0,
      "SF": 0,
      "IBB": 0,
      "Current Streak": 0,
      "Longest Streak": 0,
      "BA": 0.0,
      "OBP": 0.0,
      "SLG": 0.0,
      "OPS": 0.0,
      "TB": 0
    },
    {
      "Player": "Doug Bochtler",
      "G": 0,
      "PA": 0,
      "AB": 0,
      "R": 0,
      "H": 0,
      "2B": 0,
      "3B": 0,
      "HR": 0,
      "RBI": 0,
      "SB": 0,
      "CS": 0,
      "BB": 0,
      "SO": 0,
      "GIDP": 0,
      "HBP": 0,
      "SH": 0,
      "SF": 0,
      "IBB": 0,
      "Current Streak": 0,
      "Longest Streak": 0,
      "BA": 0.0,
      "OBP": 0.0,
      "SLG": 0.0,
      "OPS": 0.0,
      "TB": 0
    },
    {
      "Player": "Mel Rojas",
      "G": 2,
      "PA": 0,
      "AB": 0,
      "R": 0,
      "H": 0,
      "2B": 0,
      "3B": 0,
      "HR": 0,
      "RBI": 0,
      "SB": 0,
      "CS": 0,
      "BB": 0,
      "SO": 0,
      "GIDP": 0,
      "HBP": 0,
      "SH": 0,
      "SF": 0,
      "IBB": 0,
      "Current Streak": 0,
      "Longest Streak": 0,
      "BA": 0.0,
      "OBP": 0.0,
      "SLG": 0.0,
      "OPS": 0.0,
      "TB": 0
    },
    {
      "Player": "Antonio Osuna",
      "G": 0,
      "PA": 0,
      "AB": 0,
      "R": 0,
      "H": 0,
      "2B": 0,
      "3B": 0,
      "HR": 0,
      "RBI": 0,
      "SB": 0,
      "CS": 0,
      "BB": 0,
      "SO": 0,
      "GIDP": 0,
      "HBP": 0,
      "SH": 0,
      "SF": 0,
      "IBB": 0,
      "Current Streak": 0,
      "Longest Streak": 0,
      "BA": 0.0,
      "OBP": 0.0,
      "SLG": 0.0,
      "OPS": 0.0,
      "TB": 0
    }
  ],
  "pitching": [
    {
      "Player": "Jamie Arnold",
      "W": 0,
      "L": 0,
      "W-L%": 0,
      "ERA": "---",
      "G": 0,
      "GS": 0,
      "CG": 0,
      "SHO": 0,
      "SV": 0,
      "IP": 0.0,
      "H": 0,
      "R": 0,
      "ER": 0,
      "HR": 0,
      "BB": 0,
      "IBB": 0,
      "SO": 0,
      "HBP": 0,
      "BK": 0,
      "WP": 0,
      "WHIP": 0.0,
      "H9": 0.0,
      "HR9": 0.0,
      "BB9": 0.0,
      "SO9": 0.0,
      "SO/BB": 0.0,
      "P/S": 74.0,
      "Max": 101.0
    },
    {
      "Player": "Doug Bochtler",
      "W": 0,
      "L": 0,
      "W-L%": 0,
      "ERA": "---",
      "G": 0,
      "GS": 0,
      "CG": 0,
      "SHO": 0,
      "SV": 0,
      "IP": 0.0,
      "H": 0,
      "R": 0,
      "ER": 0,
      "HR": 0,
      "BB": 0,
      "IBB": 0,
      "SO": 0,
      "HBP": 0,
      "BK": 0,
      "WP": 0,
      "WHIP": 0.0,
      "H9": 0.0,
      "HR9": 0.0,
      "BB9": 0.0,
      "SO9": 0.0,
      "SO/BB": 0.0,
      "P/S": NaN,
      "Max": NaN
    },
    {
      "Player": "Pedro Borbon",
      "W": 0,
      "L": 0,
      "W-L%": 0,
      "ERA": 0,
      "G": 2,
      "GS": 0,
      "CG": 0,
      "SHO": 0,
      "SV": 0,
      "IP": 1.0,
      "H": 0,
      "R": 0,
      "ER": 0,
      "HR": 0,
      "BB": 0,
      "IBB": 0,
      "SO": 0,
      "HBP": 0,
      "BK": 0,
      "WP": 0,
      "WHIP": 0.0,
      "H9": 0.0,
      "HR9": 0.0,
      "BB9": 0.0,
      "SO9": 0.0,
      "SO/BB": 0.0,
      "P/S": NaN,
      "Max": NaN
    },
    {
      "Player": "Kevin Brown",
      "W": 0,
      "L": 1,
      "W-L%": 0,
      "ERA": 1.2857142857142856,
      "G": 1,
      "GS": 1,
      "CG": 0,
      "SHO": 0,
      "SV": 0,
      "IP": 7.0,
      "H": 6,
      "R": 3,
      "ER": 1,
      "HR": 1,
      "BB": 2,
      "IBB": 0,
      "SO": 4,
      "HBP": 0,
      "BK": 0,
      "WP": 2,
      "WHIP": 1.1428571428571428,
      "H9": 7.7142857142857135,
      "HR9": 1.2857142857142856,
      "BB9": 2.571428571428571,
      "SO9": 5.142857142857142,
      "SO/BB": 2.0,
      "P/S": 108.0,
      "Max": 124.0
    },
    {
      "Player": "Robinson Checo",
      "W": 0,
      "L": 0,
      "W-L%": 0,
      "ERA": "---",
      "G": 0,
      "GS": 0,
      "CG": 0,
      "SHO": 0,
      "SV": 0,
      "IP": 0.0,
      "H": 0,
      "R": 0,
      "ER": 0,
      "HR": 0,
      "BB": 0,
      "IBB": 0,
      "SO": 0,
      "HBP": 0,
      "BK": 0,
      "WP": 0,
      "WHIP": 0.0,
      "H9": 0.0,
      "HR9": 0.0,
      "BB9": 0.0,
      "SO9": 0.0,
      "SO/BB": 0.0,
      "P/S": 60.0,
      "Max": 83.0
    },
    {
      "Player": "Darren Dreifort",
      "W": 0,
      "L": 0,
      "W-L%": 0,
      "ERA": "---",
      "G": 0,
      "GS": 0,
      "CG": 0,
      "SHO": 0,
      "SV": 0,
      "IP": 0.0,
      "H": 0,
      "R": 0,
      "ER": 0,
      "HR": 0,
      "BB": 0,
      "IBB": 0,
      "SO": 0,
      "HBP": 0,
      "BK": 0,
      "WP": 0,
      "WHIP": 0.0,
      "H9": 0.0,
      "HR9": 0.0,
      "BB9": 0.0,
      "SO9": 0.0,
      "SO/BB": 0.0,
      "P/S": 95.0,
      "Max": 117.0
    },
    {
      "Player": "Eric Gagne",
      "W": 0,
      "L": 0,
      "W-L%": 0,
      "ERA": "---",
      "G": 0,
      "GS": 0,
      "CG": 0,
      "SHO": 0,
      "SV": 0,
      "IP": 0.0,
      "H": 0,
      "R": 0,
      "ER": 0,
      "HR": 0,
      "BB": 0,
      "IBB": 0,
      "SO": 0,
      "HBP": 0,
      "BK": 0,
      "WP": 0,
      "WHIP": 0.0,
      "H9": 0.0,
      "HR9": 0.0,
      "BB9": 0.0,
      "SO9": 0.0,
      "SO/BB": 0.0,
      "P/S": 102.0,
      "Max": 109.0
    },
    {
      "Player": "Matt Herges",
      "W": 0,
      "L": 0,
      "W-L%": 0,
      "ERA": "---",
      "G": 0,
      "GS": 0,
      "CG": 0,
      "SHO": 0,
      "SV": 0,
      "IP": 0.0,
      "H": 0,
      "R": 0,
      "ER": 0,
      "HR": 0,
      "BB": 0,
      "IBB": 0,
      "SO": 0,
      "HBP": 0,
      "BK": 0,
      "WP": 0,
      "WHIP": 0.0,
      "H9": 0.0,
      "HR9": 0.0,
      "BB9": 0.0,
      "SO9": 0.0,
      "SO/BB": 0.0,
      "P/S": NaN,
      "Max": NaN
    },
    {
      "Player": "Mike Judd",
      "W": 0,
      "L": 0,
      "W-L%": 0,
      "ERA": "---",
      "G": 0,
      "GS": 0,
      "CG": 0,
      "SHO": 0,
      "SV": 0,
      "IP": 0.0,
      "H": 0,
      "R": 0,
      "ER": 0,
      "HR": 0,
      "BB": 0,
      "IBB": 0,
      "SO": 0,
      "HBP": 0,
      "BK": 0,
      "WP": 0,
      "WHIP": 0.0,
      "H9": 0.0,
      "HR9": 0.0,
      "BB9": 0.0,
      "SO9": 0.0,
      "SO/BB": 0.0,
      "P/S": 88.0,
      "Max": 95.0
    },
    {
      "Player": "Jeff Kubenka",
      "W": 0,
      "L": 0,
      "W-L%": 0,
      "ERA": "---",
      "G": 0,
      "GS": 0,
      "CG": 0,
      "SHO": 0,
      "SV": 0,
      "IP": 0.0,
      "H": 0,
      "R": 0,
      "ER": 0,
      "HR": 0,
      "BB": 0,
      "IBB": 0,
      "SO": 0,
      "HBP": 0,
      "BK": 0,
      "WP": 0,
      "WHIP": 0.0,
      "H9": 0.0,
      "HR9": 0.0,
      "BB9": 0.0,
      "SO9": 0.0,
      "SO/BB": 0.0,
      "P/S": NaN,
      "Max": NaN
    },
    {
      "Player": "Mike Maddux",
      "W": 0,
      "L": 0,
      "W-L%": 0,
      "ERA": "---",
      "G": 0,
      "GS": 0,
      "CG": 0,
      "SHO": 0,
      "SV": 0,
      "IP": 0.0,
      "H": 0,
      "R": 0,
      "ER": 0,
      "HR": 0,
      "BB": 0,
      "IBB": 0,
      "SO": 0,
      "HBP": 0,
      "BK": 0,
      "WP": 0,
      "WHIP": 0.0,
      "H9": 0.0,
      "HR9": 0.0,
      "BB9": 0.0,
      "SO9": 0.0,
      "SO/BB": 0.0,
      "P/S": NaN,
      "Max": NaN
    },
    {
      "Player": "Onan Masaoka",
      "W": 0,
      "L": 0,
      "W-L%": 0,
      "ERA": 0,
      "G": 2,
      "GS": 0,
      "CG": 0,
      "SHO": 0,
      "SV": 0,
      "IP": 1.6666666666666665,
      "H": 2,
      "R": 0,
      "ER": 0,
      "HR": 0,
      "BB": 0,
      "IBB": 0,
      "SO": 1,
      "HBP": 1,
      "BK": 0,
      "WP": 0,
      "WHIP": 1.2000000000000002,
      "H9": 10.8,
      "HR9": 0.0,
      "BB9": 0.0,
      "SO9": 5.4,
      "SO/BB": 0.0,
      "P/S": NaN,
      "Max": NaN
    },
    {
      "Player": "Alan Mills",
      "W": 0,
      "L": 0,
      "W-L%": 0,
      "ERA": 18,
      "G": 2,
      "GS": 0,
      "CG": 0,
      "SHO": 0,
      "SV": 0,
      "IP": 2.0,
      "H": 3,
      "R": 4,
      "ER": 4,
      "HR": 2,
      "BB": 2,
      "IBB": 0,
      "SO": 0,
      "HBP": 0,
      "BK": 0,
      "WP": 0,
      "WHIP": 2.5,
      "H9": 13.5,
      "HR9": 9.0,
      "BB9": 9.0,
      "SO9": 0.0,
      "SO/BB": 0.0,
      "P/S": NaN,
      "Max": NaN
    },
    {
      "Player": "Dave Mlicki",
      "W": 0,
      "L": 0,
      "W-L%": 0,
      "ERA": 0,
      "G": 2,
      "GS": 0,
      "CG": 0,
      "SHO": 0,
      "SV": 0,
      "IP": 1.0,
      "H": 2,
      "R": 0,
      "ER": 0,
      "HR": 0,
      "BB": 2,
      "IBB": 0,
      "SO": 0,
      "HBP": 0,
      "BK": 0,
      "WP": 0,
      "WHIP": 4.0,
      "H9": 18.0,
      "HR9": 0.0,
      "BB9": 18.0,
      "SO9": 0.0,
      "SO/BB": 0.0,
      "P/S": NaN,
      "Max": NaN
    },
    {
      "Player": "Antonio Osuna",
      "W": 0,
      "L": 0,
      "W-L%": 0,
      "ERA": "---",
      "G": 0,
      "GS": 0,
      "CG": 0,
      "SHO": 0,
      "SV": 0,
      "IP": 0.0,
      "H": 0,
      "R": 0,
      "ER": 0,
      "HR": 0,
      "BB": 0,
      "IBB": 0,
      "SO": 0,
      "HBP": 0,
      "BK": 0,
      "WP": 0,
      "WHIP": 0.0,
      "H9": 0.0,
      "HR9": 0.0,
      "BB9": 0.0,
      "SO9": 0.0,
      "SO/BB": 0.0,
      "P/S": NaN,
      "Max": NaN
    },
    {
      "Player": "Chan Ho Park",
      "W": 0,
      "L": 0,
      "W-L%": 0,
      "ERA": 3.6,
      "G": 1,
      "GS": 1,
      "CG": 0,
      "SHO": 0,
      "SV": 0,
      "IP": 5.0,
      "H": 3,
      "R": 2,
      "ER": 2,
      "HR": 0,
      "BB": 4,
      "IBB": 0,
      "SO": 6,
      "HBP": 0,
      "BK": 0,
      "WP": 0,
      "WHIP": 1.4,
      "H9": 5.3999999999999995,
      "HR9": 0.0,
      "BB9": 7.2,
      "SO9": 10.799999999999999,
      "SO/BB": 1.5,
      "P/S": 99.0,
      "Max": 119.0
    },
    {
      "Player": "Carlos Perez",
      "W": 0,
      "L": 0,
      "W-L%": 0,
      "ERA": "---",
      "G": 0,
      "GS": 0,
      "CG": 0,
      "SHO": 0,
      "SV": 0,
      "IP": 0.0,
      "H": 0,
      "R": 0,
      "ER": 0,
      "HR": 0,
      "BB": 0,
      "IBB": 0,
      "SO": 0,
      "HBP": 0,
      "BK": 0,
      "WP": 0,
      "WHIP": 0.0,
      "H9": 0.0,
      "HR9": 0.0,
      "BB9": 0.0,
      "SO9": 0.0,
      "SO/BB": 0.0,
      "P/S": 88.0,
      "Max": 122.0
    },
    {
      "Player": "Mel Rojas",
      "W": 0,
      "L": 0,
      "W-L%": 0,
      "ERA": 0,
      "G": 2,
      "GS": 0,
      "CG": 0,
      "SHO": 0,
      "SV": 0,
      "IP": 1.3333333333333333,
      "H": 3,
      "R": 1,
      "ER": 0,
      "HR": 0,
      "BB": 0,
      "IBB": 1,
      "SO": 0,
      "HBP": 0,
      "BK": 0,
      "WP": 0,
      "WHIP": 2.25,
      "H9": 20.25,
      "HR9": 0.0,
      "BB9": 0.0,
      "SO9": 0.0,
      "SO/BB": 0.0,
      "P/S": NaN,
      "Max": NaN
    },
    {
      "Player": "Jeff Shaw",
      "W": 1,
      "L": 0,
      "W-L%": 1,
      "ERA": 0,
      "G": 1,
      "GS": 0,
      "CG": 0,
      "SHO": 0,
      "SV": 0,
      "IP": 2.0,
      "H": 2,
      "R": 0,
      "ER": 0,
      "HR": 0,
      "BB": 0,
      "IBB": 0,
      "SO": 2,
      "HBP": 0,
      "BK": 0,
      "WP": 0,
      "WHIP": 1.0,
      "H9": 9.0,
      "HR9": 0.0,
      "BB9": 0.0,
      "SO9": 9.0,
      "SO/BB": 0.0,
      "P/S": NaN,
      "Max": NaN
    },
    {
      "Player": "Ismael Valdez",
      "W": 1,
      "L": 0,
      "W-L%": 1,
      "ERA": 5.142857142857142,
      "G": 1,
      "GS": 1,
      "CG": 0,
      "SHO": 0,
      "SV": 0,
      "IP": 7.0,
      "H": 4,
      "R": 4,
      "ER": 4,
      "HR": 1,
      "BB": 3,
      "IBB": 0,
      "SO": 6,
      "HBP": 1,
      "BK": 0,
      "WP": 0,
      "WHIP": 1.0,
      "H9": 5.142857142857142,
      "HR9": 1.2857142857142856,
      "BB9": 3.8571428571428568,
      "SO9": 7.7142857142857135,
      "SO/BB": 2.0,
      "P/S": 99.0,
      "Max": 124.0
    },
    {
      "Player": "Jeff Williams",
      "W": 0,
      "L": 0,
      "W-L%": 0,
      "ERA": "---",
      "G": 0,
      "GS": 0,
      "CG": 0,
      "SHO": 0,
      "SV": 0,
      "IP": 0.0,
      "H": 0,
      "R": 0,
      "ER": 0,
      "HR": 0,
      "BB": 0,
      "IBB": 0,
      "SO": 0,
      "HBP": 0,
      "BK": 0,
      "WP": 0,
      "WHIP": 0.0,
      "H9": 0.0,
      "HR9": 0.0,
      "BB9": 0.0,
      "SO9": 0.0,
      "SO/BB": 0.0,
      "P/S": 80.0,
      "Max": 85.0
    }
  ],
  "fielding": [
    {
      "Player": "Jamie Arnold",
      "POS": "P",
      "G": 0,
      "GS": 0,
      "INN": 0.0,
      "PO": 0,
      "A": 0,
      "ERR": 0,
      "DP": 0,
      "TP": 0,
      "PB": 0,
      "SB": 0,
      "CS": 0,
      "PkO": 0,
      "PCT": 0.0,
      "CS%": NaN
    },
    {
      "Player": "Doug Bochtler",
      "POS": "P",
      "G": 0,
      "GS": 0,
      "INN": 0.0,
      "PO": 0,
      "A": 0,
      "ERR": 0,
      "DP": 0,
      "TP": 0,
      "PB": 0,
      "SB": 0,
      "CS": 0,
      "PkO": 0,
      "PCT": 0.0,
      "CS%": NaN
    },
    {
      "Player": "Pedro Borbon",
      "POS": "P",
      "G": 2,
      "GS": 0,
      "INN": 1.0,
      "PO": 0,
      "A": 0,
      "ERR": 0,
      "DP": 0,
      "TP": 0,
      "PB": 0,
      "SB": 0,
      "CS": 0,
      "PkO": 0,
      "PCT": 0.0,
      "CS%": NaN
    },
    {
      "Player": "Kevin Brown",
      "POS": "P",
      "G": 1,
      "GS": 1,
      "INN": 7.0,
      "PO": 0,
      "A": 0,
      "ERR": 0,
      "DP": 0,
      "TP": 0,
      "PB": 0,
      "SB": 0,
      "CS": 0,
      "PkO": 0,
      "PCT": 0.0,
      "CS%": NaN
    },
    {
      "Player": "Robinson Checo",
      "POS": "P",
      "G": 0,
      "GS": 0,
      "INN": 0.0,
      "PO": 0,
      "A": 0,
      "ERR": 0,
      "DP": 0,
      "TP": 0,
      "PB": 0,
      "SB": 0,
      "CS": 0,
      "PkO": 0,
      "PCT": 0.0,
      "CS%": NaN
    },
    {
      "Player": "Darren Dreifort",
      "POS": "P",
      "G": 0,
      "GS": 0,
      "INN": 0.0,
      "PO": 0,
      "A": 0,
      "ERR": 0,
      "DP": 0,
      "TP": 0,
      "PB": 0,
      "SB": 0,
      "CS": 0,
      "PkO": 0,
      "PCT": 0.0,
      "CS%": NaN
    },
    {
      "Player": "Eric Gagne",
      "POS": "P",
      "G": 0,
      "GS": 0,
      "INN": 0.0,
      "PO": 0,
      "A": 0,
      "ERR": 0,
      "DP": 0,
      "TP": 0,
      "PB": 0,
      "SB": 0,
      "CS": 0,
      "PkO": 0,
      "PCT": 0.0,
      "CS%": NaN
    },
    {
      "Player": "Matt Herges",
      "POS": "P",
      "G": 0,
      "GS": 0,
      "INN": 0.0,
      "PO": 0,
      "A": 0,
      "ERR": 0,
      "DP": 0,
      "TP": 0,
      "PB": 0,
      "SB": 0,
      "CS": 0,
      "PkO": 0,
      "PCT": 0.0,
      "CS%": NaN
    },
    {
      "Player": "Mike Judd",
      "POS": "P",
      "G": 0,
      "GS": 0,
      "INN": 0.0,
      "PO": 0,
      "A": 0,
      "ERR": 0,
      "DP": 0,
      "TP": 0,
      "PB": 0,
      "SB": 0,
      "CS": 0,
      "PkO": 0,
      "PCT": 0.0,
      "CS%": NaN
    },
    {
      "Player": "Jeff Kubenka",
      "POS": "P",
      "G": 0,
      "GS": 0,
      "INN": 0.0,
      "PO": 0,
      "A": 0,
      "ERR": 0,
      "DP": 0,
      "TP": 0,
      "PB": 0,
      "SB": 0,
      "CS": 0,
      "PkO": 0,
      "PCT": 0.0,
      "CS%": NaN
    },
    {
      "Player": "Mike Maddux",
      "POS": "P",
      "G": 0,
      "GS": 0,
      "INN": 0.0,
      "PO": 0,
      "A": 0,
      "ERR": 0,
      "DP": 0,
      "TP": 0,
      "PB": 0,
      "SB": 0,
      "CS": 0,
      "PkO": 0,
      "PCT": 0.0,
      "CS%": NaN
    },
    {
      "Player": "Onan Masaoka",
      "POS": "P",
      "G": 2,
      "GS": 0,
      "INN": 1.6666666666666665,
      "PO": 0,
      "A": 0,
      "ERR": 0,
      "DP": 0,
      "TP": 0,
      "PB": 0,
      "SB": 0,
      "CS": 0,
      "PkO": 0,
      "PCT": 0.0,
      "CS%": NaN
    },
    {
      "Player": "Alan Mills",
      "POS": "P",
      "G": 2,
      "GS": 0,
      "INN": 2.0,
      "PO": 0,
      "A": 0,
      "ERR": 0,
      "DP": 0,
      "TP": 0,
      "PB": 0,
      "SB": 0,
      "CS": 0,
      "PkO": 0,
      "PCT": 0.0,
      "CS%": NaN
    },
    {
      "Player": "Dave Mlicki",
      "POS": "P",
      "G": 2,
      "GS": 0,
      "INN": 1.0,
      "PO": 1,
      "A": 0,
      "ERR": 0,
      "DP": 0,
      "TP": 0,
      "PB": 0,
      "SB": 0,
      "CS": 0,
      "PkO": 0,
      "PCT": 1.0,
      "CS%": NaN
    },
    {
      "Player": "Antonio Osuna",
      "POS": "P",
      "G": 0,
      "GS": 0,
      "INN": 0.0,
      "PO": 0,
      "A": 0,
      "ERR": 0,
      "DP": 0,
      "TP": 0,
      "PB": 0,
      "SB": 0,
      "CS": 0,
      "PkO": 0,
      "PCT": 0.0,
      "CS%": NaN
    },
    {
      "Player": "Chan Ho Park",
      "POS": "P",
      "G": 1,
      "GS": 1,
      "INN": 5.0,
      "PO": 1,
      "A": 2,
      "ERR": 0,
      "DP": 0,
      "TP": 0,
      "PB": 0,
      "SB": 1,
      "CS": 0,
      "PkO": 0,
      "PCT": 1.0,
      "CS%": NaN
    },
    {
      "Player": "Carlos Perez",
      "POS": "P",
      "G": 0,
      "GS": 0,
      "INN": 0.0,
      "PO": 0,
      "A": 0,
      "ERR": 0,
      "DP": 0,
      "TP": 0,
      "PB": 0,
      "SB": 0,
      "CS": 0,
      "PkO": 0,
      "PCT": 0.0,
      "CS%": NaN
    },
    {
      "Player": "Mel Rojas",
      "POS": "P",
      "G": 2,
      "GS": 0,
      "INN": 1.3333333333333333,
      "PO": 0,
      "A": 0,
      "ERR": 0,
      "DP": 0,
      "TP": 0,
      "PB": 0,
      "SB": 0,
      "CS": 0,
      "PkO": 0,
      "PCT": 0.0,
      "CS%": NaN
    },
    {
      "Player": "Jeff Shaw",
      "POS": "P",
      "G": 1,
      "GS": 0,
      "INN": 2.0,
      "PO": 0,
      "A": 0,
      "ERR": 0,
      "DP": 0,
      "TP": 0,
      "PB": 0,
      "SB": 0,
      "CS": 0,
      "PkO": 0,
      "PCT": 0.0,
      "CS%": NaN
    },
    {
      "Player": "Ismael Valdez",
      "POS": "P",
      "G": 1,
      "GS": 1,
      "INN": 7.0,
      "PO": 0,
      "A": 0,
      "ERR": 0,
      "DP": 0,
      "TP": 0,
      "PB": 0,
      "SB": 0,
      "CS": 1,
      "PkO": 0,
      "PCT": 0.0,
      "CS%": NaN
    },
    {
      "Player": "Jeff Williams",
      "POS": "P",
      "G": 0,
      "GS": 0,
      "INN": 0.0,
      "PO": 0,
      "A": 0,
      "ERR": 0,
      "DP": 0,
      "TP": 0,
      "PB": 0,
      "SB": 0,
      "CS": 0,
      "PkO": 0,
      "PCT": 0.0,
      "CS%": NaN
    },
    {
      "Player": "Trent Hubbard",
      "POS": "C",
      "G": 0,
      "GS": 0,
      "INN": 0.0,
      "PO": 0,
      "A": 0,
      "ERR": 0,
      "DP": 0,
      "TP": 0,
      "PB": 0,
      "SB": 0,
      "CS": 0,
      "PkO": 0,
      "PCT": 0.0,
      "CS%": 0.0
    },
    {
      "Player": "Todd Hundley",
      "POS": "C",
      "G": 3,
      "GS": 3,
      "INN": 26.0,
      "PO": 21,
      "A": 1,
      "ERR": 0,
      "DP": 0,
      "TP": 0,
      "PB": 0,
      "SB": 1,
      "CS": 1,
      "PkO": 0,
      "PCT": 1.0,
      "CS%": 0.5
    },
    {
      "Player": "Paul Lo Duca",
      "POS": "C",
      "G": 1,
      "GS": 0,
      "INN": 2.0,
      "PO": 0,
      "A": 1,
      "ERR": 0,
      "DP": 0,
      "TP": 0,
      "PB": 0,
      "SB": 0,
      "CS": 0,
      "PkO": 0,
      "PCT": 1.0,
      "CS%": 0.0
    },
    {
      "Player": "Angel Pena",
      "POS": "C",
      "G": 0,
      "GS": 0,
      "INN": 0.0,
      "PO": 0,
      "A": 0,
      "ERR": 0,
      "DP": 0,
      "TP": 0,
      "PB": 0,
      "SB": 0,
      "CS": 0,
      "PkO": 0,
      "PCT": 0.0,
      "CS%": 0.0
    },
    {
      "Player": "Rick Wilkins",
      "POS": "C",
      "G": 0,
      "GS": 0,
      "INN": 0.0,
      "PO": 0,
      "A": 0,
      "ERR": 0,
      "DP": 0,
      "TP": 0,
      "PB": 0,
      "SB": 0,
      "CS": 0,
      "PkO": 0,
      "PCT": 0.0,
      "CS%": 0.0
    },
    {
      "Player": "Tripp Cromer",
      "POS": "1B",
      "G": 0,
      "GS": 0,
      "INN": 0.0,
      "PO": 0,
      "A": 0,
      "ERR": 0,
      "DP": 0,
      "TP": 0,
      "PB": 0,
      "SB": 0,
      "CS": 0,
      "PkO": 0,
      "PCT": 0.0,
      "CS%": NaN
    },
    {
      "Player": "Dave Hansen",
      "POS": "1B",
      "G": 0,
      "GS": 0,
      "INN": 0.0,
      "PO": 0,
      "A": 0,
      "ERR": 0,
      "DP": 0,
      "TP": 0,
      "PB": 0,
      "SB": 0,
      "CS": 0,
      "PkO": 0,
      "PCT": 0.0,
      "CS%": NaN
    },
    {
      "Player": "Todd Hollandsworth",
      "POS": "1B",
      "G": 0,
      "GS": 0,
      "INN": 0.0,
      "PO": 0,
      "A": 0,
      "ERR": 0,
      "DP": 0,
      "TP": 0,
      "PB": 0,
      "SB": 0,
      "CS": 0,
      "PkO": 0,
      "PCT": 0.0,
      "CS%": NaN
    },
    {
      "Player": "Eric Karros",
      "POS": "1B",
      "G": 3,
      "GS": 3,
      "INN": 28.0,
      "PO": 26,
      "A": 1,
      "ERR": 0,
      "DP": 1,
      "TP": 0,
      "PB": 0,
      "SB": 0,
      "CS": 0,
      "PkO": 0,
      "PCT": 1.0,
      "CS%": NaN
    },
    {
      "Player": "Juan Castro",
      "POS": "2B",
      "G": 0,
      "GS": 0,
      "INN": 0.0,
      "PO": 0,
      "A": 0,
      "ERR": 0,
      "DP": 0,
      "TP": 0,
      "PB": 0,
      "SB": 0,
      "CS": 0,
      "PkO": 0,
      "PCT": 0.0,
      "CS%": NaN
    },
    {
      "Player": "Alex Cora",
      "POS": "2B",
      "G": 0,
      "GS": 0,
      "INN": 0.0,
      "PO": 0,
      "A": 0,
      "ERR": 0,
      "DP": 0,
      "TP": 0,
      "PB": 0,
      "SB": 0,
      "CS": 0,
      "PkO": 0,
      "PCT": 0.0,
      "CS%": NaN
    },
    {
      "Player": "Craig Counsell",
      "POS": "2B",
      "G": 0,
      "GS": 0,
      "INN": 0.0,
      "PO": 0,
      "A": 0,
      "ERR": 0,
      "DP": 0,
      "TP": 0,
      "PB": 0,
      "SB": 0,
      "CS": 0,
      "PkO": 0,
      "PCT": 0.0,
      "CS%": NaN
    },
    {
      "Player": "Tripp Cromer",
      "POS": "2B",
      "G": 0,
      "GS": 0,
      "INN": 0.0,
      "PO": 0,
      "A": 0,
      "ERR": 0,
      "DP": 0,
      "TP": 0,
      "PB": 0,
      "SB": 0,
      "CS": 0,
      "PkO": 0,
      "PCT": 0.0,
      "CS%": NaN
    },
    {
      "Player": "Trent Hubbard",
      "POS": "2B",
      "G": 0,
      "GS": 0,
      "INN": 0.0,
      "PO": 0,
      "A": 0,
      "ERR": 0,
      "DP": 0,
      "TP": 0,
      "PB": 0,
      "SB": 0,
      "CS": 0,
      "PkO": 0,
      "PCT": 0.0,
      "CS%": NaN
    },
    {
      "Player": "Chance Sanford",
      "POS": "2B",
      "G": 0,
      "GS": 0,
      "INN": 0.0,
      "PO": 0,
      "A": 0,
      "ERR": 0,
      "DP": 0,
      "TP": 0,
      "PB": 0,
      "SB": 0,
      "CS": 0,
      "PkO": 0,
      "PCT": 0.0,
      "CS%": NaN
    },
    {
      "Player": "Jose Vizcaino",
      "POS": "2B",
      "G": 1,
      "GS": 0,
      "INN": 2.0,
      "PO": 1,
      "A": 0,
      "ERR": 0,
      "DP": 0,
      "TP": 0,
      "PB": 0,
      "SB": 0,
      "CS": 0,
      "PkO": 0,
      "PCT": 1.0,
      "CS%": NaN
    },
    {
      "Player": "Eric Young",
      "POS": "2B",
      "G": 3,
      "GS": 3,
      "INN": 26.0,
      "PO": 4,
      "A": 9,
      "ERR": 1,
      "DP": 1,
      "TP": 0,
      "PB": 0,
      "SB": 0,
      "CS": 0,
      "PkO": 0,
      "PCT": 0.9285714285714286,
      "CS%": NaN
    },
    {
      "Player": "Adrian Beltre",
      "POS": "3B",
      "G": 3,
      "GS": 3,
      "INN": 26.333333333333332,
      "PO": 4,
      "A": 3,
      "ERR": 1,
      "DP": 0,
      "TP": 0,
      "PB": 0,
      "SB": 0,
      "CS": 0,
      "PkO": 0,
      "PCT": 0.875,
      "CS%": NaN
    },
    {
      "Player": "Tripp Cromer",
      "POS": "3B",
      "G": 0,
      "GS": 0,
      "INN": 0.0,
      "PO": 0,
      "A": 0,
      "ERR": 0,
      "DP": 0,
      "TP": 0,
      "PB": 0,
      "SB": 0,
      "CS": 0,
      "PkO": 0,
      "PCT": 0.0,
      "CS%": NaN
    },
    {
      "Player": "Dave Hansen",
      "POS": "3B",
      "G": 0,
      "GS": 0,
      "INN": 0.0,
      "PO": 0,
      "A": 0,
      "ERR": 0,
      "DP": 0,
      "TP": 0,
      "PB": 0,
      "SB": 0,
      "CS": 0,
      "PkO": 0,
      "PCT": 0.0,
      "CS%": NaN
    },
    {
      "Player": "Jose Vizcaino",
      "POS": "3B",
      "G": 1,
      "GS": 0,
      "INN": 1.6666666666666665,
      "PO": 1,
      "A": 1,
      "ERR": 0,
      "DP": 0,
      "TP": 0,
      "PB": 0,
      "SB": 0,
      "CS": 0,
      "PkO": 0,
      "PCT": 1.0,
      "CS%": NaN
    },
    {
      "Player": "Juan Castro",
      "POS": "SS",
      "G": 0,
      "GS": 0,
      "INN": 0.0,
      "PO": 0,
      "A": 0,
      "ERR": 0,
      "DP": 0,
      "TP": 0,
      "PB": 0,
      "SB": 0,
      "CS": 0,
      "PkO": 0,
      "PCT": 0.0,
      "CS%": NaN
    },
    {
      "Player": "Alex Cora",
      "POS": "SS",
      "G": 0,
      "GS": 0,
      "INN": 0.0,
      "PO": 0,
      "A": 0,
      "ERR": 0,
      "DP": 0,
      "TP": 0,
      "PB": 0,
      "SB": 0,
      "CS": 0,
      "PkO": 0,
      "PCT": 0.0,
      "CS%": NaN
    },
    {
      "Player": "Craig Counsell",
      "POS": "SS",
      "G": 0,
      "GS": 0,
      "INN": 0.0,
      "PO": 0,
      "A": 0,
      "ERR": 0,
      "DP": 0,
      "TP": 0,
      "PB": 0,
      "SB": 0,
      "CS": 0,
      "PkO": 0,
      "PCT": 0.0,
      "CS%": NaN
    },
    {
      "Player": "Tripp Cromer",
      "POS": "SS",
      "G": 0,
      "GS": 0,
      "INN": 0.0,
      "PO": 0,
      "A": 0,
      "ERR": 0,
      "DP": 0,
      "TP": 0,
      "PB": 0,
      "SB": 0,
      "CS": 0,
      "PkO": 0,
      "PCT": 0.0,
      "CS%": NaN
    },
    {
      "Player": "Mark Grudzielanek",
      "POS": "SS",
      "G": 3,
      "GS": 3,
      "INN": 28.0,
      "PO": 6,
      "A": 7,
      "ERR": 1,
      "DP": 1,
      "TP": 0,
      "PB": 0,
      "SB": 0,
      "CS": 0,
      "PkO": 0,
      "PCT": 0.9285714285714286,
      "CS%": NaN
    },
    {
      "Player": "Jose Vizcaino",
      "POS": "SS",
      "G": 0,
      "GS": 0,
      "INN": 0.0,
      "PO": 0,
      "A": 0,
      "ERR": 0,
      "DP": 0,
      "TP": 0,
      "PB": 0,
      "SB": 0,
      "CS": 0,
      "PkO": 0,
      "PCT": 0.0,
      "CS%": NaN
    },
    {
      "Player": "Jacob Brumfield",
      "POS": "LF",
      "G": 0,
      "GS": 0,
      "INN": 0.0,
      "PO": 0,
      "A": 0,
      "ERR": 0,
      "DP": 0,
      "TP": 0,
      "PB": 0,
      "SB": 0,
      "CS": 0,
      "PkO": 0,
      "PCT": 0.0,
      "CS%": NaN
    },
    {
      "Player": "Brent Cookson",
      "POS": "LF",
      "G": 0,
      "GS": 0,
      "INN": 0.0,
      "PO": 0,
      "A": 0,
      "ERR": 0,
      "DP": 0,
      "TP": 0,
      "PB": 0,
      "SB": 0,
      "CS": 0,
      "PkO": 0,
      "PCT": 0.0,
      "CS%": NaN
    },
    {
      "Player": "Tripp Cromer",
      "POS": "LF",
      "G": 0,
      "GS": 0,
      "INN": 0.0,
      "PO": 0,
      "A": 0,
      "ERR": 0,
      "DP": 0,
      "TP": 0,
      "PB": 0,
      "SB": 0,
      "CS": 0,
      "PkO": 0,
      "PCT": 0.0,
      "CS%": NaN
    },
    {
      "Player": "Todd Hollandsworth",
      "POS": "LF",
      "G": 0,
      "GS": 0,
      "INN": 0.0,
      "PO": 0,
      "A": 0,
      "ERR": 0,
      "DP": 0,
      "TP": 0,
      "PB": 0,
      "SB": 0,
      "CS": 0,
      "PkO": 0,
      "PCT": 0.0,
      "CS%": NaN
    },
    {
      "Player": "Trent Hubbard",
      "POS": "LF",
      "G": 0,
      "GS": 0,
      "INN": 0.0,
      "PO": 0,
      "A": 0,
      "ERR": 0,
      "DP": 0,
      "TP": 0,
      "PB": 0,
      "SB": 0,
      "CS": 0,
      "PkO": 0,
      "PCT": 0.0,
      "CS%": NaN
    },
    {
      "Player": "Gary Sheffield",
      "POS": "LF",
      "G": 3,
      "GS": 3,
      "INN": 28.0,
      "PO": 4,
      "A": 0,
      "ERR": 1,
      "DP": 0,
      "TP": 0,
      "PB": 0,
      "SB": 0,
      "CS": 0,
      "PkO": 0,
      "PCT": 0.8,
      "CS%": NaN
    },
    {
      "Player": "Jose Vizcaino",
      "POS": "LF",
      "G": 0,
      "GS": 0,
      "INN": 0.0,
      "PO": 0,
      "A": 0,
      "ERR": 0,
      "DP": 0,
      "TP": 0,
      "PB": 0,
      "SB": 0,
      "CS": 0,
      "PkO": 0,
      "PCT": 0.0,
      "CS%": NaN
    },
    {
      "Player": "Jacob Brumfield",
      "POS": "CF",
      "G": 0,
      "GS": 0,
      "INN": 0.0,
      "PO": 0,
      "A": 0,
      "ERR": 0,
      "DP": 0,
      "TP": 0,
      "PB": 0,
      "SB": 0,
      "CS": 0,
      "PkO": 0,
      "PCT": 0.0,
      "CS%": NaN
    },
    {
      "Player": "Todd Hollandsworth",
      "POS": "CF",
      "G": 0,
      "GS": 0,
      "INN": 0.0,
      "PO": 0,
      "A": 0,
      "ERR": 0,
      "DP": 0,
      "TP": 0,
      "PB": 0,
      "SB": 0,
      "CS": 0,
      "PkO": 0,
      "PCT": 0.0,
      "CS%": NaN
    },
    {
      "Player": "Trent Hubbard",
      "POS": "CF",
      "G": 0,
      "GS": 0,
      "INN": 0.0,
      "PO": 0,
      "A": 0,
      "ERR": 0,
      "DP": 0,
      "TP": 0,
      "PB": 0,
      "SB": 0,
      "CS": 0,
      "PkO": 0,
      "PCT": 0.0,
      "CS%": NaN
    },
    {
      "Player": "Raul Mondesi",
      "POS": "CF",
      "G": 0,
      "GS": 0,
      "INN": 0.0,
      "PO": 0,
      "A": 0,
      "ERR": 0,
      "DP": 0,
      "TP": 0,
      "PB": 0,
      "SB": 0,
      "CS": 0,
      "PkO": 0,
      "PCT": 0.0,
      "CS%": NaN
    },
    {
      "Player": "Devon White",
      "POS": "CF",
      "G": 3,
      "GS": 3,
      "INN": 28.0,
      "PO": 6,
      "A": 0,
      "ERR": 0,
      "DP": 0,
      "TP": 0,
      "PB": 0,
      "SB": 0,
      "CS": 0,
      "PkO": 0,
      "PCT": 1.0,
      "CS%": NaN
    },
    {
      "Player": "Brent Cookson",
      "POS": "RF",
      "G": 0,
      "GS": 0,
      "INN": 0.0,
      "PO": 0,
      "A": 0,
      "ERR": 0,
      "DP": 0,
      "TP": 0,
      "PB": 0,
      "SB": 0,
      "CS": 0,
      "PkO": 0,
      "PCT": 0.0,
      "CS%": NaN
    },
    {
      "Player": "Tripp Cromer",
      "POS": "RF",
      "G": 0,
      "GS": 0,
      "INN": 0.0,
      "PO": 0,
      "A": 0,
      "ERR": 0,
      "DP": 0,
      "TP": 0,
      "PB": 0,
      "SB": 0,
      "CS": 0,
      "PkO": 0,
      "PCT": 0.0,
      "CS%": NaN
    },
    {
      "Player": "Dave Hansen",
      "POS": "RF",
      "G": 0,
      "GS": 0,
      "INN": 0.0,
      "PO": 0,
      "A": 0,
      "ERR": 0,
      "DP": 0,
      "TP": 0,
      "PB": 0,
      "SB": 0,
      "CS": 0,
      "PkO": 0,
      "PCT": 0.0,
      "CS%": NaN
    },
    {
      "Player": "Todd Hollandsworth",
      "POS": "RF",
      "G": 0,
      "GS": 0,
      "INN": 0.0,
      "PO": 0,
      "A": 0,
      "ERR": 0,
      "DP": 0,
      "TP": 0,
      "PB": 0,
      "SB": 0,
      "CS": 0,
      "PkO": 0,
      "PCT": 0.0,
      "CS%": NaN
    },
    {
      "Player": "Trent Hubbard",
      "POS": "RF",
      "G": 0,
      "GS": 0,
      "INN": 0.0,
      "PO": 0,
      "A": 0,
      "ERR": 0,
      "DP": 0,
      "TP": 0,
      "PB": 0,
      "SB": 0,
      "CS": 0,
      "PkO": 0,
      "PCT": 0.0,
      "CS%": NaN
    },
    {
      "Player": "Raul Mondesi",
      "POS": "RF",
      "G": 3,
      "GS": 3,
      "INN": 28.0,
      "PO": 9,
      "A": 0,
      "ERR": 0,
      "DP": 0,
      "TP": 0,
      "PB": 0,
      "SB": 0,
      "CS": 0,
      "PkO": 0,
      "PCT": 1.0,
      "CS%": NaN
    }
  ]
}