{
  "batting": [
    {
      "Player": "Ivan Rodriguez",
      "G": 3,
      "PA": 14,
      "AB": 14,
      "R": 1,
      "H": 6,
      "2B": 1,
      "3B": 0,
      "HR": 1,
      "RBI": 6,
      "SB": 0,
      "CS": 0,
      "BB": 0,
      "SO": 1,
      "GIDP": 1,
      "HBP": 0,
      "SH": 0,
      "SF": 0,
      "IBB": 0,
      "Current Streak": 3,
      "Longest Streak": 3,
      "BA": 0.42857142857142855,
      "OBP": 0.42857142857142855,
      "SLG": 0.7142857142857143,
      "OPS": 1.1428571428571428,
      "TB": 10
    },
    {
      "Player": "Lee Stevens",
      "G": 3,
      "PA": 13,
      "AB": 13,
      "R": 4,
      "H": 6,
      "2B": 1,
      "3B": 0,
      "HR": 2,
      "RBI": 3,
      "SB": 0,
      "CS": 0,
      "BB": 0,
      "SO": 5,
      "GIDP": 0,
      "HBP": 0,
      "SH": 0,
      "SF": 0,
      "IBB": 0,
      "Current Streak": 2,
      "Longest Streak": 2,
      "BA": 0.46153846153846156,
      "OBP": 0.46153846153846156,
      "SLG": 1.0,
      "OPS": 1.4615384615384617,
      "TB": 13
    },
    {
      "Player": "Mark McLemore",
      "G": 0,
      "PA": 0,
      "AB": 0,
      "R": 0,
      "H": 0,
      "2B": 0,
      "3B": 0,
      "HR": 0,
      "RBI": 0,
      "SB": 0,
      "CS": 0,
      "BB": 0,
      "SO": 0,
      "GIDP": 0,
      "HBP": 0,
      "SH": 0,
      "SF": 0,
      "IBB": 0,
      "Current Streak": 0,
      "Longest Streak": 0,
      "BA": 0.0,
      "OBP": 0.0,
      "SLG": 0.0,
      "OPS": 0.0,
      "TB": 0
    },
    {
      "Player": "Todd Zeile",
      "G": 3,
      "PA": 13,
      "AB": 10,
      "R": 6,
      "H": 4,
      "2B": 1,
      "3B": 0,
      "HR": 0,
      "RBI": 0,
      "SB": 0,
      "CS": 0,
      "BB": 2,
      "SO": 0,
      "GIDP": 0,
      "HBP": 1,
      "SH": 0,
      "SF": 0,
      "IBB": 0,
      "Current Streak": 1,
      "Longest Streak": 1,
      "BA": 0.4,
      "OBP": 0.5384615384615384,
      "SLG": 0.5,
      "OPS": 1.0384615384615383,
      "TB": 5
    },
    {
      "Player": "Royce Clayton",
      "G": 3,
      "PA": 12,
      "AB": 11,
      "R": 2,
      "H": 5,
      "2B": 2,
      "3B": 0,
      "HR": 0,
      "RBI": 3,
      "SB": 0,
      "CS": 0,
      "BB": 1,
      "SO": 2,
      "GIDP": 0,
      "HBP": 0,
      "SH": 0,
      "SF": 0,
      "IBB": 0,
      "Current Streak": 3,
      "Longest Streak": 3,
      "BA": 0.45454545454545453,
      "OBP": 0.5,
      "SLG": 0.6363636363636364,
      "OPS": 1.1363636363636362,
      "TB": 7
    },
    {
      "Player": "Rusty Greer",
      "G": 3,
      "PA": 14,
      "AB": 14,
      "R": 4,
      "H": 4,
      "2B": 2,
      "3B": 0,
      "HR": 1,
      "RBI": 2,
      "SB": 0,
      "CS": 0,
      "BB": 0,
      "SO": 1,
      "GIDP": 1,
      "HBP": 0,
      "SH": 0,
      "SF": 0,
      "IBB": 0,
      "Current Streak": 2,
      "Longest Streak": 2,
      "BA": 0.2857142857142857,
      "OBP": 0.2857142857142857,
      "SLG": 0.6428571428571429,
      "OPS": 0.9285714285714286,
      "TB": 9
    },
    {
      "Player": "Tom Goodwin",
      "G": 2,
      "PA": 11,
      "AB": 11,
      "R": 4,
      "H": 6,
      "2B": 0,
      "3B": 0,
      "HR": 0,
      "RBI": 4,
      "SB": 1,
      "CS": 1,
      "BB": 0,
      "SO": 0,
      "GIDP": 0,
      "HBP": 0,
      "SH": 0,
      "SF": 0,
      "IBB": 0,
      "Current Streak": 2,
      "Longest Streak": 2,
      "BA": 0.5454545454545454,
      "OBP": 0.5454545454545454,
      "SLG": 0.5454545454545454,
      "OPS": 1.0909090909090908,
      "TB": 6
    },
    {
      "Player": "Juan Gonzalez",
      "G": 3,
      "PA": 13,
      "AB": 13,
      "R": 3,
      "H": 4,
      "2B": 1,
      "3B": 0,
      "HR": 1,
      "RBI": 2,
      "SB": 0,
      "CS": 0,
      "BB": 0,
      "SO": 2,
      "GIDP": 0,
      "HBP": 0,
      "SH": 0,
      "SF": 0,
      "IBB": 0,
      "Current Streak": 3,
      "Longest Streak": 3,
      "BA": 0.3076923076923077,
      "OBP": 0.3076923076923077,
      "SLG": 0.6153846153846154,
      "OPS": 0.9230769230769231,
      "TB": 8
    },
    {
      "Player": "Rafael Palmeiro",
      "G": 3,
      "PA": 13,
      "AB": 13,
      "R": 4,
      "H": 5,
      "2B": 2,
      "3B": 0,
      "HR": 2,
      "RBI": 6,
      "SB": 0,
      "CS": 0,
      "BB": 0,
      "SO": 2,
      "GIDP": 0,
      "HBP": 0,
      "SH": 0,
      "SF": 0,
      "IBB": 0,
      "Current Streak": 3,
      "Longest Streak": 3,
      "BA": 0.38461538461538464,
      "OBP": 0.38461538461538464,
      "SLG": 1.0,
      "OPS": 1.3846153846153846,
      "TB": 13
    },
    {
      "Player": "Roberto Kelly",
      "G": 1,
      "PA": 4,
      "AB": 3,
      "R": 1,
      "H": 1,
      "2B": 0,
      "3B": 0,
      "HR": 0,
      "RBI": 0,
      "SB": 0,
      "CS": 0,
      "BB": 1,
      "SO": 0,
      "GIDP": 0,
      "HBP": 0,
      "SH": 0,
      "SF": 0,
      "IBB": 0,
      "Current Streak": 1,
      "Longest Streak": 1,
      "BA": 0.3333333333333333,
      "OBP": 0.5,
      "SLG": 0.3333333333333333,
      "OPS": 0.8333333333333333,
      "TB": 1
    },
    {
      "Player": "Luis Alicea",
      "G": 3,
      "PA": 13,
      "AB": 11,
      "R": 4,
      "H": 4,
      "2B": 1,
      "3B": 0,
      "HR": 1,
      "RBI": 3,
      "SB": 0,
      "CS": 0,
      "BB": 2,
      "SO": 1,
      "GIDP": 0,
      "HBP": 0,
      "SH": 0,
      "SF": 0,
      "IBB": 0,
      "Current Streak": 3,
      "Longest Streak": 3,
      "BA": 0.36363636363636365,
      "OBP": 0.46153846153846156,
      "SLG": 0.7272727272727273,
      "OPS": 1.1888111888111887,
      "TB": 8
    },
    {
      "Player": "Ruben Mateo",
      "G": 0,
      "PA": 0,
      "AB": 0,
      "R": 0,
      "H": 0,
      "2B": 0,
      "3B": 0,
      "HR": 0,
      "RBI": 0,
      "SB": 0,
      "CS": 0,
      "BB": 0,
      "SO": 0,
      "GIDP": 0,
      "HBP": 0,
      "SH": 0,
      "SF": 0,
      "IBB": 0,
      "Current Streak": 0,
      "Longest Streak": 0,
      "BA": 0.0,
      "OBP": 0.0,
      "SLG": 0.0,
      "OPS": 0.0,
      "TB": 0
    },
    {
      "Player": "Gregg Zaun",
      "G": 1,
      "PA": 1,
      "AB": 1,
      "R": 0,
      "H": 0,
      "2B": 0,
      "3B": 0,
      "HR": 0,
      "RBI": 0,
      "SB": 0,
      "CS": 0,
      "BB": 0,
      "SO": 0,
      "GIDP": 0,
      "HBP": 0,
      "SH": 0,
      "SF": 0,
      "IBB": 0,
      "Current Streak": 0,
      "Longest Streak": 0,
      "BA": 0.0,
      "OBP": 0.0,
      "SLG": 0.0,
      "OPS": 0.0,
      "TB": 0
    },
    {
      "Player": "Jon Shave",
      "G": 1,
      "PA": 2,
      "AB": 2,
      "R": 1,
      "H": 1,
      "2B": 0,
      "3B": 0,
      "HR": 0,
      "RBI": 0,
      "SB": 0,
      "CS": 0,
      "BB": 0,
      "SO": 1,
      "GIDP": 0,
      "HBP": 0,
      "SH": 0,
      "SF": 0,
      "IBB": 0,
      "Current Streak": 0,
      "Longest Streak": 0,
      "BA": 0.5,
      "OBP": 0.5,
      "SLG": 0.5,
      "OPS": 1.0,
      "TB": 1
    },
    {
      "Player": "Kelly Dransfeldt",
      "G": 0,
      "PA": 0,
      "AB": 0,
      "R": 0,
      "H": 0,
      "2B": 0,
      "3B": 0,
      "HR": 0,
      "RBI": 0,
      "SB": 0,
      "CS": 0,
      "BB": 0,
      "SO": 0,
      "GIDP": 0,
      "HBP": 0,
      "SH": 0,
      "SF": 0,
      "IBB": 0,
      "Current Streak": 0,
      "Longest Streak": 0,
      "BA": 0.0,
      "OBP": 0.0,
      "SLG": 0.0,
      "OPS": 0.0,
      "TB": 0
    },
    {
      "Player": "Scarborough Green",
      "G": 0,
      "PA": 0,
      "AB": 0,
      "R": 0,
      "H": 0,
      "2B": 0,
      "3B": 0,
      "HR": 0,
      "RBI": 0,
      "SB": 0,
      "CS": 0,
      "BB": 0,
      "SO": 0,
      "GIDP": 0,
      "HBP": 0,
      "SH": 0,
      "SF": 0,
      "IBB": 0,
      "Current Streak": 0,
      "Longest Streak": 0,
      "BA": 0.0,
      "OBP": 0.0,
      "SLG": 0.0,
      "OPS": 0.0,
      "TB": 0
    },
    {
      "Player": "Mike Simms",
      "G": 0,
      "PA": 0,
      "AB": 0,
      "R": 0,
      "H": 0,
      "2B": 0,
      "3B": 0,
      "HR": 0,
      "RBI": 0,
      "SB": 0,
      "CS": 0,
      "BB": 0,
      "SO": 0,
      "GIDP": 0,
      "HBP": 0,
      "SH": 0,
      "SF": 0,
      "IBB": 0,
      "Current Streak": 0,
      "Longest Streak": 0,
      "BA": 0.0,
      "OBP": 0.0,
      "SLG": 0.0,
      "OPS": 0.0,
      "TB": 0
    },
    {
      "Player": "Scott Sheldon",
      "G": 0,
      "PA": 0,
      "AB": 0,
      "R": 0,
      "H": 0,
      "2B": 0,
      "3B": 0,
      "HR": 0,
      "RBI": 0,
      "SB": 0,
      "CS": 0,
      "BB": 0,
      "SO": 0,
      "GIDP": 0,
      "HBP": 0,
      "SH": 0,
      "SF": 0,
      "IBB": 0,
      "Current Streak": 0,
      "Longest Streak": 0,
      "BA": 0.0,
      "OBP": 0.0,
      "SLG": 0.0,
      "OPS": 0.0,
      "TB": 0
    },
    {
      "Player": "Aaron Sele",
      "G": 1,
      "PA": 0,
      "AB": 0,
      "R": 0,
      "H": 0,
      "2B": 0,
      "3B": 0,
      "HR": 0,
      "RBI": 0,
      "SB": 0,
      "CS": 0,
      "BB": 0,
      "SO": 0,
      "GIDP": 0,
      "HBP": 0,
      "SH": 0,
      "SF": 0,
      "IBB": 0,
      "Current Streak": 0,
      "Longest Streak": 0,
      "BA": 0.0,
      "OBP": 0.0,
      "SLG": 0.0,
      "OPS": 0.0,
      "TB": 0
    },
    {
      "Player": "Mike Morgan",
      "G": 1,
      "PA": 0,
      "AB": 0,
      "R": 0,
      "H": 0,
      "2B": 0,
      "3B": 0,
      "HR": 0,
      "RBI": 0,
      "SB": 0,
      "CS": 0,
      "BB": 0,
      "SO": 0,
      "GIDP": 0,
      "HBP": 0,
      "SH": 0,
      "SF": 0,
      "IBB": 0,
      "Current Streak": 0,
      "Longest Streak": 0,
      "BA": 0.0,
      "OBP": 0.0,
      "SLG": 0.0,
      "OPS": 0.0,
      "TB": 0
    },
    {
      "Player": "Rick Helling",
      "G": 1,
      "PA": 0,
      "AB": 0,
      "R": 0,
      "H": 0,
      "2B": 0,
      "3B": 0,
      "HR": 0,
      "RBI": 0,
      "SB": 0,
      "CS": 0,
      "BB": 0,
      "SO": 0,
      "GIDP": 0,
      "HBP": 0,
      "SH": 0,
      "SF": 0,
      "IBB": 0,
      "Current Streak": 0,
      "Longest Streak": 0,
      "BA": 0.0,
      "OBP": 0.0,
      "SLG": 0.0,
      "OPS": 0.0,
      "TB": 0
    },
    {
      "Player": "John Burkett",
      "G": 0,
      "PA": 0,
      "AB": 0,
      "R": 0,
      "H": 0,
      "2B": 0,
      "3B": 0,
      "HR": 0,
      "RBI": 0,
      "SB": 0,
      "CS": 0,
      "BB": 0,
      "SO": 0,
      "GIDP": 0,
      "HBP": 0,
      "SH": 0,
      "SF": 0,
      "IBB": 0,
      "Current Streak": 0,
      "Longest Streak": 0,
      "BA": 0.0,
      "OBP": 0.0,
      "SLG": 0.0,
      "OPS": 0.0,
      "TB": 0
    },
    {
      "Player": "Mark Clark",
      "G": 1,
      "PA": 0,
      "AB": 0,
      "R": 0,
      "H": 0,
      "2B": 0,
      "3B": 0,
      "HR": 0,
      "RBI": 0,
      "SB": 0,
      "CS": 0,
      "BB": 0,
      "SO": 0,
      "GIDP": 0,
      "HBP": 0,
      "SH": 0,
      "SF": 0,
      "IBB": 0,
      "Current Streak": 0,
      "Longest Streak": 0,
      "BA": 0.0,
      "OBP": 0.0,
      "SLG": 0.0,
      "OPS": 0.0,
      "TB": 0
    },
    {
      "Player": "Danny Patterson",
      "G": 1,
      "PA": 0,
      "AB": 0,
      "R": 0,
      "H": 0,
      "2B": 0,
      "3B": 0,
      "HR": 0,
      "RBI": 0,
      "SB": 0,
      "CS": 0,
      "BB": 0,
      "SO": 0,
      "GIDP": 0,
      "HBP": 0,
      "SH": 0,
      "SF": 0,
      "IBB": 0,
      "Current Streak": 0,
      "Longest Streak": 0,
      "BA": 0.0,
      "OBP": 0.0,
      "SLG": 0.0,
      "OPS": 0.0,
      "TB": 0
    },
    {
      "Player": "Ryan Glynn",
      "G": 0,
      "PA": 0,
      "AB": 0,
      "R": 0,
      "H": 0,
      "2B": 0,
      "3B": 0,
      "HR": 0,
      "RBI": 0,
      "SB": 0,
      "CS": 0,
      "BB": 0,
      "SO": 0,
      "GIDP": 0,
      "HBP": 0,
      "SH": 0,
      "SF": 0,
      "IBB": 0,
      "Current Streak": 0,
      "Longest Streak": 0,
      "BA": 0.0,
      "OBP": 0.0,
      "SLG": 0.0,
      "OPS": 0.0,
      "TB": 0
    }
  ],
  "pitching": [
    {
      "Player": "Rick Helling",
      "W": 1,
      "L": 0,
      "W-L%": 1,
      "ERA": 1,
      "G": 1,
      "GS": 1,
      "CG": 1,
      "SHO": 0,
      "SV": 0,
      "IP": 9.0,
      "H": 5,
      "R": 1,
      "ER": 1,
      "HR": 0,
      "BB": 0,
      "IBB": 0,
      "SO": 10,
      "HBP": 0,
      "BK": 0,
      "WP": 0,
      "WHIP": 0.5555555555555556,
      "H9": 5.0,
      "HR9": 0.0,
      "BB9": 0.0,
      "SO9": 10.0,
      "SO/BB": 0.0,
      "P/S": null,
      "Max": null
    },
    {
      "Player": "Aaron Sele",
      "W": 1,
      "L": 0,
      "W-L%": 1,
      "ERA": 4.5,
      "G": 1,
      "GS": 1,
      "CG": 0,
      "SHO": 0,
      "SV": 0,
      "IP": 6.0,
      "H": 6,
      "R": 5,
      "ER": 3,
      "HR": 4,
      "BB": 2,
      "IBB": 0,
      "SO": 6,
      "HBP": 0,
      "BK": 0,
      "WP": 1,
      "WHIP": 1.3333333333333333,
      "H9": 9.0,
      "HR9": 6.0,
      "BB9": 3.0,
      "SO9": 9.0,
      "SO/BB": 3.0,
      "P/S": null,
      "Max": null
    },
    {
      "Player": "John Burkett",
      "W": 0,
      "L": 0,
      "W-L%": 0,
      "ERA": "---",
      "G": 0,
      "GS": 0,
      "CG": 0,
      "SHO": 0,
      "SV": 0,
      "IP": 0.0,
      "H": 0,
      "R": 0,
      "ER": 0,
      "HR": 0,
      "BB": 0,
      "IBB": 0,
      "SO": 0,
      "HBP": 0,
      "BK": 0,
      "WP": 0,
      "WHIP": 0.0,
      "H9": 0.0,
      "HR9": 0.0,
      "BB9": 0.0,
      "SO9": 0.0,
      "SO/BB": 0.0,
      "P/S": null,
      "Max": null
    },
    {
      "Player": "Mike Morgan",
      "W": 0,
      "L": 0,
      "W-L%": 0,
      "ERA": 0,
      "G": 1,
      "GS": 0,
      "CG": 0,
      "SHO": 0,
      "SV": 0,
      "IP": 2.0,
      "H": 1,
      "R": 0,
      "ER": 0,
      "HR": 0,
      "BB": 0,
      "IBB": 0,
      "SO": 1,
      "HBP": 0,
      "BK": 0,
      "WP": 0,
      "WHIP": 0.5,
      "H9": 4.5,
      "HR9": 0.0,
      "BB9": 0.0,
      "SO9": 4.5,
      "SO/BB": 0.0,
      "P/S": null,
      "Max": null
    },
    {
      "Player": "Esteban Loaiza",
      "W": 0,
      "L": 0,
      "W-L%": 0,
      "ERA": 0,
      "G": 1,
      "GS": 0,
      "CG": 0,
      "SHO": 0,
      "SV": 0,
      "IP": 1.3333333333333333,
      "H": 1,
      "R": 0,
      "ER": 0,
      "HR": 0,
      "BB": 2,
      "IBB": 0,
      "SO": 3,
      "HBP": 0,
      "BK": 0,
      "WP": 0,
      "WHIP": 2.25,
      "H9": 6.75,
      "HR9": 0.0,
      "BB9": 13.5,
      "SO9": 20.25,
      "SO/BB": 1.5,
      "P/S": null,
      "Max": null
    },
    {
      "Player": "Jeff Zimmerman",
      "W": 0,
      "L": 0,
      "W-L%": 0,
      "ERA": "---",
      "G": 0,
      "GS": 0,
      "CG": 0,
      "SHO": 0,
      "SV": 0,
      "IP": 0.0,
      "H": 0,
      "R": 0,
      "ER": 0,
      "HR": 0,
      "BB": 0,
      "IBB": 0,
      "SO": 0,
      "HBP": 0,
      "BK": 0,
      "WP": 0,
      "WHIP": 0.0,
      "H9": 0.0,
      "HR9": 0.0,
      "BB9": 0.0,
      "SO9": 0.0,
      "SO/BB": 0.0,
      "P/S": null,
      "Max": null
    },
    {
      "Player": "Mark Clark",
      "W": 1,
      "L": 0,
      "W-L%": 1,
      "ERA": 7.7142857142857135,
      "G": 1,
      "GS": 1,
      "CG": 0,
      "SHO": 0,
      "SV": 0,
      "IP": 7.0,
      "H": 9,
      "R": 7,
      "ER": 6,
      "HR": 2,
      "BB": 0,
      "IBB": 0,
      "SO": 4,
      "HBP": 1,
      "BK": 0,
      "WP": 2,
      "WHIP": 1.2857142857142858,
      "H9": 11.571428571428573,
      "HR9": 2.571428571428571,
      "BB9": 0.0,
      "SO9": 5.142857142857142,
      "SO/BB": 0.0,
      "P/S": null,
      "Max": null
    },
    {
      "Player": "Mike Venafro",
      "W": 0,
      "L": 0,
      "W-L%": 0,
      "ERA": "---",
      "G": 0,
      "GS": 0,
      "CG": 0,
      "SHO": 0,
      "SV": 0,
      "IP": 0.0,
      "H": 0,
      "R": 0,
      "ER": 0,
      "HR": 0,
      "BB": 0,
      "IBB": 0,
      "SO": 0,
      "HBP": 0,
      "BK": 0,
      "WP": 0,
      "WHIP": 0.0,
      "H9": 0.0,
      "HR9": 0.0,
      "BB9": 0.0,
      "SO9": 0.0,
      "SO/BB": 0.0,
      "P/S": null,
      "Max": null
    },
    {
      "Player": "John Wetteland",
      "W": 0,
      "L": 0,
      "W-L%": 0,
      "ERA": 0,
      "G": 1,
      "GS": 0,
      "CG": 0,
      "SHO": 0,
      "SV": 1,
      "IP": 0.6666666666666666,
      "H": 0,
      "R": 0,
      "ER": 0,
      "HR": 0,
      "BB": 0,
      "IBB": 0,
      "SO": 2,
      "HBP": 0,
      "BK": 0,
      "WP": 0,
      "WHIP": 0.0,
      "H9": 0.0,
      "HR9": 0.0,
      "BB9": 0.0,
      "SO9": 27.0,
      "SO/BB": 0.0,
      "P/S": null,
      "Max": null
    },
    {
      "Player": "Tim Crabtree",
      "W": 0,
      "L": 0,
      "W-L%": 0,
      "ERA": 0,
      "G": 1,
      "GS": 0,
      "CG": 0,
      "SHO": 0,
      "SV": 0,
      "IP": 0.6666666666666666,
      "H": 0,
      "R": 0,
      "ER": 0,
      "HR": 0,
      "BB": 0,
      "IBB": 0,
      "SO": 0,
      "HBP": 0,
      "BK": 0,
      "WP": 0,
      "WHIP": 0.0,
      "H9": 0.0,
      "HR9": 0.0,
      "BB9": 0.0,
      "SO9": 0.0,
      "SO/BB": 0.0,
      "P/S": null,
      "Max": null
    },
    {
      "Player": "Danny Patterson",
      "W": 0,
      "L": 0,
      "W-L%": 0,
      "ERA": 27,
      "G": 1,
      "GS": 0,
      "CG": 0,
      "SHO": 0,
      "SV": 0,
      "IP": 0.3333333333333333,
      "H": 1,
      "R": 1,
      "ER": 1,
      "HR": 0,
      "BB": 3,
      "IBB": 0,
      "SO": 0,
      "HBP": 0,
      "BK": 0,
      "WP": 0,
      "WHIP": 12.0,
      "H9": 27.0,
      "HR9": 0.0,
      "BB9": 81.0,
      "SO9": 0.0,
      "SO/BB": 0.0,
      "P/S": null,
      "Max": null
    },
    {
      "Player": "Ryan Glynn",
      "W": 0,
      "L": 0,
      "W-L%": 0,
      "ERA": "---",
      "G": 0,
      "GS": 0,
      "CG": 0,
      "SHO": 0,
      "SV": 0,
      "IP": 0.0,
      "H": 0,
      "R": 0,
      "ER": 0,
      "HR": 0,
      "BB": 0,
      "IBB": 0,
      "SO": 0,
      "HBP": 0,
      "BK": 0,
      "WP": 0,
      "WHIP": 0.0,
      "H9": 0.0,
      "HR9": 0.0,
      "BB9": 0.0,
      "SO9": 0.0,
      "SO/BB": 0.0,
      "P/S": null,
      "Max": null
    },
    {
      "Player": "Mike Munoz",
      "W": 0,
      "L": 0,
      "W-L%": 0,
      "ERA": "---",
      "G": 0,
      "GS": 0,
      "CG": 0,
      "SHO": 0,
      "SV": 0,
      "IP": 0.0,
      "H": 0,
      "R": 0,
      "ER": 0,
      "HR": 0,
      "BB": 0,
      "IBB": 0,
      "SO": 0,
      "HBP": 0,
      "BK": 0,
      "WP": 0,
      "WHIP": 0.0,
      "H9": 0.0,
      "HR9": 0.0,
      "BB9": 0.0,
      "SO9": 0.0,
      "SO/BB": 0.0,
      "P/S": null,
      "Max": null
    },
    {
      "Player": "Danny Kolb",
      "W": 0,
      "L": 0,
      "W-L%": 0,
      "ERA": "---",
      "G": 0,
      "GS": 0,
      "CG": 0,
      "SHO": 0,
      "SV": 0,
      "IP": 0.0,
      "H": 0,
      "R": 0,
      "ER": 0,
      "HR": 0,
      "BB": 0,
      "IBB": 0,
      "SO": 0,
      "HBP": 0,
      "BK": 0,
      "WP": 0,
      "WHIP": 0.0,
      "H9": 0.0,
      "HR9": 0.0,
      "BB9": 0.0,
      "SO9": 0.0,
      "SO/BB": 0.0,
      "P/S": null,
      "Max": null
    },
    {
      "Player": "Jeff Fassero",
      "W": 0,
      "L": 0,
      "W-L%": 0,
      "ERA": "---",
      "G": 0,
      "GS": 0,
      "CG": 0,
      "SHO": 0,
      "SV": 0,
      "IP": 0.0,
      "H": 0,
      "R": 0,
      "ER": 0,
      "HR": 0,
      "BB": 0,
      "IBB": 0,
      "SO": 0,
      "HBP": 0,
      "BK": 0,
      "WP": 0,
      "WHIP": 0.0,
      "H9": 0.0,
      "HR9": 0.0,
      "BB9": 0.0,
      "SO9": 0.0,
      "SO/BB": 0.0,
      "P/S": null,
      "Max": null
    },
    {
      "Player": "Matt Perisho",
      "W": 0,
      "L": 0,
      "W-L%": 0,
      "ERA": "---",
      "G": 0,
      "GS": 0,
      "CG": 0,
      "SHO": 0,
      "SV": 0,
      "IP": 0.0,
      "H": 0,
      "R": 0,
      "ER": 0,
      "HR": 0,
      "BB": 0,
      "IBB": 0,
      "SO": 0,
      "HBP": 0,
      "BK": 0,
      "WP": 0,
      "WHIP": 0.0,
      "H9": 0.0,
      "HR9": 0.0,
      "BB9": 0.0,
      "SO9": 0.0,
      "SO/BB": 0.0,
      "P/S": null,
      "Max": null
    },
    {
      "Player": "Eric Gunderson",
      "W": 0,
      "L": 0,
      "W-L%": 0,
      "ERA": "---",
      "G": 0,
      "GS": 0,
      "CG": 0,
      "SHO": 0,
      "SV": 0,
      "IP": 0.0,
      "H": 0,
      "R": 0,
      "ER": 0,
      "HR": 0,
      "BB": 0,
      "IBB": 0,
      "SO": 0,
      "HBP": 0,
      "BK": 0,
      "WP": 0,
      "WHIP": 0.0,
      "H9": 0.0,
      "HR9": 0.0,
      "BB9": 0.0,
      "SO9": 0.0,
      "SO/BB": 0.0,
      "P/S": null,
      "Max": null
    },
    {
      "Player": "Jonathan Johnson",
      "W": 0,
      "L": 0,
      "W-L%": 0,
      "ERA": "---",
      "G": 0,
      "GS": 0,
      "CG": 0,
      "SHO": 0,
      "SV": 0,
      "IP": 0.0,
      "H": 0,
      "R": 0,
      "ER": 0,
      "HR": 0,
      "BB": 0,
      "IBB": 0,
      "SO": 0,
      "HBP": 0,
      "BK": 0,
      "WP": 0,
      "WHIP": 0.0,
      "H9": 0.0,
      "HR9": 0.0,
      "BB9": 0.0,
      "SO9": 0.0,
      "SO/BB": 0.0,
      "P/S": null,
      "Max": null
    },
    {
      "Player": "Doug Davis",
      "W": 0,
      "L": 0,
      "W-L%": 0,
      "ERA": "---",
      "G": 0,
      "GS": 0,
      "CG": 0,
      "SHO": 0,
      "SV": 0,
      "IP": 0.0,
      "H": 0,
      "R": 0,
      "ER": 0,
      "HR": 0,
      "BB": 0,
      "IBB": 0,
      "SO": 0,
      "HBP": 0,
      "BK": 0,
      "WP": 0,
      "WHIP": 0.0,
      "H9": 0.0,
      "HR9": 0.0,
      "BB9": 0.0,
      "SO9": 0.0,
      "SO/BB": 0.0,
      "P/S": null,
      "Max": null
    },
    {
      "Player": "Corey Lee",
      "W": 0,
      "L": 0,
      "W-L%": 0,
      "ERA": "---",
      "G": 0,
      "GS": 0,
      "CG": 0,
      "SHO": 0,
      "SV": 0,
      "IP": 0.0,
      "H": 0,
      "R": 0,
      "ER": 0,
      "HR": 0,
      "BB": 0,
      "IBB": 0,
      "SO": 0,
      "HBP": 0,
      "BK": 0,
      "WP": 0,
      "WHIP": 0.0,
      "H9": 0.0,
      "HR9": 0.0,
      "BB9": 0.0,
      "SO9": 0.0,
      "SO/BB": 0.0,
      "P/S": null,
      "Max": null
    }
  ],
  "fielding": [
    {
      "Player": "John Burkett",
      "POS": "P",
      "G": 0,
      "GS": 0,
      "INN": 0.0,
      "PO": 0,
      "A": 0,
      "ERR": 0,
      "DP": 0,
      "TP": 0,
      "PB": 0,
      "SB": 0,
      "CS": 0,
      "PkO": 0,
      "PCT": 0.0,
      "CS%": null
    },
    {
      "Player": "Mark Clark",
      "POS": "P",
      "G": 1,
      "GS": 1,
      "INN": 7.0,
      "PO": 0,
      "A": 4,
      "ERR": 1,
      "DP": 0,
      "TP": 0,
      "PB": 0,
      "SB": 0,
      "CS": 0,
      "PkO": 0,
      "PCT": 0.8,
      "CS%": null
    },
    {
      "Player": "Tim Crabtree",
      "POS": "P",
      "G": 1,
      "GS": 0,
      "INN": 0.6666666666666666,
      "PO": 0,
      "A": 0,
      "ERR": 0,
      "DP": 0,
      "TP": 0,
      "PB": 0,
      "SB": 0,
      "CS": 0,
      "PkO": 0,
      "PCT": 0.0,
      "CS%": null
    },
    {
      "Player": "Doug Davis",
      "POS": "P",
      "G": 0,
      "GS": 0,
      "INN": 0.0,
      "PO": 0,
      "A": 0,
      "ERR": 0,
      "DP": 0,
      "TP": 0,
      "PB": 0,
      "SB": 0,
      "CS": 0,
      "PkO": 0,
      "PCT": 0.0,
      "CS%": null
    },
    {
      "Player": "Jeff Fassero",
      "POS": "P",
      "G": 0,
      "GS": 0,
      "INN": 0.0,
      "PO": 0,
      "A": 0,
      "ERR": 0,
      "DP": 0,
      "TP": 0,
      "PB": 0,
      "SB": 0,
      "CS": 0,
      "PkO": 0,
      "PCT": 0.0,
      "CS%": null
    },
    {
      "Player": "Ryan Glynn",
      "POS": "P",
      "G": 0,
      "GS": 0,
      "INN": 0.0,
      "PO": 0,
      "A": 0,
      "ERR": 0,
      "DP": 0,
      "TP": 0,
      "PB": 0,
      "SB": 0,
      "CS": 0,
      "PkO": 0,
      "PCT": 0.0,
      "CS%": null
    },
    {
      "Player": "Eric Gunderson",
      "POS": "P",
      "G": 0,
      "GS": 0,
      "INN": 0.0,
      "PO": 0,
      "A": 0,
      "ERR": 0,
      "DP": 0,
      "TP": 0,
      "PB": 0,
      "SB": 0,
      "CS": 0,
      "PkO": 0,
      "PCT": 0.0,
      "CS%": null
    },
    {
      "Player": "Rick Helling",
      "POS": "P",
      "G": 1,
      "GS": 1,
      "INN": 9.0,
      "PO": 1,
      "A": 2,
      "ERR": 0,
      "DP": 0,
      "TP": 0,
      "PB": 0,
      "SB": 0,
      "CS": 0,
      "PkO": 0,
      "PCT": 1.0,
      "CS%": null
    },
    {
      "Player": "Jonathan Johnson",
      "POS": "P",
      "G": 0,
      "GS": 0,
      "INN": 0.0,
      "PO": 0,
      "A": 0,
      "ERR": 0,
      "DP": 0,
      "TP": 0,
      "PB": 0,
      "SB": 0,
      "CS": 0,
      "PkO": 0,
      "PCT": 0.0,
      "CS%": null
    },
    {
      "Player": "Danny Kolb",
      "POS": "P",
      "G": 0,
      "GS": 0,
      "INN": 0.0,
      "PO": 0,
      "A": 0,
      "ERR": 0,
      "DP": 0,
      "TP": 0,
      "PB": 0,
      "SB": 0,
      "CS": 0,
      "PkO": 0,
      "PCT": 0.0,
      "CS%": null
    },
    {
      "Player": "Corey Lee",
      "POS": "P",
      "G": 0,
      "GS": 0,
      "INN": 0.0,
      "PO": 0,
      "A": 0,
      "ERR": 0,
      "DP": 0,
      "TP": 0,
      "PB": 0,
      "SB": 0,
      "CS": 0,
      "PkO": 0,
      "PCT": 0.0,
      "CS%": null
    },
    {
      "Player": "Esteban Loaiza",
      "POS": "P",
      "G": 1,
      "GS": 0,
      "INN": 1.3333333333333333,
      "PO": 0,
      "A": 0,
      "ERR": 0,
      "DP": 0,
      "TP": 0,
      "PB": 0,
      "SB": 0,
      "CS": 0,
      "PkO": 0,
      "PCT": 0.0,
      "CS%": null
    },
    {
      "Player": "Mike Morgan",
      "POS": "P",
      "G": 1,
      "GS": 0,
      "INN": 2.0,
      "PO": 0,
      "A": 0,
      "ERR": 0,
      "DP": 0,
      "TP": 0,
      "PB": 0,
      "SB": 0,
      "CS": 0,
      "PkO": 0,
      "PCT": 0.0,
      "CS%": null
    },
    {
      "Player": "Mike Munoz",
      "POS": "P",
      "G": 0,
      "GS": 0,
      "INN": 0.0,
      "PO": 0,
      "A": 0,
      "ERR": 0,
      "DP": 0,
      "TP": 0,
      "PB": 0,
      "SB": 0,
      "CS": 0,
      "PkO": 0,
      "PCT": 0.0,
      "CS%": null
    },
    {
      "Player": "Danny Patterson",
      "POS": "P",
      "G": 1,
      "GS": 0,
      "INN": 0.3333333333333333,
      "PO": 0,
      "A": 0,
      "ERR": 0,
      "DP": 0,
      "TP": 0,
      "PB": 0,
      "SB": 0,
      "CS": 0,
      "PkO": 0,
      "PCT": 0.0,
      "CS%": null
    },
    {
      "Player": "Matt Perisho",
      "POS": "P",
      "G": 0,
      "GS": 0,
      "INN": 0.0,
      "PO": 0,
      "A": 0,
      "ERR": 0,
      "DP": 0,
      "TP": 0,
      "PB": 0,
      "SB": 0,
      "CS": 0,
      "PkO": 0,
      "PCT": 0.0,
      "CS%": null
    },
    {
      "Player": "Aaron Sele",
      "POS": "P",
      "G": 1,
      "GS": 1,
      "INN": 6.0,
      "PO": 0,
      "A": 1,
      "ERR": 1,
      "DP": 0,
      "TP": 0,
      "PB": 0,
      "SB": 0,
      "CS": 0,
      "PkO": 0,
      "PCT": 0.5,
      "CS%": null
    },
    {
      "Player": "Mike Venafro",
      "POS": "P",
      "G": 0,
      "GS": 0,
      "INN": 0.0,
      "PO": 0,
      "A": 0,
      "ERR": 0,
      "DP": 0,
      "TP": 0,
      "PB": 0,
      "SB": 0,
      "CS": 0,
      "PkO": 0,
      "PCT": 0.0,
      "CS%": null
    },
    {
      "Player": "John Wetteland",
      "POS": "P",
      "G": 1,
      "GS": 0,
      "INN": 0.6666666666666666,
      "PO": 0,
      "A": 0,
      "ERR": 0,
      "DP": 0,
      "TP": 0,
      "PB": 0,
      "SB": 0,
      "CS": 0,
      "PkO": 0,
      "PCT": 0.0,
      "CS%": null
    },
    {
      "Player": "Jeff Zimmerman",
      "POS": "P",
      "G": 0,
      "GS": 0,
      "INN": 0.0,
      "PO": 0,
      "A": 0,
      "ERR": 0,
      "DP": 0,
      "TP": 0,
      "PB": 0,
      "SB": 0,
      "CS": 0,
      "PkO": 0,
      "PCT": 0.0,
      "CS%": null
    },
    {
      "Player": "Ivan Rodriguez",
      "POS": "C",
      "G": 3,
      "GS": 3,
      "INN": 24.0,
      "PO": 26,
      "A": 1,
      "ERR": 1,
      "DP": 0,
      "TP": 0,
      "PB": 0,
      "SB": 0,
      "CS": 0,
      "PkO": 0,
      "PCT": 0.9642857142857143,
      "CS%": 0.0
    },
    {
      "Player": "Gregg Zaun",
      "POS": "C",
      "G": 1,
      "GS": 0,
      "INN": 3.0,
      "PO": 2,
      "A": 0,
      "ERR": 0,
      "DP": 0,
      "TP": 0,
      "PB": 0,
      "SB": 0,
      "CS": 0,
      "PkO": 0,
      "PCT": 1.0,
      "CS%": 0.0
    },
    {
      "Player": "Rafael Palmeiro",
      "POS": "1B",
      "G": 0,
      "GS": 0,
      "INN": 0.0,
      "PO": 0,
      "A": 0,
      "ERR": 0,
      "DP": 0,
      "TP": 0,
      "PB": 0,
      "SB": 0,
      "CS": 0,
      "PkO": 0,
      "PCT": 0.0,
      "CS%": null
    },
    {
      "Player": "Jon Shave",
      "POS": "1B",
      "G": 0,
      "GS": 0,
      "INN": 0.0,
      "PO": 0,
      "A": 0,
      "ERR": 0,
      "DP": 0,
      "TP": 0,
      "PB": 0,
      "SB": 0,
      "CS": 0,
      "PkO": 0,
      "PCT": 0.0,
      "CS%": null
    },
    {
      "Player": "Mike Simms",
      "POS": "1B",
      "G": 0,
      "GS": 0,
      "INN": 0.0,
      "PO": 0,
      "A": 0,
      "ERR": 0,
      "DP": 0,
      "TP": 0,
      "PB": 0,
      "SB": 0,
      "CS": 0,
      "PkO": 0,
      "PCT": 0.0,
      "CS%": null
    },
    {
      "Player": "Lee Stevens",
      "POS": "1B",
      "G": 3,
      "GS": 3,
      "INN": 27.0,
      "PO": 22,
      "A": 1,
      "ERR": 0,
      "DP": 2,
      "TP": 0,
      "PB": 0,
      "SB": 0,
      "CS": 0,
      "PkO": 0,
      "PCT": 1.0,
      "CS%": null
    },
    {
      "Player": "Todd Zeile",
      "POS": "1B",
      "G": 0,
      "GS": 0,
      "INN": 0.0,
      "PO": 0,
      "A": 0,
      "ERR": 0,
      "DP": 0,
      "TP": 0,
      "PB": 0,
      "SB": 0,
      "CS": 0,
      "PkO": 0,
      "PCT": 0.0,
      "CS%": null
    },
    {
      "Player": "Luis Alicea",
      "POS": "2B",
      "G": 3,
      "GS": 3,
      "INN": 27.0,
      "PO": 8,
      "A": 4,
      "ERR": 0,
      "DP": 2,
      "TP": 0,
      "PB": 0,
      "SB": 0,
      "CS": 0,
      "PkO": 0,
      "PCT": 1.0,
      "CS%": null
    },
    {
      "Player": "Mark McLemore",
      "POS": "2B",
      "G": 0,
      "GS": 0,
      "INN": 0.0,
      "PO": 0,
      "A": 0,
      "ERR": 0,
      "DP": 0,
      "TP": 0,
      "PB": 0,
      "SB": 0,
      "CS": 0,
      "PkO": 0,
      "PCT": 0.0,
      "CS%": null
    },
    {
      "Player": "Jon Shave",
      "POS": "2B",
      "G": 0,
      "GS": 0,
      "INN": 0.0,
      "PO": 0,
      "A": 0,
      "ERR": 0,
      "DP": 0,
      "TP": 0,
      "PB": 0,
      "SB": 0,
      "CS": 0,
      "PkO": 0,
      "PCT": 0.0,
      "CS%": null
    },
    {
      "Player": "Luis Alicea",
      "POS": "3B",
      "G": 0,
      "GS": 0,
      "INN": 0.0,
      "PO": 0,
      "A": 0,
      "ERR": 0,
      "DP": 0,
      "TP": 0,
      "PB": 0,
      "SB": 0,
      "CS": 0,
      "PkO": 0,
      "PCT": 0.0,
      "CS%": null
    },
    {
      "Player": "Jon Shave",
      "POS": "3B",
      "G": 0,
      "GS": 0,
      "INN": 0.0,
      "PO": 0,
      "A": 0,
      "ERR": 0,
      "DP": 0,
      "TP": 0,
      "PB": 0,
      "SB": 0,
      "CS": 0,
      "PkO": 0,
      "PCT": 0.0,
      "CS%": null
    },
    {
      "Player": "Scott Sheldon",
      "POS": "3B",
      "G": 0,
      "GS": 0,
      "INN": 0.0,
      "PO": 0,
      "A": 0,
      "ERR": 0,
      "DP": 0,
      "TP": 0,
      "PB": 0,
      "SB": 0,
      "CS": 0,
      "PkO": 0,
      "PCT": 0.0,
      "CS%": null
    },
    {
      "Player": "Todd Zeile",
      "POS": "3B",
      "G": 3,
      "GS": 3,
      "INN": 27.0,
      "PO": 2,
      "A": 1,
      "ERR": 0,
      "DP": 0,
      "TP": 0,
      "PB": 0,
      "SB": 0,
      "CS": 0,
      "PkO": 0,
      "PCT": 1.0,
      "CS%": null
    },
    {
      "Player": "Royce Clayton",
      "POS": "SS",
      "G": 3,
      "GS": 3,
      "INN": 27.0,
      "PO": 3,
      "A": 8,
      "ERR": 1,
      "DP": 2,
      "TP": 0,
      "PB": 0,
      "SB": 0,
      "CS": 0,
      "PkO": 0,
      "PCT": 0.9166666666666666,
      "CS%": null
    },
    {
      "Player": "Kelly Dransfeldt",
      "POS": "SS",
      "G": 0,
      "GS": 0,
      "INN": 0.0,
      "PO": 0,
      "A": 0,
      "ERR": 0,
      "DP": 0,
      "TP": 0,
      "PB": 0,
      "SB": 0,
      "CS": 0,
      "PkO": 0,
      "PCT": 0.0,
      "CS%": null
    },
    {
      "Player": "Jon Shave",
      "POS": "SS",
      "G": 1,
      "GS": 0,
      "INN": 9.0,
      "PO": 0,
      "A": 0,
      "ERR": 0,
      "DP": 0,
      "TP": 0,
      "PB": 0,
      "SB": 0,
      "CS": 0,
      "PkO": 0,
      "PCT": 0.0,
      "CS%": null
    },
    {
      "Player": "Luis Alicea",
      "POS": "LF",
      "G": 0,
      "GS": 0,
      "INN": 0.0,
      "PO": 0,
      "A": 0,
      "ERR": 0,
      "DP": 0,
      "TP": 0,
      "PB": 0,
      "SB": 0,
      "CS": 0,
      "PkO": 0,
      "PCT": 0.0,
      "CS%": null
    },
    {
      "Player": "Scarborough Green",
      "POS": "LF",
      "G": 0,
      "GS": 0,
      "INN": 0.0,
      "PO": 0,
      "A": 0,
      "ERR": 0,
      "DP": 0,
      "TP": 0,
      "PB": 0,
      "SB": 0,
      "CS": 0,
      "PkO": 0,
      "PCT": 0.0,
      "CS%": null
    },
    {
      "Player": "Rusty Greer",
      "POS": "LF",
      "G": 3,
      "GS": 3,
      "INN": 27.0,
      "PO": 4,
      "A": 0,
      "ERR": 0,
      "DP": 0,
      "TP": 0,
      "PB": 0,
      "SB": 0,
      "CS": 0,
      "PkO": 0,
      "PCT": 1.0,
      "CS%": null
    },
    {
      "Player": "Roberto Kelly",
      "POS": "LF",
      "G": 0,
      "GS": 0,
      "INN": 0.0,
      "PO": 0,
      "A": 0,
      "ERR": 0,
      "DP": 0,
      "TP": 0,
      "PB": 0,
      "SB": 0,
      "CS": 0,
      "PkO": 0,
      "PCT": 0.0,
      "CS%": null
    },
    {
      "Player": "Mark McLemore",
      "POS": "LF",
      "G": 0,
      "GS": 0,
      "INN": 0.0,
      "PO": 0,
      "A": 0,
      "ERR": 0,
      "DP": 0,
      "TP": 0,
      "PB": 0,
      "SB": 0,
      "CS": 0,
      "PkO": 0,
      "PCT": 0.0,
      "CS%": null
    },
    {
      "Player": "Tom Goodwin",
      "POS": "CF",
      "G": 2,
      "GS": 2,
      "INN": 18.0,
      "PO": 7,
      "A": 0,
      "ERR": 0,
      "DP": 0,
      "TP": 0,
      "PB": 0,
      "SB": 0,
      "CS": 0,
      "PkO": 0,
      "PCT": 1.0,
      "CS%": null
    },
    {
      "Player": "Scarborough Green",
      "POS": "CF",
      "G": 0,
      "GS": 0,
      "INN": 0.0,
      "PO": 0,
      "A": 0,
      "ERR": 0,
      "DP": 0,
      "TP": 0,
      "PB": 0,
      "SB": 0,
      "CS": 0,
      "PkO": 0,
      "PCT": 0.0,
      "CS%": null
    },
    {
      "Player": "Roberto Kelly",
      "POS": "CF",
      "G": 1,
      "GS": 1,
      "INN": 9.0,
      "PO": 2,
      "A": 0,
      "ERR": 0,
      "DP": 0,
      "TP": 0,
      "PB": 0,
      "SB": 0,
      "CS": 0,
      "PkO": 0,
      "PCT": 1.0,
      "CS%": null
    },
    {
      "Player": "Ruben Mateo",
      "POS": "CF",
      "G": 0,
      "GS": 0,
      "INN": 0.0,
      "PO": 0,
      "A": 0,
      "ERR": 0,
      "DP": 0,
      "TP": 0,
      "PB": 0,
      "SB": 0,
      "CS": 0,
      "PkO": 0,
      "PCT": 0.0,
      "CS%": null
    },
    {
      "Player": "Juan Gonzalez",
      "POS": "RF",
      "G": 3,
      "GS": 3,
      "INN": 27.0,
      "PO": 4,
      "A": 0,
      "ERR": 1,
      "DP": 0,
      "TP": 0,
      "PB": 0,
      "SB": 0,
      "CS": 0,
      "PkO": 0,
      "PCT": 0.8,
      "CS%": null
    },
    {
      "Player": "Scarborough Green",
      "POS": "RF",
      "G": 0,
      "GS": 0,
      "INN": 0.0,
      "PO": 0,
      "A": 0,
      "ERR": 0,
      "DP": 0,
      "TP": 0,
      "PB": 0,
      "SB": 0,
      "CS": 0,
      "PkO": 0,
      "PCT": 0.0,
      "CS%": null
    },
    {
      "Player": "Roberto Kelly",
      "POS": "RF",
      "G": 0,
      "GS": 0,
      "INN": 0.0,
      "PO": 0,
      "A": 0,
      "ERR": 0,
      "DP": 0,
      "TP": 0,
      "PB": 0,
      "SB": 0,
      "CS": 0,
      "PkO": 0,
      "PCT": 0.0,
      "CS%": null
    },
    {
      "Player": "Mark McLemore",
      "POS": "RF",
      "G": 0,
      "GS": 0,
      "INN": 0.0,
      "PO": 0,
      "A": 0,
      "ERR": 0,
      "DP": 0,
      "TP": 0,
      "PB": 0,
      "SB": 0,
      "CS": 0,
      "PkO": 0,
      "PCT": 0.0,
      "CS%": null
    },
    {
      "Player": "Mike Simms",
      "POS": "RF",
      "G": 0,
      "GS": 0,
      "INN": 0.0,
      "PO": 0,
      "A": 0,
      "ERR": 0,
      "DP": 0,
      "TP": 0,
      "PB": 0,
      "SB": 0,
      "CS": 0,
      "PkO": 0,
      "PCT": 0.0,
      "CS%": null
    }
  ]
}