{
  "batting": {
    "CHW": [
      {
        "Player": "Ray Durham",
        "BOP": 1,
        "AB": 3,
        "H": 0,
        "2B": 0,
        "3B": 0,
        "HR": 0,
        "BB": 1,
        "IBB": 0,
        "SO": 0,
        "R": 1,
        "RBI": 0,
        "HBP": 0,
        "SH": 0,
        "SF": 0,
        "GIDP": 0,
        "SB": 0,
        "CS": 0,
        "Removed": null
      },
      {
        "Player": "Mike Caruso",
        "BOP": 2,
        "AB": 4,
        "H": 2,
        "2B": 0,
        "3B": 0,
        "HR": 0,
        "BB": 0,
        "IBB": 0,
        "SO": 2,
        "R": 0,
        "RBI": 0,
        "HBP": 0,
        "SH": 0,
        "SF": 0,
        "GIDP": 0,
        "SB": 1,
        "CS": 1,
        "Removed": null
      },
      {
        "Player": "Frank Thomas",
        "BOP": 3,
        "AB": 3,
        "H": 1,
        "2B": 1,
        "3B": 0,
        "HR": 0,
        "BB": 0,
        "IBB": 0,
        "SO": 0,
        "R": 0,
        "RBI": 1,
        "HBP": 0,
        "SH": 0,
        "SF": 1,
        "GIDP": 0,
        "SB": 0,
        "CS": 0,
        "Removed": null
      },
      {
        "Player": "Jeff Liefer",
        "BOP": 4,
        "AB": 3,
        "H": 0,
        "2B": 0,
        "3B": 0,
        "HR": 0,
        "BB": 0,
        "IBB": 0,
        "SO": 0,
        "R": 0,
        "RBI": 0,
        "HBP": 0,
        "SH": 0,
        "SF": 0,
        "GIDP": 0,
        "SB": 0,
        "CS": 0,
        "Removed": "x"
      },
      {
        "Player": "Craig Wilson",
        "BOP": 4,
        "AB": 1,
        "H": 0,
        "2B": 0,
        "3B": 0,
        "HR": 0,
        "BB": 0,
        "IBB": 0,
        "SO": 0,
        "R": 0,
        "RBI": 0,
        "HBP": 0,
        "SH": 0,
        "SF": 0,
        "GIDP": 0,
        "SB": 0,
        "CS": 0,
        "Removed": null
      },
      {
        "Player": "Magglio Ordonez",
        "BOP": 5,
        "AB": 4,
        "H": 1,
        "2B": 0,
        "3B": 0,
        "HR": 0,
        "BB": 0,
        "IBB": 0,
        "SO": 1,
        "R": 0,
        "RBI": 0,
        "HBP": 0,
        "SH": 0,
        "SF": 0,
        "GIDP": 0,
        "SB": 0,
        "CS": 0,
        "Removed": null
      },
      {
        "Player": "Greg Norton",
        "BOP": 6,
        "AB": 3,
        "H": 1,
        "2B": 0,
        "3B": 0,
        "HR": 1,
        "BB": 0,
        "IBB": 0,
        "SO": 0,
        "R": 1,
        "RBI": 1,
        "HBP": 0,
        "SH": 0,
        "SF": 0,
        "GIDP": 0,
        "SB": 0,
        "CS": 0,
        "Removed": null
      },
      {
        "Player": "Darrin Jackson",
        "BOP": 7,
        "AB": 3,
        "H": 0,
        "2B": 0,
        "3B": 0,
        "HR": 0,
        "BB": 0,
        "IBB": 0,
        "SO": 1,
        "R": 0,
        "RBI": 0,
        "HBP": 0,
        "SH": 0,
        "SF": 0,
        "GIDP": 0,
        "SB": 0,
        "CS": 0,
        "Removed": null
      },
      {
        "Player": "Mark Johnson",
        "BOP": 8,
        "AB": 2,
        "H": 0,
        "2B": 0,
        "3B": 0,
        "HR": 0,
        "BB": 0,
        "IBB": 0,
        "SO": 1,
        "R": 0,
        "RBI": 0,
        "HBP": 0,
        "SH": 0,
        "SF": 0,
        "GIDP": 0,
        "SB": 0,
        "CS": 0,
        "Removed": "x"
      },
      {
        "Player": "Paul Konerko",
        "BOP": 8,
        "AB": 1,
        "H": 0,
        "2B": 0,
        "3B": 0,
        "HR": 0,
        "BB": 0,
        "IBB": 0,
        "SO": 1,
        "R": 0,
        "RBI": 0,
        "HBP": 0,
        "SH": 0,
        "SF": 0,
        "GIDP": 0,
        "SB": 0,
        "CS": 0,
        "Removed": "x"
      },
      {
        "Player": "McKay Christensen",
        "BOP": 9,
        "AB": 2,
        "H": 0,
        "2B": 0,
        "3B": 0,
        "HR": 0,
        "BB": 0,
        "IBB": 0,
        "SO": 0,
        "R": 0,
        "RBI": 0,
        "HBP": 0,
        "SH": 0,
        "SF": 0,
        "GIDP": 0,
        "SB": 0,
        "CS": 0,
        "Removed": "x"
      },
      {
        "Player": "Jeff Abbott",
        "BOP": 9,
        "AB": 1,
        "H": 1,
        "2B": 0,
        "3B": 0,
        "HR": 0,
        "BB": 0,
        "IBB": 0,
        "SO": 0,
        "R": 0,
        "RBI": 0,
        "HBP": 0,
        "SH": 0,
        "SF": 0,
        "GIDP": 0,
        "SB": 0,
        "CS": 0,
        "Removed": null
      }
    ],
    "SEA": [
      {
        "Player": "Carlos Guillen",
        "BOP": 1,
        "AB": 4,
        "H": 1,
        "2B": 0,
        "3B": 0,
        "HR": 0,
        "BB": 1,
        "IBB": 0,
        "SO": 0,
        "R": 2,
        "RBI": 0,
        "HBP": 0,
        "SH": 0,
        "SF": 0,
        "GIDP": 0,
        "SB": 0,
        "CS": 0,
        "Removed": null
      },
      {
        "Player": "David Bell",
        "BOP": 2,
        "AB": 3,
        "H": 0,
        "2B": 0,
        "3B": 0,
        "HR": 0,
        "BB": 1,
        "IBB": 0,
        "SO": 0,
        "R": 0,
        "RBI": 0,
        "HBP": 0,
        "SH": 0,
        "SF": 0,
        "GIDP": 0,
        "SB": 0,
        "CS": 0,
        "Removed": null
      },
      {
        "Player": "Ken Griffey Jr",
        "BOP": 3,
        "AB": 4,
        "H": 3,
        "2B": 1,
        "3B": 0,
        "HR": 1,
        "BB": 0,
        "IBB": 0,
        "SO": 0,
        "R": 0,
        "RBI": 2,
        "HBP": 0,
        "SH": 0,
        "SF": 0,
        "GIDP": 0,
        "SB": 0,
        "CS": 0,
        "Removed": null
      },
      {
        "Player": "Edgar Martinez",
        "BOP": 4,
        "AB": 3,
        "H": 1,
        "2B": 1,
        "3B": 0,
        "HR": 0,
        "BB": 1,
        "IBB": 0,
        "SO": 1,
        "R": 1,
        "RBI": 1,
        "HBP": 0,
        "SH": 0,
        "SF": 0,
        "GIDP": 0,
        "SB": 0,
        "CS": 0,
        "Removed": null
      },
      {
        "Player": "David Segui",
        "BOP": 5,
        "AB": 4,
        "H": 3,
        "2B": 0,
        "3B": 0,
        "HR": 0,
        "BB": 0,
        "IBB": 0,
        "SO": 0,
        "R": 0,
        "RBI": 0,
        "HBP": 0,
        "SH": 0,
        "SF": 0,
        "GIDP": 0,
        "SB": 0,
        "CS": 0,
        "Removed": null
      },
      {
        "Player": "Jay Buhner",
        "BOP": 6,
        "AB": 4,
        "H": 1,
        "2B": 1,
        "3B": 0,
        "HR": 0,
        "BB": 0,
        "IBB": 0,
        "SO": 1,
        "R": 1,
        "RBI": 0,
        "HBP": 0,
        "SH": 0,
        "SF": 0,
        "GIDP": 0,
        "SB": 0,
        "CS": 0,
        "Removed": null
      },
      {
        "Player": "John Mabry",
        "BOP": 7,
        "AB": 4,
        "H": 1,
        "2B": 0,
        "3B": 0,
        "HR": 0,
        "BB": 0,
        "IBB": 0,
        "SO": 0,
        "R": 1,
        "RBI": 0,
        "HBP": 0,
        "SH": 0,
        "SF": 0,
        "GIDP": 0,
        "SB": 0,
        "CS": 0,
        "Removed": null
      },
      {
        "Player": "Russ Davis",
        "BOP": 8,
        "AB": 4,
        "H": 1,
        "2B": 0,
        "3B": 0,
        "HR": 0,
        "BB": 0,
        "IBB": 0,
        "SO": 0,
        "R": 1,
        "RBI": 1,
        "HBP": 0,
        "SH": 0,
        "SF": 0,
        "GIDP": 0,
        "SB": 0,
        "CS": 0,
        "Removed": null
      },
      {
        "Player": "Dan Wilson",
        "BOP": 9,
        "AB": 4,
        "H": 1,
        "2B": 0,
        "3B": 0,
        "HR": 0,
        "BB": 0,
        "IBB": 0,
        "SO": 1,
        "R": 0,
        "RBI": 0,
        "HBP": 0,
        "SH": 0,
        "SF": 0,
        "GIDP": 0,
        "SB": 0,
        "CS": 0,
        "Removed": null
      }
    ]
  },
  "pitching": {
    "CHW": [
      {
        "Player": "John Snyder",
        "IP": 5,
        "ER": 4,
        "H": 9,
        "BB": 2,
        "SO": 1,
        "HR": 0,
        "W": 0,
        "L": 1,
        "SV": 0
      },
      {
        "Player": "Bryan Ward",
        "IP": 1,
        "ER": 2,
        "H": 2,
        "BB": 0,
        "SO": 0,
        "HR": 1,
        "W": 0,
        "L": 0,
        "SV": 0
      },
      {
        "Player": "David Lundquist",
        "IP": 1,
        "ER": 0,
        "H": 1,
        "BB": 1,
        "SO": 2,
        "HR": 0,
        "W": 0,
        "L": 0,
        "SV": 0
      }
    ],
    "SEA": [
      {
        "Player": "Freddy Garcia",
        "IP": 7,
        "ER": 2,
        "H": 5,
        "BB": 1,
        "SO": 3,
        "HR": 1,
        "W": 1,
        "L": 0,
        "SV": 0
      },
      {
        "Player": "John Halama",
        "IP": 2,
        "ER": 0,
        "H": 1,
        "BB": 0,
        "SO": 3,
        "HR": 0,
        "W": 0,
        "L": 0,
        "SV": 0
      }
    ]
  },
  "meta": {
    "date": "",
    "home": "",
    "away": "",
    "home_score": "",
    "away_score": ""
  }
}