{
  "batting": {
    "COL": [
      {
        "Player": "Darryl Hamilton",
        "BOP": 1,
        "AB": 5,
        "H": 0,
        "2B": 0,
        "3B": 0,
        "HR": 0,
        "BB": 0,
        "SO": 2,
        "R": 0,
        "RBI": 0,
        "Removed": NaN
      },
      {
        "Player": "Neifi Perez",
        "BOP": 2,
        "AB": 4,
        "H": 1,
        "2B": 0,
        "3B": 0,
        "HR": 0,
        "BB": 0,
        "SO": 0,
        "R": 1,
        "RBI": 0,
        "Removed": NaN
      },
      {
        "Player": "Lenny Harris",
        "BOP": 3,
        "AB": 4,
        "H": 0,
        "2B": 0,
        "3B": 0,
        "HR": 0,
        "BB": 0,
        "SO": 0,
        "R": 0,
        "RBI": 0,
        "Removed": "x"
      },
      {
        "Player": "Dante Bichette",
        "BOP": 4,
        "AB": 4,
        "H": 1,
        "2B": 0,
        "3B": 0,
        "HR": 1,
        "BB": 0,
        "SO": 0,
        "R": 2,
        "RBI": 2,
        "Removed": NaN
      },
      {
        "Player": "Vinny Castilla",
        "BOP": 5,
        "AB": 4,
        "H": 3,
        "2B": 1,
        "3B": 0,
        "HR": 0,
        "BB": 0,
        "SO": 0,
        "R": 3,
        "RBI": 0,
        "Removed": NaN
      },
      {
        "Player": "Todd Helton",
        "BOP": 6,
        "AB": 4,
        "H": 2,
        "2B": 1,
        "3B": 0,
        "HR": 1,
        "BB": 0,
        "SO": 0,
        "R": 2,
        "RBI": 3,
        "Removed": NaN
      },
      {
        "Player": "Mike Lansing",
        "BOP": 7,
        "AB": 4,
        "H": 0,
        "2B": 0,
        "3B": 0,
        "HR": 0,
        "BB": 0,
        "SO": 0,
        "R": 0,
        "RBI": 0,
        "Removed": NaN
      },
      {
        "Player": "Jeff Reed",
        "BOP": 8,
        "AB": 4,
        "H": 0,
        "2B": 0,
        "3B": 0,
        "HR": 0,
        "BB": 0,
        "SO": 3,
        "R": 1,
        "RBI": 0,
        "Removed": NaN
      },
      {
        "Player": "Jamey Wright",
        "BOP": 9,
        "AB": 3,
        "H": 0,
        "2B": 0,
        "3B": 0,
        "HR": 0,
        "BB": 0,
        "SO": 1,
        "R": 0,
        "RBI": 0,
        "Removed": "x"
      },
      {
        "Player": "Angel Echevarria",
        "BOP": 9,
        "AB": 1,
        "H": 1,
        "2B": 1,
        "3B": 0,
        "HR": 0,
        "BB": 0,
        "SO": 0,
        "R": 0,
        "RBI": 2,
        "Removed": "x"
      }
    ],
    "SDP": [
      {
        "Player": "Quilvio Veras",
        "BOP": 1,
        "AB": 3,
        "H": 0,
        "2B": 0,
        "3B": 0,
        "HR": 0,
        "BB": 2,
        "SO": 1,
        "R": 0,
        "RBI": 0,
        "Removed": NaN
      },
      {
        "Player": "Reggie Sanders",
        "BOP": 2,
        "AB": 3,
        "H": 0,
        "2B": 0,
        "3B": 0,
        "HR": 0,
        "BB": 2,
        "SO": 0,
        "R": 0,
        "RBI": 0,
        "Removed": NaN
      },
      {
        "Player": "Tony Gwynn",
        "BOP": 3,
        "AB": 4,
        "H": 1,
        "2B": 0,
        "3B": 1,
        "HR": 0,
        "BB": 0,
        "SO": 0,
        "R": 1,
        "RBI": 1,
        "Removed": NaN
      },
      {
        "Player": "Wally Joyner",
        "BOP": 4,
        "AB": 2,
        "H": 0,
        "2B": 0,
        "3B": 0,
        "HR": 0,
        "BB": 2,
        "SO": 0,
        "R": 0,
        "RBI": 0,
        "Removed": NaN
      },
      {
        "Player": "John Vander Wal",
        "BOP": 5,
        "AB": 3,
        "H": 0,
        "2B": 0,
        "3B": 0,
        "HR": 0,
        "BB": 0,
        "SO": 1,
        "R": 0,
        "RBI": 0,
        "Removed": "x"
      },
      {
        "Player": "Jim Leyritz",
        "BOP": 5,
        "AB": 1,
        "H": 0,
        "2B": 0,
        "3B": 0,
        "HR": 0,
        "BB": 0,
        "SO": 0,
        "R": 0,
        "RBI": 0,
        "Removed": "x"
      },
      {
        "Player": "Greg Myers",
        "BOP": 6,
        "AB": 3,
        "H": 1,
        "2B": 0,
        "3B": 0,
        "HR": 0,
        "BB": 1,
        "SO": 0,
        "R": 0,
        "RBI": 0,
        "Removed": NaN
      },
      {
        "Player": "George Arias",
        "BOP": 7,
        "AB": 3,
        "H": 1,
        "2B": 0,
        "3B": 0,
        "HR": 0,
        "BB": 0,
        "SO": 1,
        "R": 0,
        "RBI": 0,
        "Removed": "x"
      },
      {
        "Player": "Ruben Rivera",
        "BOP": 7,
        "AB": 1,
        "H": 0,
        "2B": 0,
        "3B": 0,
        "HR": 0,
        "BB": 0,
        "SO": 0,
        "R": 0,
        "RBI": 0,
        "Removed": NaN
      },
      {
        "Player": "Chris Gomez",
        "BOP": 8,
        "AB": 4,
        "H": 1,
        "2B": 0,
        "3B": 0,
        "HR": 0,
        "BB": 0,
        "SO": 0,
        "R": 0,
        "RBI": 0,
        "Removed": NaN
      },
      {
        "Player": "Woody Williams",
        "BOP": 9,
        "AB": 2,
        "H": 0,
        "2B": 0,
        "3B": 0,
        "HR": 0,
        "BB": 0,
        "SO": 0,
        "R": 0,
        "RBI": 0,
        "Removed": "x"
      },
      {
        "Player": "Dave Magadan",
        "BOP": 9,
        "AB": 1,
        "H": 1,
        "2B": 1,
        "3B": 0,
        "HR": 0,
        "BB": 0,
        "SO": 0,
        "R": 1,
        "RBI": 0,
        "Removed": "x"
      },
      {
        "Player": "Carlos Garcia",
        "BOP": 9,
        "AB": 1,
        "H": 1,
        "2B": 0,
        "3B": 0,
        "HR": 0,
        "BB": 0,
        "SO": 0,
        "R": 0,
        "RBI": 0,
        "Removed": NaN
      }
    ]
  },
  "pitching": {
    "COL": [
      {
        "Player": "Jamey Wright",
        "IP": 7,
        "ER": 1,
        "H": 4,
        "BB": 5,
        "SO": 3,
        "HR": 0,
        "W": 1,
        "L": 0,
        "SV": 0
      },
      {
        "Player": "Chuck McElroy",
        "IP": 0,
        "ER": 0,
        "H": 0,
        "BB": 1,
        "SO": 0,
        "HR": 0,
        "W": 0,
        "L": 0,
        "SV": 0
      },
      {
        "Player": "Roberto Ramirez",
        "IP": 0,
        "ER": 0,
        "H": 2,
        "BB": 1,
        "SO": 0,
        "HR": 0,
        "W": 0,
        "L": 0,
        "SV": 0
      },
      {
        "Player": "Jerry Dipoto",
        "IP": 0,
        "ER": 0,
        "H": 0,
        "BB": 0,
        "SO": 0,
        "HR": 0,
        "W": 0,
        "L": 0,
        "SV": 0
      }
    ],
    "SDP": [
      {
        "Player": "Dan Miceli",
        "IP": 1,
        "ER": 0,
        "H": 2,
        "BB": 0,
        "SO": 0,
        "HR": 0,
        "W": 0,
        "L": 0,
        "SV": 0
      },
      {
        "Player": "Brian Boehringer",
        "IP": 1,
        "ER": 0,
        "H": 0,
        "BB": 0,
        "SO": 0,
        "HR": 0,
        "W": 0,
        "L": 0,
        "SV": 0
      },
      {
        "Player": "Woody Williams",
        "IP": 5,
        "ER": 3,
        "H": 5,
        "BB": 0,
        "SO": 4,
        "HR": 1,
        "W": 0,
        "L": 1,
        "SV": 0
      },
      {
        "Player": "Carlos Reyes",
        "IP": 1,
        "ER": 1,
        "H": 1,
        "BB": 0,
        "SO": 2,
        "HR": 1,
        "W": 0,
        "L": 0,
        "SV": 0
      }
    ]
  },
  "meta": {
    "date": "",
    "home": "",
    "away": "",
    "home_score": "",
    "away_score": ""
  }
}