{
  "meta": {
    "date": "1999-04-08 00:00:00",
    "home": "STL",
    "away": "MIL",
    "home_score": "4.0",
    "away_score": "5.0"
  },
  "batting": {
    "MIL": {
      "Fernando Vina": {
        "Player": "Fernando Vina",
        "Player ID": "vinafe01",
        "AB": 6,
        "R": 1,
        "H": 2,
        "2B": 1,
        "PO": 3,
        "A": 7,
        "DP": 1
      },
      "Marquis Grissom": {
        "Player": "Marquis Grissom",
        "Player ID": "grissma02",
        "AB": 6,
        "H": 4,
        "2B": 2,
        "RBI": 2,
        "SO": 2,
        "PO": 3
      },
      "Jeff Cirillo": {
        "Player": "Jeff Cirillo",
        "Player ID": "cirilje01",
        "AB": 4,
        "BB": 2,
        "IBB": 1,
        "A": 4
      },
      "Jeromy Burnitz": {
        "Player": "Jeromy Burnitz",
        "Player ID": "burnije01",
        "AB": 5,
        "SO": 1,
        "PO": 2
      },
      "Sean Berry": {
        "Player": "Sean Berry",
        "Player ID": "berryse01",
        "AB": 5,
        "R": 2,
        "H": 3,
        "2B": 1,
        "3B": 1,
        "PO": 15
      },
      "Mark Loretta": {
        "Player": "Mark Loretta",
        "Player ID": "loretma01",
        "AB": 5,
        "H": 4,
        "2B": 1,
        "RBI": 1,
        "A": 2
      },
      "Bobby Hughes": {
        "Player": "Bobby Hughes",
        "Player ID": "hughebo01",
        "AB": 3,
        "RBI": 1,
        "SO": 1,
        "GDP": 1,
        "SF": 1,
        "PO": 6,
        "A": 1,
        "ERR": 1,
        "CS against": 1
      },
      "Dave Nilsson": {
        "Player": "Dave Nilsson",
        "Player ID": "nilssda01",
        "AB": 1,
        "GDP": 1,
        "PO": 2,
        "SB against": 1
      },
      "Alex Ochoa": {
        "Player": "Alex Ochoa",
        "Player ID": "ochoaal01",
        "AB": 4,
        "R": 1,
        "H": 1,
        "2B": 1,
        "RBI": 1,
        "BB": 1,
        "PO": 2
      },
      "Jim Abbott": {
        "Player": "Jim Abbott",
        "Player ID": "abbotji01",
        "AB": 2,
        "SO": 2,
        "IP": "5.1",
        "H allowed": 2,
        "R against": 2,
        "ER": 2,
        "BB against": 3,
        "SO against": 2,
        "CS against": 1
      },
      "David Weathers": {
        "Player": "David Weathers",
        "Player ID": "weathda01",
        "IP": "0.2",
        "BB against": 1,
        "A": 1
      },
      "Jose Valentin": {
        "Player": "Jose Valentin",
        "Player ID": "valenjo03",
        "AB": 1,
        "SO": 1
      },
      "Mike Myers": {
        "Player": "Mike Myers",
        "Player ID": "myersmi01",
        "IP": "1.0",
        "SO against": 2,
        "A": 1
      },
      "Brian Banks": {
        "Player": "Brian Banks",
        "Player ID": "banksbr01",
        "AB": 1,
        "SO": 1
      },
      "Valerio de los Santos": {
        "Player": "Valerio de los Santos",
        "Player ID": "delosva01",
        "IP": "0.2",
        "H allowed": 1
      },
      "Bob Wickman": {
        "Player": "Bob Wickman",
        "Player ID": "wickmbo01",
        "IP": "1.1",
        "H allowed": 2,
        "R against": 2,
        "ER": 2,
        "HR allowed": 1,
        "BB against": 3,
        "SO against": 2
      },
      "Eric Plunk": {
        "Player": "Eric Plunk",
        "Player ID": "plunker01",
        "SH": 1,
        "W": 1,
        "IP": "2.0",
        "BB against": 2,
        "IBB against": 1,
        "SO against": 2,
        "SB against": 1
      }
    },
    "STL": {
      "Darren Bragg": {
        "Player": "Darren Bragg",
        "Player ID": "braggda01",
        "AB": 3,
        "H": 1,
        "2B": 1,
        "RBI": 1,
        "BB": 1,
        "SH": 1,
        "PO": 2
      },
      "Luis Ordaz": {
        "Player": "Luis Ordaz",
        "Player ID": "ordazlu01",
        "AB": 1,
        "SO": 1,
        "PO": 1
      },
      "Shawon Dunston": {
        "Player": "Shawon Dunston",
        "Player ID": "dunstsh01",
        "AB": 5,
        "H": 1,
        "RBI": 1,
        "SO": 1,
        "PO": 2,
        "A": 4,
        "DP": 1
      },
      "Juan Acevedo": {
        "Player": "Juan Acevedo",
        "Player ID": "aceveju01",
        "L": 1,
        "IP": "2.0",
        "H allowed": 2,
        "R against": 1,
        "ER": 1,
        "BB against": 1,
        "A": 1,
        "DP": 1
      },
      "Mark McGwire": {
        "Player": "Mark McGwire",
        "Player ID": "mcgwima01",
        "AB": 3,
        "RBI": 1,
        "BB": 1,
        "SO": 1,
        "SF": 1,
        "PO": 11,
        "A": 2,
        "DP": 2
      },
      "Eric Davis": {
        "Player": "Eric Davis",
        "Player ID": "daviser01",
        "AB": 4,
        "BB": 1,
        "PO": 1
      },
      "Fernando Tatis": {
        "Player": "Fernando Tatis",
        "Player ID": "tatisfe01",
        "AB": 5,
        "R": 1,
        "H": 1,
        "HR": 1,
        "RBI": 1,
        "SO": 1,
        "A": 2
      },
      "Willie McGee": {
        "Player": "Willie McGee",
        "Player ID": "mcgeewi01",
        "AB": 5,
        "H": 1,
        "SO": 2,
        "CS": 1,
        "PO": 2
      },
      "Alberto Castillo": {
        "Player": "Alberto Castillo",
        "Player ID": "castial01",
        "AB": 5,
        "R": 1,
        "H": 1,
        "SO": 1,
        "PO": 9
      },
      "Joe McEwing": {
        "Player": "Joe McEwing",
        "Player ID": "mcewijo01",
        "AB": 2,
        "R": 1,
        "BB": 1,
        "SO": 1,
        "PO": 2,
        "A": 4,
        "DP": 1
      },
      "J.D. Drew": {
        "Player": "J.D. Drew",
        "Player ID": "drewj.01",
        "BB": 2,
        "SB": 1,
        "PO": 1
      },
      "Kent Mercker": {
        "Player": "Kent Mercker",
        "Player ID": "merckke01",
        "AB": 1,
        "IP": "6.0",
        "H allowed": 8,
        "R against": 2,
        "ER": 2,
        "BB against": 1,
        "SO against": 4,
        "WP": 1,
        "PO": 1,
        "A": 1
      },
      "Placido Polanco": {
        "Player": "Placido Polanco",
        "Player ID": "polanpl01",
        "R": 1,
        "BB": 1
      },
      "Lance Painter": {
        "Player": "Lance Painter",
        "Player ID": "paintla01",
        "IP": "2.0",
        "H allowed": 4,
        "R against": 2,
        "ER": 2,
        "BB against": 1,
        "IBB against": 1,
        "SO against": 3,
        "WP": 1
      },
      "Eli Marrero": {
        "Player": "Eli Marrero",
        "Player ID": "marreel01",
        "AB": 1
      },
      "Manny Aybar": {
        "Player": "Manny Aybar",
        "Player ID": "aybarma01",
        "IP": "1.0",
        "SO against": 1
      },
      "Edgar Renteria": {
        "Player": "Edgar Renteria",
        "Player ID": "renteed01",
        "BB": 2,
        "IBB": 1,
        "PO": 1,
        "A": 1,
        "DP": 1
      }
    }
  },
  "pitching": {
    "MIL": {
      "Jim Abbott": {
        "Player": "Jim Abbott",
        "Player ID": "abbotji01",
        "AB": 2,
        "SO": 2,
        "IP": "5.1",
        "H allowed": 2,
        "R against": 2,
        "ER": 2,
        "BB against": 3,
        "SO against": 2,
        "CS against": 1
      },
      "David Weathers": {
        "Player": "David Weathers",
        "Player ID": "weathda01",
        "IP": "0.2",
        "BB against": 1,
        "A": 1
      },
      "Mike Myers": {
        "Player": "Mike Myers",
        "Player ID": "myersmi01",
        "IP": "1.0",
        "SO against": 2,
        "A": 1
      },
      "Valerio de los Santos": {
        "Player": "Valerio de los Santos",
        "Player ID": "delosva01",
        "IP": "0.2",
        "H allowed": 1
      },
      "Bob Wickman": {
        "Player": "Bob Wickman",
        "Player ID": "wickmbo01",
        "IP": "1.1",
        "H allowed": 2,
        "R against": 2,
        "ER": 2,
        "HR allowed": 1,
        "BB against": 3,
        "SO against": 2
      },
      "Eric Plunk": {
        "Player": "Eric Plunk",
        "Player ID": "plunker01",
        "SH": 1,
        "W": 1,
        "IP": "2.0",
        "BB against": 2,
        "IBB against": 1,
        "SO against": 2,
        "SB against": 1
      }
    },
    "STL": {
      "Juan Acevedo": {
        "Player": "Juan Acevedo",
        "Player ID": "aceveju01",
        "L": 1,
        "IP": "2.0",
        "H allowed": 2,
        "R against": 1,
        "ER": 1,
        "BB against": 1,
        "A": 1,
        "DP": 1
      },
      "Kent Mercker": {
        "Player": "Kent Mercker",
        "Player ID": "merckke01",
        "AB": 1,
        "IP": "6.0",
        "H allowed": 8,
        "R against": 2,
        "ER": 2,
        "BB against": 1,
        "SO against": 4,
        "WP": 1,
        "PO": 1,
        "A": 1
      },
      "Lance Painter": {
        "Player": "Lance Painter",
        "Player ID": "paintla01",
        "IP": "2.0",
        "H allowed": 4,
        "R against": 2,
        "ER": 2,
        "BB against": 1,
        "IBB against": 1,
        "SO against": 3,
        "WP": 1
      },
      "Manny Aybar": {
        "Player": "Manny Aybar",
        "Player ID": "aybarma01",
        "IP": "1.0",
        "SO against": 1
      }
    }
  },
  "batting_order": {
    "MIL": [
      [
        1,
        "Fernando Vina"
      ],
      [
        2,
        "Marquis Grissom"
      ],
      [
        3,
        "Jeff Cirillo"
      ],
      [
        4,
        "Jeromy Burnitz"
      ],
      [
        5,
        "Sean Berry"
      ],
      [
        6,
        "Mark Loretta"
      ],
      [
        7,
        "Bobby Hughes"
      ],
      [
        7,
        "Dave Nilsson"
      ],
      [
        7,
        "Dave Nilsson"
      ],
      [
        8,
        "Alex Ochoa"
      ],
      [
        9,
        "Jim Abbott"
      ],
      [
        9,
        "David Weathers"
      ],
      [
        9,
        "Jose Valentin"
      ],
      [
        9,
        "Mike Myers"
      ],
      [
        9,
        "Brian Banks"
      ],
      [
        9,
        "Valerio de los Santos"
      ],
      [
        9,
        "Bob Wickman"
      ],
      [
        9,
        "Eric Plunk"
      ]
    ],
    "STL": [
      [
        1,
        "Darren Bragg"
      ],
      [
        1,
        "Luis Ordaz"
      ],
      [
        2,
        "Shawon Dunston"
      ],
      [
        2,
        "Juan Acevedo"
      ],
      [
        3,
        "Mark McGwire"
      ],
      [
        4,
        "Eric Davis"
      ],
      [
        5,
        "Fernando Tatis"
      ],
      [
        6,
        "Willie McGee"
      ],
      [
        7,
        "Alberto Castillo"
      ],
      [
        8,
        "Joe McEwing"
      ],
      [
        8,
        "J.D. Drew"
      ],
      [
        8,
        "J.D. Drew"
      ],
      [
        9,
        "Kent Mercker"
      ],
      [
        9,
        "Placido Polanco"
      ],
      [
        9,
        "Lance Painter"
      ],
      [
        9,
        "Eli Marrero"
      ],
      [
        9,
        "Manny Aybar"
      ],
      [
        9,
        "Edgar Renteria"
      ],
      [
        9,
        "Edgar Renteria"
      ]
    ]
  },
  "positions": {
    "MIL": {
      "Fernando Vina": [
        "4"
      ],
      "Marquis Grissom": [
        "8"
      ],
      "Jeff Cirillo": [
        "5"
      ],
      "Jeromy Burnitz": [
        "9"
      ],
      "Sean Berry": [
        "3"
      ],
      "Mark Loretta": [
        "6"
      ],
      "Bobby Hughes": [
        "2"
      ],
      "Dave Nilsson": [
        "2",
        "PH"
      ],
      "Alex Ochoa": [
        "7"
      ],
      "Jim Abbott": [
        "1"
      ],
      "David Weathers": [
        "1"
      ],
      "Jose Valentin": [
        "PH"
      ],
      "Mike Myers": [
        "1"
      ],
      "Brian Banks": [
        "PH"
      ],
      "Valerio de los Santos": [
        "1"
      ],
      "Bob Wickman": [
        "1"
      ],
      "Eric Plunk": [
        "1"
      ]
    },
    "STL": {
      "Darren Bragg": [
        "8"
      ],
      "Luis Ordaz": [
        "4"
      ],
      "Shawon Dunston": [
        "6"
      ],
      "Juan Acevedo": [
        "1"
      ],
      "Mark McGwire": [
        "3"
      ],
      "Eric Davis": [
        "9"
      ],
      "Fernando Tatis": [
        "5"
      ],
      "Willie McGee": [
        "7"
      ],
      "Alberto Castillo": [
        "2"
      ],
      "Joe McEwing": [
        "4"
      ],
      "J.D. Drew": [
        "PH",
        "8"
      ],
      "Kent Mercker": [
        "1"
      ],
      "Placido Polanco": [
        "PH"
      ],
      "Lance Painter": [
        "1"
      ],
      "Eli Marrero": [
        "PH"
      ],
      "Manny Aybar": [
        "1"
      ],
      "Edgar Renteria": [
        "PH",
        "6"
      ]
    }
  },
  "games_started": {
    "MIL": {
      "Fernando Vina": 1,
      "Marquis Grissom": 1,
      "Jeff Cirillo": 1,
      "Jeromy Burnitz": 1,
      "Sean Berry": 1,
      "Mark Loretta": 1,
      "Bobby Hughes": 1,
      "Alex Ochoa": 1,
      "Jim Abbott": 1
    },
    "STL": {
      "Darren Bragg": 1,
      "Shawon Dunston": 1,
      "Mark McGwire": 1,
      "Eric Davis": 1,
      "Fernando Tatis": 1,
      "Willie McGee": 1,
      "Alberto Castillo": 1,
      "Joe McEwing": 1,
      "Kent Mercker": 1
    }
  }
}