{"Darryl Hamilton":[{"game":"19990404_COL@SD", "ab":4, "h":0, "rbi":0, "r":0, "hr":0},{"game":"19990406_COL@SD", "ab":4, "h":1, "rbi":0, "r":1, "hr":0},{"game":"19990407_COL@SD", "ab":5, "h":0, "rbi":0, "r":0, "hr":0}],"Neifi Perez":[{"game":"19990404_COL@SD", "ab":4, "h":1, "rbi":0, "r":0, "hr":0},{"game":"19990406_COL@SD", "ab":5, "h":0, "rbi":0, "r":0, "hr":0},{"game":"19990407_COL@SD", "ab":4, "h":1, "rbi":0, "r":1, "hr":0}],"Lenny Harris":[{"game":"19990404_COL@SD", "ab":4, "h":1, "rbi":0, "r":0, "hr":0},{"game":"19990406_COL@SD", "ab":1, "h":0, "rbi":0, "r":0, "hr":0},{"game":"19990407_COL@SD", "ab":4, "h":0, "rbi":0, "r":0, "hr":0}],"Dante Bichette":[{"game":"19990404_COL@SD", "ab":4, "h":0, "rbi":0, "r":0, "hr":0},{"game":"19990406_COL@SD", "ab":4, "h":2, "rbi":2, "r":1, "hr":0},{"game":"19990407_COL@SD", "ab":4, "h":1, "rbi":2, "r":2, "hr":1}],"Vinny Castilla":[{"game":"19990404_COL@SD", "ab":4, "h":2, "rbi":0, "r":2, "hr":0},{"game":"19990406_COL@SD", "ab":4, "h":2, "rbi":0, "r":0, "hr":0},{"game":"19990407_COL@SD", "ab":4, "h":3, "rbi":0, "r":3, "hr":0}],"Todd Helton":[{"game":"19990404_COL@SD", "ab":3, "h":2, "rbi":1, "r":0, "hr":0},{"game":"19990406_COL@SD", "ab":4, "h":1, "rbi":1, "r":0, "hr":0},{"game":"19990407_COL@SD", "ab":4, "h":2, "rbi":3, "r":2, "hr":1}],"Mike Lansing":[{"game":"19990404_COL@SD", "ab":3, "h":0, "rbi":1, "r":0, "hr":0},{"game":"19990406_COL@SD", "ab":4, "h":0, "rbi":0, "r":0, "hr":0},{"game":"19990407_COL@SD", "ab":4, "h":0, "rbi":0, "r":0, "hr":0}],"Kirt Manwaring":[{"game":"19990404_COL@SD", "ab":1, "h":0, "rbi":0, "r":0, "hr":0},{"game":"19990406_COL@SD", "ab":2, "h":0, "rbi":0, "r":0, "hr":0}],"Darryl Kile":[{"game":"19990404_COL@SD", "ab":2, "h":0, "rbi":0, "r":0, "hr":0}],"Angel Echevarria":[{"game":"19990404_COL@SD", "ab":1, "h":0, "rbi":0, "r":0, "hr":0},{"game":"19990407_COL@SD", "ab":1, "h":1, "rbi":2, "r":0, "hr":0}],"Quilvio Veras":[{"game":"19990404_COL@SD", "ab":3, "h":0, "rbi":0, "r":1, "hr":0},{"game":"19990406_COL@SD", "ab":4, "h":0, "rbi":0, "r":0, "hr":0},{"game":"19990407_COL@SD", "ab":3, "h":0, "rbi":0, "r":0, "hr":0}],"Reggie Sanders":[{"game":"19990404_COL@SD", "ab":4, "h":1, "rbi":1, "r":1, "hr":1},{"game":"19990406_COL@SD", "ab":4, "h":1, "rbi":0, "r":1, "hr":0},{"game":"19990406_COL@SD", "ab":0, "h":0, "rbi":0, "r":0, "hr":0},{"game":"19990407_COL@SD", "ab":3, "h":0, "rbi":0, "r":0, "hr":0},{"game":"19990407_COL@SD", "ab":0, "h":0, "rbi":0, "r":0, "hr":0}],"Tony Gwynn":[{"game":"19990404_COL@SD", "ab":4, "h":0, "rbi":0, "r":0, "hr":0},{"game":"19990406_COL@SD", "ab":4, "h":2, "rbi":1, "r":0, "hr":0},{"game":"19990407_COL@SD", "ab":4, "h":1, "rbi":1, "r":1, "hr":0}],"Wally Joyner":[{"game":"19990404_COL@SD", "ab":3, "h":2, "rbi":0, "r":1, "hr":0},{"game":"19990406_COL@SD", "ab":4, "h":0, "rbi":0, "r":0, "hr":0},{"game":"19990407_COL@SD", "ab":2, "h":0, "rbi":0, "r":0, "hr":0}],"Greg Myers":[{"game":"19990404_COL@SD", "ab":4, "h":1, "rbi":0, "r":1, "hr":0},{"game":"19990407_COL@SD", "ab":3, "h":1, "rbi":0, "r":0, "hr":0}],"George Arias":[{"game":"19990404_COL@SD", "ab":4, "h":0, "rbi":0, "r":0, "hr":0},{"game":"19990406_COL@SD", "ab":2, "h":0, "rbi":0, "r":0, "hr":0},{"game":"19990407_COL@SD", "ab":3, "h":1, "rbi":0, "r":0, "hr":0}],"Ruben Rivera":[{"game":"19990404_COL@SD", "ab":4, "h":1, "rbi":3, "r":1, "hr":1},{"game":"19990406_COL@SD", "ab":3, "h":0, "rbi":0, "r":0, "hr":0},{"game":"19990407_COL@SD", "ab":1, "h":0, "rbi":0, "r":0, "hr":0}],"Chris Gomez":[{"game":"19990404_COL@SD", "ab":1, "h":0, "rbi":0, "r":0, "hr":0},{"game":"19990406_COL@SD", "ab":3, "h":0, "rbi":0, "r":0, "hr":0},{"game":"19990407_COL@SD", "ab":4, "h":1, "rbi":0, "r":0, "hr":0}],"Andy Ashby":[{"game":"19990404_COL@SD", "ab":2, "h":0, "rbi":0, "r":0, "hr":0}],"John Vander Wal":[{"game":"19990404_COL@SD", "ab":0, "h":0, "rbi":0, "r":0, "hr":0},{"game":"19990406_COL@SD", "ab":1, "h":0, "rbi":0, "r":0, "hr":0},{"game":"19990407_COL@SD", "ab":3, "h":0, "rbi":0, "r":0, "hr":0}],"Damian Jackson":[{"game":"19990404_COL@SD", "ab":0, "h":0, "rbi":0, "r":0, "hr":0}],"Mike DeJean":[{"game":"19990404_COL@SD", "ab":0, "h":0, "rbi":0, "r":0, "hr":0}],"Bobby M. Jones":[{"game":"19990404_COL@SD", "ab":0, "h":0, "rbi":0, "r":0, "hr":0}],"Curt Leskanic":[{"game":"19990404_COL@SD", "ab":0, "h":0, "rbi":0, "r":0, "hr":0}],"Roberto Rivera":[{"game":"19990404_COL@SD", "ab":0, "h":0, "rbi":0, "r":0, "hr":0},{"game":"19990406_COL@SD", "ab":0, "h":0, "rbi":0, "r":0, "hr":0}],"Carlos Reyes":[{"game":"19990404_COL@SD", "ab":0, "h":0, "rbi":0, "r":0, "hr":0},{"game":"19990407_COL@SD", "ab":0, "h":0, "rbi":0, "r":0, "hr":0}],"Dan Miceli":[{"game":"19990404_COL@SD", "ab":0, "h":0, "rbi":0, "r":0, "hr":0},{"game":"19990407_COL@SD", "ab":0, "h":0, "rbi":0, "r":0, "hr":0}],"Trevor Hoffman":[{"game":"19990404_COL@SD", "ab":0, "h":0, "rbi":0, "r":0, "hr":0}],"Jose Offerman":[{"game":"19990405_BOS@KC", "ab":4, "h":2, "rbi":0, "r":1, "hr":0},{"game":"19990407_BOS@KC", "ab":3, "h":0, "rbi":0, "r":0, "hr":0},{"game":"19990408_BOS@KC", "ab":4, "h":2, "rbi":1, "r":1, "hr":0}],"Darren Lewis":[{"game":"19990405_BOS@KC", "ab":3, "h":0, "rbi":0, "r":0, "hr":0},{"game":"19990407_BOS@KC", "ab":2, "h":1, "rbi":0, "r":0, "hr":0},{"game":"19990408_BOS@KC", "ab":5, "h":1, "rbi":1, "r":0, "hr":0}],"John Valentin":[{"game":"19990405_BOS@KC", "ab":5, "h":0, "rbi":0, "r":2, "hr":0},{"game":"19990407_BOS@KC", "ab":5, "h":1, "rbi":0, "r":0, "hr":0},{"game":"19990408_BOS@KC", "ab":5, "h":0, "rbi":0, "r":0, "hr":0}],"Nomar Garciaparra":[{"game":"19990405_BOS@KC", "ab":5, "h":3, "rbi":2, "r":1, "hr":1},{"game":"19990407_BOS@KC", "ab":4, "h":2, "rbi":0, "r":0, "hr":0}],"Troy O'Leary":[{"game":"19990405_BOS@KC", "ab":2, "h":0, "rbi":0, "r":1, "hr":0},{"game":"19990407_BOS@KC", "ab":5, "h":4, "rbi":2, "r":2, "hr":2},{"game":"19990408_BOS@KC", "ab":4, "h":1, "rbi":0, "r":0, "hr":0}],"Mike Stanley":[{"game":"19990405_BOS@KC", "ab":4, "h":2, "rbi":2, "r":1, "hr":1},{"game":"19990407_BOS@KC", "ab":5, "h":0, "rbi":0, "r":0, "hr":0},{"game":"19990408_BOS@KC", "ab":5, "h":2, "rbi":0, "r":0, "hr":0}],"Scott Hatteberg":[{"game":"19990405_BOS@KC", "ab":4, "h":1, "rbi":0, "r":0, "hr":0}],"Jeff Frye":[{"game":"19990405_BOS@KC", "ab":3, "h":1, "rbi":0, "r":0, "hr":0},{"game":"19990407_BOS@KC", "ab":2, "h":0, "rbi":0, "r":0, "hr":0},{"game":"19990408_BOS@KC", "ab":4, "h":2, "rbi":1, "r":2, "hr":0}],"Trot Nixon":[{"game":"19990405_BOS@KC", "ab":4, "h":1, "rbi":1, "r":1, "hr":1},{"game":"19990407_BOS@KC", "ab":2, "h":0, "rbi":0, "r":0, "hr":0},{"game":"19990407_BOS@KC", "ab":0, "h":0, "rbi":0, "r":0, "hr":0},{"game":"19990408_BOS@KC", "ab":3, "h":2, "rbi":1, "r":1, "hr":0}],"Pedro Martinez":[{"game":"19990405_BOS@KC", "ab":0, "h":0, "rbi":0, "r":0, "hr":0}],"Derek Lowe":[{"game":"19990405_BOS@KC", "ab":0, "h":0, "rbi":0, "r":0, "hr":0},{"game":"19990407_BOS@KC", "ab":0, "h":0, "rbi":0, "r":0, "hr":0}],"Tom Gordon":[{"game":"19990405_BOS@KC", "ab":0, "h":0, "rbi":0, "r":0, "hr":0},{"game":"19990407_BOS@KC", "ab":0, "h":0, "rbi":0, "r":0, "hr":0}],"Carlos Beltran":[{"game":"19990405_BOS@KC", "ab":4, "h":1, "rbi":0, "r":1, "hr":0},{"game":"19990407_BOS@KC", "ab":6, "h":4, "rbi":1, "r":2, "hr":0},{"game":"19990408_BOS@KC", "ab":4, "h":0, "rbi":0, "r":1, "hr":0}],"Joe Randa":[{"game":"19990405_BOS@KC", "ab":4, "h":2, "rbi":0, "r":0, "hr":0},{"game":"19990407_BOS@KC", "ab":5, "h":1, "rbi":1, "r":0, "hr":0},{"game":"19990408_BOS@KC", "ab":4, "h":3, "rbi":2, "r":2, "hr":1}],"Johnny Damon":[{"game":"19990405_BOS@KC", "ab":4, "h":1, "rbi":1, "r":0, "hr":0},{"game":"19990407_BOS@KC", "ab":4, "h":3, "rbi":1, "r":0, "hr":0},{"game":"19990408_BOS@KC", "ab":5, "h":1, "rbi":0, "r":0, "hr":0}],"Jeff King":[{"game":"19990405_BOS@KC", "ab":4, "h":0, "rbi":0, "r":0, "hr":0},{"game":"19990407_BOS@KC", "ab":4, "h":1, "rbi":0, "r":0, "hr":0},{"game":"19990408_BOS@KC", "ab":3, "h":0, "rbi":0, "r":0, "hr":0}],"Larry Sutton":[{"game":"19990405_BOS@KC", "ab":4, "h":0, "rbi":0, "r":0, "hr":0},{"game":"19990407_BOS@KC", "ab":2, "h":0, "rbi":0, "r":0, "hr":0}],"Jermaine Dye":[{"game":"19990405_BOS@KC", "ab":4, "h":2, "rbi":1, "r":1, "hr":1},{"game":"19990407_BOS@KC", "ab":5, "h":1, "rbi":0, "r":0, "hr":0},{"game":"19990408_BOS@KC", "ab":3, "h":1, "rbi":0, "r":0, "hr":0}],"Chad Kreuter":[{"game":"19990405_BOS@KC", "ab":2, "h":0, "rbi":0, "r":0, "hr":0},{"game":"19990407_BOS@KC", "ab":4, "h":0, "rbi":0, "r":0, "hr":0}],"Scott Pose":[{"game":"19990405_BOS@KC", "ab":1, "h":0, "rbi":0, "r":0, "hr":0},{"game":"19990407_BOS@KC", "ab":1, "h":1, "rbi":0, "r":0, "hr":0}],"Rey Sanchez":[{"game":"19990405_BOS@KC", "ab":4, "h":1, "rbi":0, "r":0, "hr":0},{"game":"19990407_BOS@KC", "ab":5, "h":2, "rbi":0, "r":2, "hr":0},{"game":"19990408_BOS@KC", "ab":4, "h":1, "rbi":0, "r":0, "hr":0}],"Carlos Febles":[{"game":"19990405_BOS@KC", "ab":4, "h":0, "rbi":0, "r":0, "hr":0},{"game":"19990407_BOS@KC", "ab":4, "h":2, "rbi":1, "r":0, "hr":0},{"game":"19990408_BOS@KC", "ab":3, "h":0, "rbi":0, "r":0, "hr":0}],"Kevin Appier":[{"game":"19990405_BOS@KC", "ab":0, "h":0, "rbi":0, "r":0, "hr":0}],"Matt Whisenant":[{"game":"19990405_BOS@KC", "ab":0, "h":0, "rbi":0, "r":0, "hr":0},{"game":"19990407_BOS@KC", "ab":0, "h":0, "rbi":0, "r":0, "hr":0}],"Jay Witasick":[{"game":"19990405_BOS@KC", "ab":0, "h":0, "rbi":0, "r":0, "hr":0}],"Don Wengert":[{"game":"19990405_BOS@KC", "ab":0, "h":0, "rbi":0, "r":0, "hr":0},{"game":"19990408_BOS@KC", "ab":0, "h":0, "rbi":0, "r":0, "hr":0}],"Steve Finley":[{"game":"19990405_ARI@LA", "ab":5, "h":1, "rbi":1, "r":1, "hr":1},{"game":"19990406_ARI@LA", "ab":5, "h":0, "rbi":0, "r":0, "hr":0},{"game":"19990407_ARI@LA", "ab":3, "h":1, "rbi":1, "r":0, "hr":0}],"Jay Bell":[{"game":"19990405_ARI@LA", "ab":4, "h":0, "rbi":1, "r":1, "hr":0},{"game":"19990406_ARI@LA", "ab":4, "h":1, "rbi":0, "r":0, "hr":0},{"game":"19990407_ARI@LA", "ab":4, "h":0, "rbi":0, "r":0, "hr":0}],"Travis Lee":[{"game":"19990405_ARI@LA", "ab":3, "h":1, "rbi":0, "r":1, "hr":0},{"game":"19990406_ARI@LA", "ab":4, "h":0, "rbi":0, "r":0, "hr":0},{"game":"19990407_ARI@LA", "ab":3, "h":1, "rbi":0, "r":1, "hr":0}],"Matt Williams":[{"game":"19990405_ARI@LA", "ab":5, "h":2, "rbi":3, "r":1, "hr":1},{"game":"19990406_ARI@LA", "ab":5, "h":0, "rbi":0, "r":0, "hr":0},{"game":"19990407_ARI@LA", "ab":2, "h":0, "rbi":0, "r":1, "hr":0}],"Luis Gonzalez":[{"game":"19990405_ARI@LA", "ab":4, "h":2, "rbi":1, "r":1, "hr":1},{"game":"19990406_ARI@LA", "ab":4, "h":1, "rbi":1, "r":1, "hr":1},{"game":"19990407_ARI@LA", "ab":4, "h":1, "rbi":1, "r":0, "hr":0}],"Ernie Young":[{"game":"19990405_ARI@LA", "ab":0, "h":0, "rbi":0, "r":0, "hr":0}],"Bernard Gilkey":[{"game":"19990405_ARI@LA", "ab":5, "h":3, "rbi":0, "r":0, "hr":0},{"game":"19990406_ARI@LA", "ab":4, "h":1, "rbi":0, "r":2, "hr":0},{"game":"19990407_ARI@LA", "ab":3, "h":0, "rbi":0, "r":0, "hr":0}],"Tony Batista":[{"game":"19990405_ARI@LA", "ab":5, "h":0, "rbi":0, "r":0, "hr":0},{"game":"19990406_ARI@LA", "ab":4, "h":3, "rbi":1, "r":0, "hr":0},{"game":"19990407_ARI@LA", "ab":2, "h":0, "rbi":0, "r":0, "hr":0}],"Kelly Stinnett":[{"game":"19990405_ARI@LA", "ab":4, "h":1, "rbi":0, "r":1, "hr":0},{"game":"19990407_ARI@LA", "ab":3, "h":1, "rbi":2, "r":2, "hr":1}],"Randy Johnson":[{"game":"19990405_ARI@LA", "ab":3, "h":1, "rbi":0, "r":1, "hr":0}],"Andy Fox":[{"game":"19990405_ARI@LA", "ab":0, "h":0, "rbi":0, "r":0, "hr":0},{"game":"19990406_ARI@LA", "ab":0, "h":0, "rbi":0, "r":0, "hr":0},{"game":"19990407_ARI@LA", "ab":1, "h":0, "rbi":0, "r":0, "hr":0}],"Greg Colbrunn":[{"game":"19990405_ARI@LA", "ab":1, "h":0, "rbi":0, "r":0, "hr":0}],"David Dellucci":[{"game":"19990405_ARI@LA", "ab":0, "h":0, "rbi":0, "r":0, "hr":0},{"game":"19990406_ARI@LA", "ab":1, "h":0, "rbi":0, "r":0, "hr":0},{"game":"19990407_ARI@LA", "ab":2, "h":0, "rbi":0, "r":0, "hr":0}],"Darren Holmes":[{"game":"19990405_ARI@LA", "ab":0, "h":0, "rbi":0, "r":0, "hr":0},{"game":"19990406_ARI@LA", "ab":0, "h":0, "rbi":0, "r":0, "hr":0}],"Armando Reynoso":[{"game":"19990405_ARI@LA", "ab":0, "h":0, "rbi":0, "r":0, "hr":0}],"Eric Young":[{"game":"19990405_ARI@LA", "ab":4, "h":0, "rbi":0, "r":0, "hr":0},{"game":"19990406_ARI@LA", "ab":4, "h":2, "rbi":2, "r":1, "hr":0},{"game":"19990407_ARI@LA", "ab":5, "h":4, "rbi":1, "r":2, "hr":0}],"Mark Grudzielanek":[{"game":"19990405_ARI@LA", "ab":4, "h":2, "rbi":0, "r":0, "hr":0},{"game":"19990406_ARI@LA", "ab":4, "h":0, "rbi":0, "r":0, "hr":0},{"game":"19990407_ARI@LA", "ab":4, "h":3, "rbi":1, "r":1, "hr":0}],"Gary Sheffield":[{"game":"19990405_ARI@LA", "ab":4, "h":1, "rbi":0, "r":0, "hr":0},{"game":"19990406_ARI@LA", "ab":4, "h":0, "rbi":0, "r":0, "hr":0},{"game":"19990407_ARI@LA", "ab":3, "h":1, "rbi":0, "r":0, "hr":0}],"Raul Mondesi":[{"game":"19990405_ARI@LA", "ab":4, "h":0, "rbi":0, "r":0, "hr":0},{"game":"19990406_ARI@LA", "ab":4, "h":0, "rbi":0, "r":0, "hr":0},{"game":"19990407_ARI@LA", "ab":5, "h":1, "rbi":1, "r":0, "hr":0}],"Devon White":[{"game":"19990405_ARI@LA", "ab":4, "h":1, "rbi":0, "r":0, "hr":0},{"game":"19990406_ARI@LA", "ab":4, "h":0, "rbi":0, "r":0, "hr":0},{"game":"19990407_ARI@LA", "ab":5, "h":2, "rbi":3, "r":2, "hr":1}],"Eric Karros":[{"game":"19990405_ARI@LA", "ab":4, "h":0, "rbi":0, "r":0, "hr":0},{"game":"19990406_ARI@LA", "ab":4, "h":2, "rbi":0, "r":1, "hr":0},{"game":"19990407_ARI@LA", "ab":4, "h":2, "rbi":0, "r":2, "hr":0}],"Todd Hundley":[{"game":"19990405_ARI@LA", "ab":4, "h":1, "rbi":0, "r":0, "hr":0},{"game":"19990406_ARI@LA", "ab":3, "h":1, "rbi":1, "r":0, "hr":0},{"game":"19990407_ARI@LA", "ab":3, "h":1, "rbi":1, "r":1, "hr":1}],"Adrian Beltre":[{"game":"19990405_ARI@LA", "ab":3, "h":1, "rbi":0, "r":0, "hr":0},{"game":"19990406_ARI@LA", "ab":4, "h":2, "rbi":1, "r":1, "hr":0},{"game":"19990407_ARI@LA", "ab":2, "h":1, "rbi":1, "r":1, "hr":0}],"Dave Hansen":[{"game":"19990405_ARI@LA", "ab":1, "h":0, "rbi":0, "r":0, "hr":0},{"game":"19990406_ARI@LA", "ab":0, "h":0, "rbi":0, "r":0, "hr":0}],"Kevin Brown":[{"game":"19990405_ARI@LA", "ab":1, "h":0, "rbi":0, "r":0, "hr":0}],"Jose Vizcaino":[{"game":"19990405_ARI@LA", "ab":1, "h":1, "rbi":0, "r":0, "hr":0},{"game":"19990406_ARI@LA", "ab":1, "h":0, "rbi":0, "r":0, "hr":0},{"game":"19990407_ARI@LA", "ab":1, "h":0, "rbi":0, "r":0, "hr":0},{"game":"19990407_ARI@LA", "ab":0, "h":0, "rbi":0, "r":0, "hr":0}],"Onan Masaoka":[{"game":"19990405_ARI@LA", "ab":0, "h":0, "rbi":0, "r":0, "hr":0},{"game":"19990406_ARI@LA", "ab":0, "h":0, "rbi":0, "r":0, "hr":0}],"Dave Mlicki":[{"game":"19990405_ARI@LA", "ab":0, "h":0, "rbi":0, "r":0, "hr":0},{"game":"19990406_ARI@LA", "ab":0, "h":0, "rbi":0, "r":0, "hr":0}],"Pedro Borbon":[{"game":"19990405_ARI@LA", "ab":0, "h":0, "rbi":0, "r":0, "hr":0},{"game":"19990406_ARI@LA", "ab":0, "h":0, "rbi":0, "r":0, "hr":0}],"Alan Mills":[{"game":"19990405_ARI@LA", "ab":0, "h":0, "rbi":0, "r":0, "hr":0},{"game":"19990407_ARI@LA", "ab":0, "h":0, "rbi":0, "r":0, "hr":0}],"Mel Rojas":[{"game":"19990405_ARI@LA", "ab":0, "h":0, "rbi":0, "r":0, "hr":0},{"game":"19990406_ARI@LA", "ab":0, "h":0, "rbi":0, "r":0, "hr":0}],"Damian Miller":[{"game":"19990406_ARI@LA", "ab":5, "h":2, "rbi":0, "r":0, "hr":0}],"Todd Stottlemyre":[{"game":"19990406_ARI@LA", "ab":3, "h":1, "rbi":0, "r":0, "hr":0}],"Greg Swindell":[{"game":"19990406_ARI@LA", "ab":0, "h":0, "rbi":0, "r":0, "hr":0}],"Gregg Olson":[{"game":"19990406_ARI@LA", "ab":0, "h":0, "rbi":0, "r":0, "hr":0}],"Chan Ho Park":[{"game":"19990406_ARI@LA", "ab":1, "h":0, "rbi":0, "r":0, "hr":0}],"Rick Wilkins":[{"game":"19990406_ARI@LA", "ab":1, "h":1, "rbi":0, "r":0, "hr":0}],"Jacob Brumfield":[{"game":"19990406_ARI@LA", "ab":0, "h":0, "rbi":0, "r":1, "hr":0}],"Tripp Cromer":[{"game":"19990406_ARI@LA", "ab":1, "h":1, "rbi":0, "r":0, "hr":0}],"Jeff Shaw":[{"game":"19990406_ARI@LA", "ab":0, "h":0, "rbi":0, "r":0, "hr":0}],"Pat Watkins":[{"game":"19990406_COL@SD", "ab":2, "h":0, "rbi":0, "r":1, "hr":0},{"game":"19990407_COL@SD", "ab":0, "h":0, "rbi":0, "r":0, "hr":0}],"Pedro Astacio":[{"game":"19990406_COL@SD", "ab":2, "h":0, "rbi":0, "r":1, "hr":0}],"Jerry Dipoto":[{"game":"19990406_COL@SD", "ab":0, "h":0, "rbi":0, "r":0, "hr":0},{"game":"19990407_COL@SD", "ab":0, "h":0, "rbi":0, "r":0, "hr":0}],"Dave Veres":[{"game":"19990406_COL@SD", "ab":0, "h":0, "rbi":0, "r":0, "hr":0}],"Jim Leyritz":[{"game":"19990406_COL@SD", "ab":4, "h":1, "rbi":1, "r":1, "hr":1},{"game":"19990407_COL@SD", "ab":1, "h":0, "rbi":0, "r":0, "hr":0}],"Dave Magadan":[{"game":"19990406_COL@SD", "ab":1, "h":0, "rbi":0, "r":0, "hr":0},{"game":"19990406_COL@SD", "ab":0, "h":0, "rbi":0, "r":0, "hr":0},{"game":"19990407_COL@SD", "ab":1, "h":1, "rbi":0, "r":1, "hr":0}],"Sterling Hitchcock":[{"game":"19990406_COL@SD", "ab":2, "h":0, "rbi":0, "r":0, "hr":0}],"Donne Wall":[{"game":"19990406_COL@SD", "ab":0, "h":0, "rbi":0, "r":0, "hr":0}],"Brian Boehringer":[{"game":"19990406_COL@SD", "ab":0, "h":0, "rbi":0, "r":0, "hr":0},{"game":"19990407_COL@SD", "ab":0, "h":0, "rbi":0, "r":0, "hr":0}],"Brian Daubach":[{"game":"19990407_BOS@KC", "ab":0, "h":0, "rbi":0, "r":0, "hr":0}],"Donnie Sadler":[{"game":"19990407_BOS@KC", "ab":1, "h":0, "rbi":0, "r":0, "hr":0},{"game":"19990407_BOS@KC", "ab":0, "h":0, "rbi":0, "r":0, "hr":0},{"game":"19990407_BOS@KC", "ab":0, "h":0, "rbi":0, "r":0, "hr":0},{"game":"19990408_BOS@KC", "ab":4, "h":3, "rbi":2, "r":2, "hr":0}],"Damon Buford":[{"game":"19990407_BOS@KC", "ab":3, "h":0, "rbi":0, "r":0, "hr":0},{"game":"19990408_BOS@KC", "ab":1, "h":0, "rbi":0, "r":1, "hr":0}],"Jason Varitek":[{"game":"19990407_BOS@KC", "ab":5, "h":2, "rbi":1, "r":1, "hr":1},{"game":"19990408_BOS@KC", "ab":4, "h":0, "rbi":0, "r":0, "hr":0}],"Bret Saberhagen":[{"game":"19990407_BOS@KC", "ab":0, "h":0, "rbi":0, "r":0, "hr":0}],"Jim Corsi":[{"game":"19990407_BOS@KC", "ab":0, "h":0, "rbi":0, "r":0, "hr":0},{"game":"19990408_BOS@KC", "ab":0, "h":0, "rbi":0, "r":0, "hr":0}],"Rheal Cormier":[{"game":"19990407_BOS@KC", "ab":0, "h":0, "rbi":0, "r":0, "hr":0}],"Scott Leius":[{"game":"19990407_BOS@KC", "ab":1, "h":0, "rbi":0, "r":0, "hr":0}],"Jose Rosado":[{"game":"19990407_BOS@KC", "ab":0, "h":0, "rbi":0, "r":0, "hr":0}],"Jose Santiago":[{"game":"19990407_BOS@KC", "ab":0, "h":0, "rbi":0, "r":0, "hr":0}],"Scott Service":[{"game":"19990407_BOS@KC", "ab":0, "h":0, "rbi":0, "r":0, "hr":0},{"game":"19990408_BOS@KC", "ab":0, "h":0, "rbi":0, "r":0, "hr":0}],"Jeff Montgomery":[{"game":"19990407_BOS@KC", "ab":0, "h":0, "rbi":0, "r":0, "hr":0},{"game":"19990408_BOS@KC", "ab":0, "h":0, "rbi":0, "r":0, "hr":0}],"Andy Benes":[{"game":"19990407_ARI@LA", "ab":0, "h":0, "rbi":0, "r":0, "hr":0}],"Hanley Frias":[{"game":"19990407_ARI@LA", "ab":3, "h":0, "rbi":0, "r":0, "hr":0}],"John Frascatore":[{"game":"19990407_ARI@LA", "ab":0, "h":0, "rbi":0, "r":0, "hr":0}],"Brian Anderson":[{"game":"19990407_ARI@LA", "ab":0, "h":0, "rbi":0, "r":0, "hr":0}],"Paul Lo Duca":[{"game":"19990407_ARI@LA", "ab":1, "h":0, "rbi":0, "r":0, "hr":0}],"Ismael Valdez":[{"game":"19990407_ARI@LA", "ab":3, "h":0, "rbi":0, "r":0, "hr":0}],"Jeff Reed":[{"game":"19990407_COL@SD", "ab":4, "h":0, "rbi":0, "r":1, "hr":0}],"Jamey Wright":[{"game":"19990407_COL@SD", "ab":3, "h":0, "rbi":0, "r":0, "hr":0}],"Chuck McElroy":[{"game":"19990407_COL@SD", "ab":0, "h":0, "rbi":0, "r":0, "hr":0}],"Roberto Ramirez":[{"game":"19990407_COL@SD", "ab":0, "h":0, "rbi":0, "r":0, "hr":0}],"Woody Williams":[{"game":"19990407_COL@SD", "ab":2, "h":0, "rbi":0, "r":0, "hr":0}],"Carlos Garcia":[{"game":"19990407_COL@SD", "ab":1, "h":1, "rbi":0, "r":0, "hr":0}],"Tim Wakefield":[{"game":"19990408_BOS@KC", "ab":0, "h":0, "rbi":0, "r":0, "hr":0}],"Mark Guthrie":[{"game":"19990408_BOS@KC", "ab":0, "h":0, "rbi":0, "r":0, "hr":0}],"Kip Gross":[{"game":"19990408_BOS@KC", "ab":0, "h":0, "rbi":0, "r":0, "hr":0}],"Mike Sweeney":[{"game":"19990408_BOS@KC", "ab":4, "h":1, "rbi":1, "r":0, "hr":0}],"Tim Spehr":[{"game":"19990408_BOS@KC", "ab":3, "h":1, "rbi":0, "r":0, "hr":0}],"Jeff Suppan":[{"game":"19990408_BOS@KC", "ab":0, "h":0, "rbi":0, "r":0, "hr":0}],"Ray Durham":[{"game":"19990405_CHW@SEA", "ab":5, "h":3, "rbi":1, "r":3, "hr":0},{"game":"19990406_CHW@SEA", "ab":5, "h":0, "rbi":0, "r":0, "hr":0},{"game":"19990407_CHW@SEA", "ab":3, "h":0, "rbi":0, "r":1, "hr":0}],"Craig Wilson":[{"game":"19990405_CHW@SEA", "ab":0, "h":0, "rbi":0, "r":0, "hr":0},{"game":"19990407_CHW@SEA", "ab":1, "h":0, "rbi":0, "r":0, "hr":0}],"Mike Caruso":[{"game":"19990405_CHW@SEA", "ab":6, "h":2, "rbi":1, "r":2, "hr":0},{"game":"19990406_CHW@SEA", "ab":4, "h":1, "rbi":0, "r":0, "hr":0},{"game":"19990407_CHW@SEA", "ab":4, "h":2, "rbi":0, "r":0, "hr":0}],"Frank Thomas":[{"game":"19990405_CHW@SEA", "ab":2, "h":2, "rbi":3, "r":1, "hr":0},{"game":"19990406_CHW@SEA", "ab":4, "h":0, "rbi":0, "r":0, "hr":0},{"game":"19990407_CHW@SEA", "ab":3, "h":1, "rbi":1, "r":0, "hr":0}],"Jeff Liefer":[{"game":"19990405_CHW@SEA", "ab":1, "h":0, "rbi":0, "r":0, "hr":0},{"game":"19990407_CHW@SEA", "ab":3, "h":0, "rbi":0, "r":0, "hr":0}],"Paul Konerko":[{"game":"19990405_CHW@SEA", "ab":6, "h":0, "rbi":1, "r":1, "hr":0},{"game":"19990406_CHW@SEA", "ab":3, "h":0, "rbi":0, "r":0, "hr":0},{"game":"19990407_CHW@SEA", "ab":1, "h":0, "rbi":0, "r":0, "hr":0}],"Magglio Ordonez":[{"game":"19990405_CHW@SEA", "ab":4, "h":3, "rbi":5, "r":1, "hr":1},{"game":"19990406_CHW@SEA", "ab":4, "h":1, "rbi":0, "r":1, "hr":0},{"game":"19990407_CHW@SEA", "ab":4, "h":1, "rbi":0, "r":0, "hr":0}],"McKay Christensen":[{"game":"19990405_CHW@SEA", "ab":1, "h":0, "rbi":0, "r":0, "hr":0},{"game":"19990407_CHW@SEA", "ab":2, "h":0, "rbi":0, "r":0, "hr":0}],"Greg Norton":[{"game":"19990405_CHW@SEA", "ab":4, "h":2, "rbi":1, "r":2, "hr":1},{"game":"19990406_CHW@SEA", "ab":3, "h":1, "rbi":0, "r":0, "hr":0},{"game":"19990407_CHW@SEA", "ab":3, "h":1, "rbi":1, "r":1, "hr":1}],"Jeff Abbott":[{"game":"19990405_CHW@SEA", "ab":5, "h":2, "rbi":2, "r":2, "hr":2},{"game":"19990406_CHW@SEA", "ab":4, "h":1, "rbi":0, "r":1, "hr":0},{"game":"19990407_CHW@SEA", "ab":1, "h":1, "rbi":0, "r":0, "hr":0},{"game":"19990407_CHW@SEA", "ab":0, "h":0, "rbi":0, "r":0, "hr":0}],"Chris Singleton":[{"game":"19990405_CHW@SEA", "ab":0, "h":0, "rbi":0, "r":0, "hr":0}],"Darrin Jackson":[{"game":"19990405_CHW@SEA", "ab":5, "h":2, "rbi":0, "r":2, "hr":0},{"game":"19990405_CHW@SEA", "ab":0, "h":0, "rbi":0, "r":0, "hr":0},{"game":"19990406_CHW@SEA", "ab":4, "h":2, "rbi":1, "r":0, "hr":0},{"game":"19990407_CHW@SEA", "ab":3, "h":0, "rbi":0, "r":0, "hr":0},{"game":"19990407_CHW@SEA", "ab":0, "h":0, "rbi":0, "r":0, "hr":0}],"Brook Fordyce":[{"game":"19990405_CHW@SEA", "ab":4, "h":3, "rbi":1, "r":2, "hr":0},{"game":"19990406_CHW@SEA", "ab":4, "h":2, "rbi":1, "r":0, "hr":0},{"game":"19990407_CHW@SEA", "ab":0, "h":0, "rbi":0, "r":0, "hr":0}],"Mark Johnson":[{"game":"19990405_CHW@SEA", "ab":0, "h":0, "rbi":0, "r":0, "hr":0},{"game":"19990407_CHW@SEA", "ab":2, "h":0, "rbi":0, "r":0, "hr":0}],"James Baldwin":[{"game":"19990405_CHW@SEA", "ab":0, "h":0, "rbi":0, "r":0, "hr":0}],"Bryan Ward":[{"game":"19990405_CHW@SEA", "ab":0, "h":0, "rbi":0, "r":0, "hr":0},{"game":"19990407_CHW@SEA", "ab":0, "h":0, "rbi":0, "r":0, "hr":0}],"David Lundquist":[{"game":"19990405_CHW@SEA", "ab":0, "h":0, "rbi":0, "r":0, "hr":0},{"game":"19990407_CHW@SEA", "ab":0, "h":0, "rbi":0, "r":0, "hr":0}],"Carlos Guillen":[{"game":"19990405_CHW@SEA", "ab":5, "h":1, "rbi":0, "r":0, "hr":0},{"game":"19990406_CHW@SEA", "ab":5, "h":1, "rbi":0, "r":0, "hr":0},{"game":"19990407_CHW@SEA", "ab":4, "h":1, "rbi":0, "r":2, "hr":0}],"David Bell":[{"game":"19990405_CHW@SEA", "ab":0, "h":0, "rbi":0, "r":0, "hr":0},{"game":"19990407_CHW@SEA", "ab":3, "h":0, "rbi":0, "r":0, "hr":0}],"Alex Rodriguez":[{"game":"19990405_CHW@SEA", "ab":4, "h":1, "rbi":0, "r":1, "hr":0},{"game":"19990406_CHW@SEA", "ab":4, "h":1, "rbi":0, "r":2, "hr":0}],"Charles Gipson":[{"game":"19990405_CHW@SEA", "ab":1, "h":0, "rbi":0, "r":0, "hr":0}],"Ken Griffey":[{"game":"19990405_CHW@SEA", "ab":3, "h":2, "rbi":0, "r":1, "hr":0},{"game":"19990406_CHW@SEA", "ab":4, "h":3, "rbi":1, "r":2, "hr":1},{"game":"19990407_CHW@SEA", "ab":4, "h":3, "rbi":2, "r":0, "hr":1}],"Matt Mieske":[{"game":"19990405_CHW@SEA", "ab":1, "h":1, "rbi":0, "r":1, "hr":0}],"Edgar Martinez":[{"game":"19990405_CHW@SEA", "ab":2, "h":1, "rbi":2, "r":1, "hr":1},{"game":"19990406_CHW@SEA", "ab":4, "h":1, "rbi":2, "r":0, "hr":0},{"game":"19990407_CHW@SEA", "ab":3, "h":1, "rbi":1, "r":1, "hr":0}],"Butch Huskey":[{"game":"19990405_CHW@SEA", "ab":1, "h":0, "rbi":0, "r":0, "hr":0},{"game":"19990406_CHW@SEA", "ab":4, "h":2, "rbi":2, "r":0, "hr":0}],"David Segui":[{"game":"19990405_CHW@SEA", "ab":3, "h":1, "rbi":1, "r":0, "hr":0},{"game":"19990406_CHW@SEA", "ab":3, "h":0, "rbi":0, "r":2, "hr":0},{"game":"19990407_CHW@SEA", "ab":4, "h":3, "rbi":0, "r":0, "hr":0}],"Jay Buhner":[{"game":"19990405_CHW@SEA", "ab":4, "h":0, "rbi":0, "r":0, "hr":0},{"game":"19990406_CHW@SEA", "ab":3, "h":2, "rbi":1, "r":2, "hr":0},{"game":"19990407_CHW@SEA", "ab":4, "h":1, "rbi":0, "r":1, "hr":0}],"Raul Ibanez":[{"game":"19990405_CHW@SEA", "ab":1, "h":0, "rbi":0, "r":0, "hr":0}],"John Mabry":[{"game":"19990405_CHW@SEA", "ab":2, "h":1, "rbi":1, "r":0, "hr":0},{"game":"19990405_CHW@SEA", "ab":0, "h":0, "rbi":0, "r":0, "hr":0},{"game":"19990406_CHW@SEA", "ab":0, "h":0, "rbi":0, "r":0, "hr":0},{"game":"19990407_CHW@SEA", "ab":4, "h":1, "rbi":0, "r":1, "hr":0}],"Russ Davis":[{"game":"19990405_CHW@SEA", "ab":5, "h":0, "rbi":0, "r":0, "hr":0},{"game":"19990406_CHW@SEA", "ab":4, "h":0, "rbi":0, "r":0, "hr":0},{"game":"19990407_CHW@SEA", "ab":4, "h":1, "rbi":1, "r":1, "hr":0}],"Dan Wilson":[{"game":"19990405_CHW@SEA", "ab":3, "h":0, "rbi":0, "r":0, "hr":0},{"game":"19990407_CHW@SEA", "ab":4, "h":1, "rbi":0, "r":0, "hr":0}],"Tom Lampkin":[{"game":"19990405_CHW@SEA", "ab":1, "h":0, "rbi":0, "r":0, "hr":0},{"game":"19990406_CHW@SEA", "ab":4, "h":2, "rbi":2, "r":1, "hr":0}],"Jeff Fassero":[{"game":"19990405_CHW@SEA", "ab":0, "h":0, "rbi":0, "r":0, "hr":0}],"Brett Hinchliffe":[{"game":"19990405_CHW@SEA", "ab":0, "h":0, "rbi":0, "r":0, "hr":0}],"Eric Weaver":[{"game":"19990405_CHW@SEA", "ab":0, "h":0, "rbi":0, "r":0, "hr":0}],"Mac Suzuki":[{"game":"19990405_CHW@SEA", "ab":0, "h":0, "rbi":0, "r":0, "hr":0}],"Jim Parque":[{"game":"19990406_CHW@SEA", "ab":0, "h":0, "rbi":0, "r":0, "hr":0}],"Sean Lowe":[{"game":"19990406_CHW@SEA", "ab":0, "h":0, "rbi":0, "r":0, "hr":0}],"Bill Simas":[{"game":"19990406_CHW@SEA", "ab":0, "h":0, "rbi":0, "r":0, "hr":0}],"Keith Foulke":[{"game":"19990406_CHW@SEA", "ab":0, "h":0, "rbi":0, "r":0, "hr":0}],"Jamie Moyer":[{"game":"19990406_CHW@SEA", "ab":0, "h":0, "rbi":0, "r":0, "hr":0}],"Jose Paniagua":[{"game":"19990406_CHW@SEA", "ab":0, "h":0, "rbi":0, "r":0, "hr":0}],"John Halama":[{"game":"19990406_CHW@SEA", "ab":0, "h":0, "rbi":0, "r":0, "hr":0},{"game":"19990407_CHW@SEA", "ab":0, "h":0, "rbi":0, "r":0, "hr":0}],"John Snyder":[{"game":"19990407_CHW@SEA", "ab":0, "h":0, "rbi":0, "r":0, "hr":0}],"Freddy Garcia":[{"game":"19990407_CHW@SEA", "ab":0, "h":0, "rbi":0, "r":0, "hr":0}],"Juan Encarnacion":[{"game":"19990405_DET@TEX", "ab":4, "h":1, "rbi":0, "r":0, "hr":0},{"game":"19990406_DET@TEX", "ab":4, "h":0, "rbi":0, "r":0, "hr":0},{"game":"19990407_DET@TEX", "ab":5, "h":3, "rbi":1, "r":2, "hr":0}],"Gregg Jefferies":[{"game":"19990405_DET@TEX", "ab":4, "h":1, "rbi":1, "r":0, "hr":0},{"game":"19990406_DET@TEX", "ab":1, "h":0, "rbi":0, "r":0, "hr":0},{"game":"19990407_DET@TEX", "ab":5, "h":1, "rbi":1, "r":1, "hr":1}],"Damion Easley":[{"game":"19990405_DET@TEX", "ab":4, "h":1, "rbi":0, "r":0, "hr":0},{"game":"19990406_DET@TEX", "ab":4, "h":2, "rbi":0, "r":0, "hr":0},{"game":"19990407_DET@TEX", "ab":4, "h":1, "rbi":1, "r":1, "hr":0}],"Tony Clark":[{"game":"19990405_DET@TEX", "ab":4, "h":0, "rbi":0, "r":0, "hr":0},{"game":"19990406_DET@TEX", "ab":3, "h":1, "rbi":1, "r":1, "hr":1},{"game":"19990407_DET@TEX", "ab":5, "h":1, "rbi":2, "r":0, "hr":0}],"Dean Palmer":[{"game":"19990405_DET@TEX", "ab":4, "h":0, "rbi":0, "r":0, "hr":0},{"game":"19990406_DET@TEX", "ab":4, "h":1, "rbi":2, "r":1, "hr":1},{"game":"19990407_DET@TEX", "ab":4, "h":0, "rbi":0, "r":0, "hr":0}],"Bobby Higginson":[{"game":"19990405_DET@TEX", "ab":3, "h":1, "rbi":0, "r":0, "hr":0},{"game":"19990406_DET@TEX", "ab":3, "h":0, "rbi":0, "r":1, "hr":0},{"game":"19990407_DET@TEX", "ab":4, "h":1, "rbi":1, "r":1, "hr":1}],"Deivi Cruz":[{"game":"19990405_DET@TEX", "ab":3, "h":0, "rbi":0, "r":0, "hr":0},{"game":"19990406_DET@TEX", "ab":3, "h":1, "rbi":0, "r":0, "hr":0},{"game":"19990407_DET@TEX", "ab":4, "h":1, "rbi":0, "r":0, "hr":0}],"Brad Ausmus":[{"game":"19990405_DET@TEX", "ab":3, "h":0, "rbi":0, "r":0, "hr":0},{"game":"19990407_DET@TEX", "ab":4, "h":1, "rbi":0, "r":1, "hr":0}],"Brian Hunter":[{"game":"19990405_DET@TEX", "ab":3, "h":1, "rbi":0, "r":1, "hr":0},{"game":"19990407_DET@TEX", "ab":4, "h":1, "rbi":0, "r":1, "hr":0}],"Brian Moehler":[{"game":"19990405_DET@TEX", "ab":0, "h":0, "rbi":0, "r":0, "hr":0}],"C.J. Nitkowski":[{"game":"19990405_DET@TEX", "ab":0, "h":0, "rbi":0, "r":0, "hr":0},{"game":"19990407_DET@TEX", "ab":0, "h":0, "rbi":0, "r":0, "hr":0}],"Masao Kida":[{"game":"19990405_DET@TEX", "ab":0, "h":0, "rbi":0, "r":0, "hr":0},{"game":"19990407_DET@TEX", "ab":0, "h":0, "rbi":0, "r":0, "hr":0}],"Tom Goodwin":[{"game":"19990405_DET@TEX", "ab":5, "h":2, "rbi":0, "r":2, "hr":0},{"game":"19990407_DET@TEX", "ab":6, "h":4, "rbi":4, "r":2, "hr":0}],"Luis Alicea":[{"game":"19990405_DET@TEX", "ab":4, "h":2, "rbi":2, "r":1, "hr":1},{"game":"19990406_DET@TEX", "ab":4, "h":1, "rbi":1, "r":0, "hr":0},{"game":"19990407_DET@TEX", "ab":3, "h":1, "rbi":0, "r":3, "hr":0}],"Rusty Greer":[{"game":"19990405_DET@TEX", "ab":4, "h":0, "rbi":0, "r":1, "hr":0},{"game":"19990406_DET@TEX", "ab":5, "h":2, "rbi":2, "r":2, "hr":1},{"game":"19990407_DET@TEX", "ab":5, "h":2, "rbi":0, "r":1, "hr":0}],"Juan Gonzalez":[{"game":"19990405_DET@TEX", "ab":4, "h":1, "rbi":0, "r":0, "hr":0},{"game":"19990406_DET@TEX", "ab":4, "h":1, "rbi":0, "r":1, "hr":0},{"game":"19990407_DET@TEX", "ab":5, "h":2, "rbi":2, "r":2, "hr":1}],"Rafael Palmeiro":[{"game":"19990405_DET@TEX", "ab":4, "h":2, "rbi":1, "r":1, "hr":0},{"game":"19990406_DET@TEX", "ab":4, "h":1, "rbi":3, "r":1, "hr":1},{"game":"19990407_DET@TEX", "ab":5, "h":2, "rbi":2, "r":2, "hr":1}],"Ivan Rodriguez":[{"game":"19990405_DET@TEX", "ab":4, "h":2, "rbi":2, "r":0, "hr":0},{"game":"19990406_DET@TEX", "ab":5, "h":1, "rbi":0, "r":0, "hr":0},{"game":"19990407_DET@TEX", "ab":5, "h":3, "rbi":4, "r":1, "hr":1}],"Lee Stevens":[{"game":"19990405_DET@TEX", "ab":4, "h":0, "rbi":0, "r":0, "hr":0},{"game":"19990406_DET@TEX", "ab":4, "h":3, "rbi":3, "r":3, "hr":2},{"game":"19990407_DET@TEX", "ab":5, "h":3, "rbi":0, "r":1, "hr":0}],"Todd Zeile":[{"game":"19990405_DET@TEX", "ab":3, "h":1, "rbi":0, "r":1, "hr":0},{"game":"19990406_DET@TEX", "ab":2, "h":0, "rbi":0, "r":2, "hr":0},{"game":"19990407_DET@TEX", "ab":5, "h":3, "rbi":0, "r":3, "hr":0}],"Royce Clayton":[{"game":"19990405_DET@TEX", "ab":4, "h":2, "rbi":0, "r":0, "hr":0},{"game":"19990406_DET@TEX", "ab":5, "h":2, "rbi":1, "r":1, "hr":0},{"game":"19990407_DET@TEX", "ab":2, "h":1, "rbi":2, "r":1, "hr":0}],"Rick Helling":[{"game":"19990405_DET@TEX", "ab":0, "h":0, "rbi":0, "r":0, "hr":0}],"Karim Garcia":[{"game":"19990406_DET@TEX", "ab":5, "h":2, "rbi":1, "r":1, "hr":1}],"Gabe Kapler":[{"game":"19990406_DET@TEX", "ab":5, "h":0, "rbi":0, "r":1, "hr":0}],"Bill Haselman":[{"game":"19990406_DET@TEX", "ab":4, "h":1, "rbi":1, "r":1, "hr":1}],"Luis Garcia":[{"game":"19990406_DET@TEX", "ab":0, "h":0, "rbi":0, "r":0, "hr":0}],"Justin Thompson":[{"game":"19990406_DET@TEX", "ab":0, "h":0, "rbi":0, "r":0, "hr":0}],"Felipe Lira":[{"game":"19990406_DET@TEX", "ab":0, "h":0, "rbi":0, "r":0, "hr":0}],"Sean Runyan":[{"game":"19990406_DET@TEX", "ab":0, "h":0, "rbi":0, "r":0, "hr":0},{"game":"19990407_DET@TEX", "ab":0, "h":0, "rbi":0, "r":0, "hr":0}],"Matt Anderson":[{"game":"19990406_DET@TEX", "ab":0, "h":0, "rbi":0, "r":0, "hr":0}],"Doug Brocail":[{"game":"19990406_DET@TEX", "ab":0, "h":0, "rbi":0, "r":0, "hr":0}],"Roberto Kelly":[{"game":"19990406_DET@TEX", "ab":3, "h":1, "rbi":0, "r":1, "hr":0}],"Aaron Sele":[{"game":"19990406_DET@TEX", "ab":0, "h":0, "rbi":0, "r":0, "hr":0}],"Esteban Loaiza":[{"game":"19990406_DET@TEX", "ab":0, "h":0, "rbi":0, "r":0, "hr":0}],"Tim Crabtree":[{"game":"19990406_DET@TEX", "ab":0, "h":0, "rbi":0, "r":0, "hr":0}],"Danny Patterson":[{"game":"19990406_DET@TEX", "ab":0, "h":0, "rbi":0, "r":0, "hr":0}],"John Wetteland":[{"game":"19990406_DET@TEX", "ab":0, "h":0, "rbi":0, "r":0, "hr":0}],"Willie Blair":[{"game":"19990407_DET@TEX", "ab":0, "h":0, "rbi":0, "r":0, "hr":0}],"Todd Jones":[{"game":"19990407_DET@TEX", "ab":0, "h":0, "rbi":0, "r":0, "hr":0}],"Gregg Zaun":[{"game":"19990407_DET@TEX", "ab":1, "h":0, "rbi":0, "r":0, "hr":0}],"Jon Shave":[{"game":"19990407_DET@TEX", "ab":2, "h":1, "rbi":0, "r":1, "hr":0},{"game":"19990407_DET@TEX", "ab":0, "h":0, "rbi":0, "r":0, "hr":0}],"Mark Clark":[{"game":"19990407_DET@TEX", "ab":0, "h":0, "rbi":0, "r":0, "hr":0}],"Mike Morgan":[{"game":"19990407_DET@TEX", "ab":0, "h":0, "rbi":0, "r":0, "hr":0}],"Chuck Knoblauch":[{"game":"19990405_NYY@OAK", "ab":3, "h":0, "rbi":0, "r":1, "hr":0},{"game":"19990406_NYY@OAK", "ab":5, "h":1, "rbi":0, "r":0, "hr":0},{"game":"19990407_NYY@OAK", "ab":3, "h":2, "rbi":2, "r":2, "hr":1}],"Derek Jeter":[{"game":"19990405_NYY@OAK", "ab":4, "h":2, "rbi":1, "r":0, "hr":0},{"game":"19990406_NYY@OAK", "ab":5, "h":4, "rbi":0, "r":0, "hr":0},{"game":"19990407_NYY@OAK", "ab":4, "h":1, "rbi":0, "r":2, "hr":0}],"Paul O'Neill":[{"game":"19990405_NYY@OAK", "ab":4, "h":2, "rbi":1, "r":0, "hr":0},{"game":"19990406_NYY@OAK", "ab":4, "h":0, "rbi":0, "r":0, "hr":0},{"game":"19990407_NYY@OAK", "ab":2, "h":0, "rbi":0, "r":1, "hr":0}],"Bernie Williams":[{"game":"19990405_NYY@OAK", "ab":4, "h":0, "rbi":0, "r":0, "hr":0},{"game":"19990406_NYY@OAK", "ab":4, "h":0, "rbi":0, "r":0, "hr":0},{"game":"19990407_NYY@OAK", "ab":5, "h":2, "rbi":2, "r":2, "hr":0}],"Tino Martinez":[{"game":"19990405_NYY@OAK", "ab":4, "h":1, "rbi":0, "r":1, "hr":0},{"game":"19990406_NYY@OAK", "ab":5, "h":1, "rbi":0, "r":0, "hr":0},{"game":"19990407_NYY@OAK", "ab":4, "h":2, "rbi":3, "r":0, "hr":0}],"Chili Davis":[{"game":"19990405_NYY@OAK", "ab":4, "h":2, "rbi":0, "r":1, "hr":0},{"game":"19990406_NYY@OAK", "ab":4, "h":2, "rbi":0, "r":0, "hr":0},{"game":"19990407_NYY@OAK", "ab":3, "h":2, "rbi":1, "r":1, "hr":1}],"Ricky Ledee":[{"game":"19990405_NYY@OAK", "ab":2, "h":1, "rbi":1, "r":1, "hr":0}],"Shane Spencer":[{"game":"19990405_NYY@OAK", "ab":1, "h":0, "rbi":0, "r":0, "hr":0},{"game":"19990405_NYY@OAK", "ab":1, "h":0, "rbi":0, "r":0, "hr":0}],"Scott Brosius":[{"game":"19990405_NYY@OAK", "ab":3, "h":1, "rbi":2, "r":1, "hr":0},{"game":"19990406_NYY@OAK", "ab":4, "h":0, "rbi":0, "r":0, "hr":0},{"game":"19990407_NYY@OAK", "ab":5, "h":0, "rbi":0, "r":0, "hr":0}],"Joe Girardi":[{"game":"19990405_NYY@OAK", "ab":2, "h":0, "rbi":0, "r":0, "hr":0}],"Roger Clemens":[{"game":"19990405_NYY@OAK", "ab":0, "h":0, "rbi":0, "r":0, "hr":0}],"Tony Phillips":[{"game":"19990405_NYY@OAK", "ab":4, "h":1, "rbi":0, "r":0, "hr":0},{"game":"19990406_NYY@OAK", "ab":4, "h":3, "rbi":0, "r":0, "hr":0},{"game":"19990406_NYY@OAK", "ab":0, "h":0, "rbi":0, "r":0, "hr":0},{"game":"19990407_NYY@OAK", "ab":4, "h":0, "rbi":0, "r":1, "hr":0},{"game":"19990407_NYY@OAK", "ab":0, "h":0, "rbi":0, "r":0, "hr":0}],"Jason McDonald":[{"game":"19990405_NYY@OAK", "ab":3, "h":0, "rbi":0, "r":0, "hr":0},{"game":"19990406_NYY@OAK", "ab":4, "h":0, "rbi":0, "r":0, "hr":0},{"game":"19990407_NYY@OAK", "ab":3, "h":1, "rbi":0, "r":1, "hr":0},{"game":"19990407_NYY@OAK", "ab":1, "h":0, "rbi":0, "r":0, "hr":0}],"Jason Giambi":[{"game":"19990405_NYY@OAK", "ab":4, "h":1, "rbi":0, "r":0, "hr":0},{"game":"19990406_NYY@OAK", "ab":3, "h":2, "rbi":0, "r":1, "hr":0},{"game":"19990407_NYY@OAK", "ab":4, "h":1, "rbi":0, "r":1, "hr":0}],"Matt Stairs":[{"game":"19990405_NYY@OAK", "ab":3, "h":0, "rbi":0, "r":0, "hr":0},{"game":"19990406_NYY@OAK", "ab":2, "h":0, "rbi":0, "r":1, "hr":0},{"game":"19990407_NYY@OAK", "ab":4, "h":1, "rbi":1, "r":1, "hr":0}],"John Jaha":[{"game":"19990405_NYY@OAK", "ab":3, "h":2, "rbi":1, "r":1, "hr":1},{"game":"19990407_NYY@OAK", "ab":2, "h":0, "rbi":0, "r":0, "hr":0}],"Ben Grieve":[{"game":"19990405_NYY@OAK", "ab":3, "h":0, "rbi":0, "r":0, "hr":0},{"game":"19990406_NYY@OAK", "ab":4, "h":2, "rbi":2, "r":1, "hr":1},{"game":"19990407_NYY@OAK", "ab":3, "h":2, "rbi":5, "r":2, "hr":2}],"Eric Chavez":[{"game":"19990405_NYY@OAK", "ab":3, "h":0, "rbi":0, "r":0, "hr":0},{"game":"19990406_NYY@OAK", "ab":4, "h":0, "rbi":0, "r":0, "hr":0},{"game":"19990407_NYY@OAK", "ab":4, "h":0, "rbi":0, "r":0, "hr":0}],"A.J. Hinch":[{"game":"19990405_NYY@OAK", "ab":3, "h":0, "rbi":0, "r":0, "hr":0},{"game":"19990406_NYY@OAK", "ab":2, "h":0, "rbi":0, "r":0, "hr":0},{"game":"19990407_NYY@OAK", "ab":3, "h":0, "rbi":0, "r":0, "hr":0}],"Miguel Tejada":[{"game":"19990405_NYY@OAK", "ab":3, "h":1, "rbi":0, "r":0, "hr":0},{"game":"19990406_NYY@OAK", "ab":3, "h":0, "rbi":0, "r":0, "hr":0},{"game":"19990407_NYY@OAK", "ab":4, "h":2, "rbi":2, "r":1, "hr":1}],"Gil Heredia":[{"game":"19990405_NYY@OAK", "ab":0, "h":0, "rbi":0, "r":0, "hr":0}],"Buddy Groom":[{"game":"19990405_NYY@OAK", "ab":0, "h":0, "rbi":0, "r":0, "hr":0},{"game":"19990407_NYY@OAK", "ab":0, "h":0, "rbi":0, "r":0, "hr":0}],"Brad Rigby":[{"game":"19990405_NYY@OAK", "ab":0, "h":0, "rbi":0, "r":0, "hr":0}],"Clay Bellinger":[{"game":"19990406_NYY@OAK", "ab":0, "h":0, "rbi":0, "r":0, "hr":0},{"game":"19990407_NYY@OAK", "ab":0, "h":0, "rbi":0, "r":1, "hr":0}],"Jorge Posada":[{"game":"19990406_NYY@OAK", "ab":2, "h":0, "rbi":0, "r":0, "hr":0},{"game":"19990407_NYY@OAK", "ab":5, "h":2, "rbi":1, "r":0, "hr":0}],"Chad Curtis":[{"game":"19990406_NYY@OAK", "ab":3, "h":2, "rbi":1, "r":1, "hr":1},{"game":"19990407_NYY@OAK", "ab":5, "h":1, "rbi":0, "r":1, "hr":0}],"Orlando Hernandez":[{"game":"19990406_NYY@OAK", "ab":0, "h":0, "rbi":0, "r":0, "hr":0}],"Mike Stanton":[{"game":"19990406_NYY@OAK", "ab":0, "h":0, "rbi":0, "r":0, "hr":0},{"game":"19990407_NYY@OAK", "ab":0, "h":0, "rbi":0, "r":0, "hr":0}],"Tim Raines":[{"game":"19990406_NYY@OAK", "ab":4, "h":1, "rbi":0, "r":0, "hr":0},{"game":"19990407_NYY@OAK", "ab":1, "h":0, "rbi":0, "r":0, "hr":0}],"Jorge Velandia":[{"game":"19990406_NYY@OAK", "ab":0, "h":0, "rbi":0, "r":0, "hr":0}],"Tom Candiotti":[{"game":"19990406_NYY@OAK", "ab":0, "h":0, "rbi":0, "r":0, "hr":0}],"Doug Jones":[{"game":"19990406_NYY@OAK", "ab":0, "h":0, "rbi":0, "r":0, "hr":0}],"Billy Taylor":[{"game":"19990406_NYY@OAK", "ab":0, "h":0, "rbi":0, "r":0, "hr":0},{"game":"19990407_NYY@OAK", "ab":0, "h":0, "rbi":0, "r":0, "hr":0}],"Ramiro Mendoza":[{"game":"19990407_NYY@OAK", "ab":0, "h":0, "rbi":0, "r":0, "hr":0}],"Jason Grimsley":[{"game":"19990407_NYY@OAK", "ab":0, "h":0, "rbi":0, "r":0, "hr":0}],"Jeff Nelson":[{"game":"19990407_NYY@OAK", "ab":0, "h":0, "rbi":0, "r":0, "hr":0}],"Mariano Rivera":[{"game":"19990407_NYY@OAK", "ab":0, "h":0, "rbi":0, "r":0, "hr":0}],"Scott Spiezio":[{"game":"19990407_NYY@OAK", "ab":4, "h":1, "rbi":1, "r":1, "hr":1}],"Ryan Christenson":[{"game":"19990407_NYY@OAK", "ab":0, "h":0, "rbi":0, "r":1, "hr":0},{"game":"19990407_NYY@OAK", "ab":0, "h":0, "rbi":0, "r":0, "hr":0}],"Mike Macfarlane":[{"game":"19990407_NYY@OAK", "ab":0, "h":0, "rbi":0, "r":0, "hr":0}],"Jimmy Haynes":[{"game":"19990407_NYY@OAK", "ab":0, "h":0, "rbi":0, "r":0, "hr":0}],"Tim Worrell":[{"game":"19990407_NYY@OAK", "ab":0, "h":0, "rbi":0, "r":0, "hr":0}],"T.J. Mathews":[{"game":"19990407_NYY@OAK", "ab":0, "h":0, "rbi":0, "r":0, "hr":0}],"Randy Winn":[{"game":"19990405_TB@BAL", "ab":5, "h":2, "rbi":0, "r":1, "hr":0},{"game":"19990407_TB@BAL", "ab":4, "h":1, "rbi":0, "r":1, "hr":0},{"game":"19990408_TB@BAL", "ab":4, "h":1, "rbi":0, "r":0, "hr":0}],"Dave Martinez":[{"game":"19990405_TB@BAL", "ab":5, "h":1, "rbi":1, "r":2, "hr":0},{"game":"19990407_TB@BAL", "ab":4, "h":1, "rbi":0, "r":1, "hr":0},{"game":"19990408_TB@BAL", "ab":3, "h":0, "rbi":0, "r":0, "hr":0}],"Jose Canseco":[{"game":"19990405_TB@BAL", "ab":4, "h":3, "rbi":0, "r":2, "hr":0},{"game":"19990407_TB@BAL", "ab":4, "h":1, "rbi":0, "r":1, "hr":0},{"game":"19990408_TB@BAL", "ab":4, "h":0, "rbi":0, "r":0, "hr":0}],"Fred McGriff":[{"game":"19990405_TB@BAL", "ab":4, "h":3, "rbi":1, "r":3, "hr":0},{"game":"19990407_TB@BAL", "ab":4, "h":2, "rbi":1, "r":1, "hr":1},{"game":"19990408_TB@BAL", "ab":4, "h":0, "rbi":0, "r":0, "hr":0}],"John Flaherty":[{"game":"19990405_TB@BAL", "ab":5, "h":1, "rbi":1, "r":0, "hr":0},{"game":"19990407_TB@BAL", "ab":3, "h":0, "rbi":1, "r":0, "hr":0},{"game":"19990408_TB@BAL", "ab":4, "h":1, "rbi":0, "r":0, "hr":0}],"Wade Boggs":[{"game":"19990405_TB@BAL", "ab":5, "h":2, "rbi":3, "r":1, "hr":0},{"game":"19990407_TB@BAL", "ab":4, "h":0, "rbi":0, "r":0, "hr":0},{"game":"19990408_TB@BAL", "ab":1, "h":1, "rbi":0, "r":0, "hr":0}],"Paul Sorrento":[{"game":"19990405_TB@BAL", "ab":3, "h":2, "rbi":2, "r":0, "hr":0},{"game":"19990407_TB@BAL", "ab":4, "h":0, "rbi":0, "r":0, "hr":0}],"Quinton McCracken":[{"game":"19990405_TB@BAL", "ab":1, "h":0, "rbi":1, "r":0, "hr":0},{"game":"19990405_TB@BAL", "ab":1, "h":0, "rbi":0, "r":0, "hr":0},{"game":"19990408_TB@BAL", "ab":4, "h":1, "rbi":0, "r":0, "hr":0}],"Miguel Cairo":[{"game":"19990405_TB@BAL", "ab":5, "h":1, "rbi":0, "r":0, "hr":0},{"game":"19990407_TB@BAL", "ab":3, "h":1, "rbi":0, "r":0, "hr":0},{"game":"19990408_TB@BAL", "ab":3, "h":1, "rbi":0, "r":0, "hr":0}],"Kevin Stocker":[{"game":"19990405_TB@BAL", "ab":4, "h":2, "rbi":0, "r":0, "hr":0},{"game":"19990407_TB@BAL", "ab":2, "h":1, "rbi":0, "r":0, "hr":0},{"game":"19990408_TB@BAL", "ab":2, "h":0, "rbi":0, "r":0, "hr":0}],"Wilson Alvarez":[{"game":"19990405_TB@BAL", "ab":0, "h":0, "rbi":0, "r":0, "hr":0}],"Mike Duvall":[{"game":"19990405_TB@BAL", "ab":0, "h":0, "rbi":0, "r":0, "hr":0}],"Rick White":[{"game":"19990405_TB@BAL", "ab":0, "h":0, "rbi":0, "r":0, "hr":0}],"Jim Mecir":[{"game":"19990405_TB@BAL", "ab":0, "h":0, "rbi":0, "r":0, "hr":0},{"game":"19990408_TB@BAL", "ab":0, "h":0, "rbi":0, "r":0, "hr":0}],"Brady Anderson":[{"game":"19990405_TB@BAL", "ab":3, "h":1, "rbi":1, "r":1, "hr":0},{"game":"19990407_TB@BAL", "ab":2, "h":0, "rbi":0, "r":1, "hr":0},{"game":"19990408_TB@BAL", "ab":3, "h":1, "rbi":0, "r":2, "hr":0}],"Mike Bordick":[{"game":"19990405_TB@BAL", "ab":3, "h":2, "rbi":1, "r":0, "hr":0},{"game":"19990407_TB@BAL", "ab":4, "h":3, "rbi":1, "r":2, "hr":0},{"game":"19990408_TB@BAL", "ab":4, "h":3, "rbi":2, "r":0, "hr":0}],"Will Clark":[{"game":"19990405_TB@BAL", "ab":5, "h":0, "rbi":0, "r":0, "hr":0},{"game":"19990407_TB@BAL", "ab":4, "h":0, "rbi":0, "r":0, "hr":0},{"game":"19990408_TB@BAL", "ab":3, "h":0, "rbi":0, "r":0, "hr":0}],"Albert Belle":[{"game":"19990405_TB@BAL", "ab":4, "h":2, "rbi":2, "r":0, "hr":0},{"game":"19990407_TB@BAL", "ab":4, "h":1, "rbi":2, "r":0, "hr":0},{"game":"19990408_TB@BAL", "ab":2, "h":0, "rbi":1, "r":0, "hr":0}],"Jeff Conine":[{"game":"19990405_TB@BAL", "ab":4, "h":0, "rbi":1, "r":0, "hr":0},{"game":"19990407_TB@BAL", "ab":2, "h":1, "rbi":0, "r":0, "hr":0}],"Cal Ripken":[{"game":"19990405_TB@BAL", "ab":4, "h":1, "rbi":0, "r":0, "hr":0}],"B.J. Surhoff":[{"game":"19990405_TB@BAL", "ab":3, "h":0, "rbi":0, "r":1, "hr":0},{"game":"19990407_TB@BAL", "ab":4, "h":0, "rbi":0, "r":0, "hr":0},{"game":"19990408_TB@BAL", "ab":4, "h":2, "rbi":0, "r":0, "hr":0}],"Charles Johnson":[{"game":"19990405_TB@BAL", "ab":3, "h":0, "rbi":0, "r":1, "hr":0},{"game":"19990407_TB@BAL", "ab":3, "h":1, "rbi":0, "r":1, "hr":0}],"Jeff Reboulet":[{"game":"19990405_TB@BAL", "ab":1, "h":0, "rbi":0, "r":2, "hr":0},{"game":"19990407_TB@BAL", "ab":3, "h":0, "rbi":0, "r":0, "hr":0},{"game":"19990407_TB@BAL", "ab":0, "h":0, "rbi":0, "r":0, "hr":0},{"game":"19990408_TB@BAL", "ab":3, "h":1, "rbi":1, "r":1, "hr":0}],"Harold Baines":[{"game":"19990405_TB@BAL", "ab":1, "h":0, "rbi":0, "r":0, "hr":0},{"game":"19990407_TB@BAL", "ab":1, "h":1, "rbi":0, "r":0, "hr":0},{"game":"19990408_TB@BAL", "ab":3, "h":0, "rbi":0, "r":0, "hr":0}],"Mike Mussina":[{"game":"19990405_TB@BAL", "ab":0, "h":0, "rbi":0, "r":0, "hr":0}],"Heathcliff Slocumb":[{"game":"19990405_TB@BAL", "ab":0, "h":0, "rbi":0, "r":0, "hr":0}],"Jesse Orosco":[{"game":"19990405_TB@BAL", "ab":0, "h":0, "rbi":0, "r":0, "hr":0}],"Ricky Bones":[{"game":"19990405_TB@BAL", "ab":0, "h":0, "rbi":0, "r":0, "hr":0}],"Doug Johns":[{"game":"19990405_TB@BAL", "ab":0, "h":0, "rbi":0, "r":0, "hr":0}],"Jesse Garcia":[{"game":"19990405_TB@BAL", "ab":0, "h":0, "rbi":0, "r":0, "hr":0},{"game":"19990407_TB@BAL", "ab":0, "h":0, "rbi":0, "r":0, "hr":0}],"Tony Saunders":[{"game":"19990407_TB@BAL", "ab":0, "h":0, "rbi":0, "r":0, "hr":0}],"Scott Aldred":[{"game":"19990407_TB@BAL", "ab":0, "h":0, "rbi":0, "r":0, "hr":0},{"game":"19990408_TB@BAL", "ab":0, "h":0, "rbi":0, "r":0, "hr":0}],"Albie Lopez":[{"game":"19990407_TB@BAL", "ab":0, "h":0, "rbi":0, "r":0, "hr":0}],"Roberto Hernandez":[{"game":"19990407_TB@BAL", "ab":0, "h":0, "rbi":0, "r":0, "hr":0}],"Willis Otanez":[{"game":"19990407_TB@BAL", "ab":4, "h":2, "rbi":0, "r":1, "hr":0},{"game":"19990408_TB@BAL", "ab":4, "h":0, "rbi":0, "r":0, "hr":0}],"Juan Guzman":[{"game":"19990407_TB@BAL", "ab":0, "h":0, "rbi":0, "r":0, "hr":0}],"Mike Fetters":[{"game":"19990407_TB@BAL", "ab":0, "h":0, "rbi":0, "r":0, "hr":0}],"Arthur Rhodes":[{"game":"19990407_TB@BAL", "ab":0, "h":0, "rbi":0, "r":0, "hr":0},{"game":"19990408_TB@BAL", "ab":0, "h":0, "rbi":0, "r":0, "hr":0}],"Mike Timlin":[{"game":"19990407_TB@BAL", "ab":0, "h":0, "rbi":0, "r":0, "hr":0},{"game":"19990408_TB@BAL", "ab":0, "h":0, "rbi":0, "r":0, "hr":0}],"Bob Smith":[{"game":"19990408_TB@BAL", "ab":3, "h":1, "rbi":0, "r":0, "hr":0}],"David Lamb":[{"game":"19990408_TB@BAL", "ab":1, "h":0, "rbi":0, "r":0, "hr":0}],"Bobby Witt":[{"game":"19990408_TB@BAL", "ab":0, "h":0, "rbi":0, "r":0, "hr":0}],"Lenny Webster":[{"game":"19990408_TB@BAL", "ab":3, "h":0, "rbi":0, "r":0, "hr":0}],"Scott Erickson":[{"game":"19990408_TB@BAL", "ab":0, "h":0, "rbi":0, "r":0, "hr":0}],"Wilton Guerrero":[{"game":"19990405_MON@PIT", "ab":4, "h":1, "rbi":2, "r":1, "hr":1},{"game":"19990406_MON@PIT", "ab":5, "h":1, "rbi":0, "r":1, "hr":0},{"game":"19990407_MON@PIT", "ab":5, "h":2, "rbi":1, "r":1, "hr":0}],"Orlando Cabrera":[{"game":"19990405_MON@PIT", "ab":6, "h":3, "rbi":1, "r":2, "hr":1},{"game":"19990406_MON@PIT", "ab":4, "h":0, "rbi":0, "r":0, "hr":0},{"game":"19990407_MON@PIT", "ab":5, "h":0, "rbi":0, "r":0, "hr":0}],"Rondell White":[{"game":"19990405_MON@PIT", "ab":5, "h":2, "rbi":2, "r":2, "hr":1},{"game":"19990406_MON@PIT", "ab":3, "h":2, "rbi":1, "r":1, "hr":0},{"game":"19990407_MON@PIT", "ab":5, "h":0, "rbi":0, "r":0, "hr":0}],"Vladimir Guerrero":[{"game":"19990405_MON@PIT", "ab":5, "h":3, "rbi":1, "r":2, "hr":1},{"game":"19990406_MON@PIT", "ab":4, "h":1, "rbi":2, "r":0, "hr":0},{"game":"19990407_MON@PIT", "ab":5, "h":4, "rbi":1, "r":2, "hr":1}],"Brad Fullmer":[{"game":"19990405_MON@PIT", "ab":3, "h":1, "rbi":2, "r":0, "hr":0},{"game":"19990406_MON@PIT", "ab":4, "h":1, "rbi":0, "r":0, "hr":0},{"game":"19990407_MON@PIT", "ab":1, "h":1, "rbi":0, "r":0, "hr":0}],"Michael Barrett":[{"game":"19990405_MON@PIT", "ab":4, "h":1, "rbi":0, "r":0, "hr":0},{"game":"19990406_MON@PIT", "ab":4, "h":1, "rbi":0, "r":0, "hr":0},{"game":"19990407_MON@PIT", "ab":4, "h":0, "rbi":0, "r":0, "hr":0},{"game":"19990407_MON@PIT", "ab":1, "h":0, "rbi":0, "r":0, "hr":0}],"Jose Vidro":[{"game":"19990405_MON@PIT", "ab":1, "h":0, "rbi":0, "r":0, "hr":0},{"game":"19990406_MON@PIT", "ab":1, "h":0, "rbi":0, "r":0, "hr":0},{"game":"19990407_MON@PIT", "ab":4, "h":3, "rbi":2, "r":0, "hr":0},{"game":"19990407_MON@PIT", "ab":1, "h":0, "rbi":0, "r":0, "hr":0}],"Chris Widger":[{"game":"19990405_MON@PIT", "ab":4, "h":1, "rbi":0, "r":1, "hr":0},{"game":"19990406_MON@PIT", "ab":4, "h":0, "rbi":0, "r":0, "hr":0},{"game":"19990407_MON@PIT", "ab":0, "h":0, "rbi":0, "r":0, "hr":0},{"game":"19990407_MON@PIT", "ab":1, "h":0, "rbi":0, "r":0, "hr":0}],"Manny Martinez":[{"game":"19990405_MON@PIT", "ab":4, "h":1, "rbi":0, "r":1, "hr":0},{"game":"19990406_MON@PIT", "ab":3, "h":0, "rbi":0, "r":0, "hr":0},{"game":"19990407_MON@PIT", "ab":4, "h":2, "rbi":0, "r":0, "hr":0}],"Orlando Merced":[{"game":"19990405_MON@PIT", "ab":1, "h":0, "rbi":0, "r":0, "hr":0},{"game":"19990406_MON@PIT", "ab":1, "h":1, "rbi":0, "r":0, "hr":0},{"game":"19990407_MON@PIT", "ab":0, "h":0, "rbi":0, "r":0, "hr":0}],"Dustin Hermanson":[{"game":"19990405_MON@PIT", "ab":1, "h":0, "rbi":1, "r":0, "hr":0}],"Shane Andrews":[{"game":"19990405_MON@PIT", "ab":2, "h":2, "rbi":0, "r":0, "hr":0},{"game":"19990406_MON@PIT", "ab":1, "h":0, "rbi":0, "r":0, "hr":0},{"game":"19990407_MON@PIT", "ab":4, "h":3, "rbi":0, "r":0, "hr":0}],"James Mouton":[{"game":"19990405_MON@PIT", "ab":0, "h":0, "rbi":0, "r":0, "hr":0},{"game":"19990407_MON@PIT", "ab":0, "h":0, "rbi":0, "r":0, "hr":0}],"Bobby Ayala":[{"game":"19990405_MON@PIT", "ab":0, "h":0, "rbi":0, "r":0, "hr":0},{"game":"19990407_MON@PIT", "ab":0, "h":0, "rbi":0, "r":0, "hr":0}],"Steve Kline":[{"game":"19990405_MON@PIT", "ab":0, "h":0, "rbi":0, "r":0, "hr":0},{"game":"19990407_MON@PIT", "ab":0, "h":0, "rbi":0, "r":0, "hr":0}],"Anthony Telford":[{"game":"19990405_MON@PIT", "ab":0, "h":0, "rbi":0, "r":0, "hr":0},{"game":"19990406_MON@PIT", "ab":0, "h":0, "rbi":0, "r":0, "hr":0}],"Jason Kendall":[{"game":"19990405_MON@PIT", "ab":4, "h":2, "rbi":1, "r":2, "hr":0},{"game":"19990406_MON@PIT", "ab":5, "h":2, "rbi":0, "r":1, "hr":0},{"game":"19990407_MON@PIT", "ab":5, "h":2, "rbi":1, "r":1, "hr":0}],"Warren Morris":[{"game":"19990405_MON@PIT", "ab":3, "h":1, "rbi":2, "r":0, "hr":0},{"game":"19990406_MON@PIT", "ab":4, "h":0, "rbi":0, "r":0, "hr":0},{"game":"19990407_MON@PIT", "ab":4, "h":2, "rbi":0, "r":1, "hr":0}],"Brian Giles":[{"game":"19990405_MON@PIT", "ab":4, "h":1, "rbi":0, "r":2, "hr":0},{"game":"19990406_MON@PIT", "ab":2, "h":1, "rbi":0, "r":2, "hr":0},{"game":"19990407_MON@PIT", "ab":3, "h":2, "rbi":0, "r":0, "hr":0},{"game":"19990407_MON@PIT", "ab":2, "h":1, "rbi":1, "r":0, "hr":0}],"Kevin Young":[{"game":"19990405_MON@PIT", "ab":5, "h":3, "rbi":3, "r":2, "hr":1},{"game":"19990406_MON@PIT", "ab":3, "h":1, "rbi":1, "r":1, "hr":0},{"game":"19990407_MON@PIT", "ab":4, "h":1, "rbi":1, "r":0, "hr":0}],"Brant Brown":[{"game":"19990405_MON@PIT", "ab":5, "h":1, "rbi":3, "r":1, "hr":1},{"game":"19990406_MON@PIT", "ab":4, "h":1, "rbi":1, "r":0, "hr":0},{"game":"19990407_MON@PIT", "ab":1, "h":0, "rbi":0, "r":1, "hr":0},{"game":"19990407_MON@PIT", "ab":1, "h":0, "rbi":0, "r":0, "hr":0}],"Ed Sprague":[{"game":"19990405_MON@PIT", "ab":4, "h":1, "rbi":1, "r":0, "hr":0},{"game":"19990406_MON@PIT", "ab":3, "h":1, "rbi":1, "r":0, "hr":0},{"game":"19990407_MON@PIT", "ab":4, "h":0, "rbi":0, "r":0, "hr":0}],"Jose Guillen":[{"game":"19990405_MON@PIT", "ab":4, "h":0, "rbi":0, "r":0, "hr":0},{"game":"19990406_MON@PIT", "ab":4, "h":1, "rbi":1, "r":0, "hr":0},{"game":"19990407_MON@PIT", "ab":4, "h":1, "rbi":0, "r":0, "hr":0}],"Mike Benjamin":[{"game":"19990405_MON@PIT", "ab":3, "h":1, "rbi":0, "r":1, "hr":0},{"game":"19990406_MON@PIT", "ab":4, "h":0, "rbi":0, "r":0, "hr":0},{"game":"19990407_MON@PIT", "ab":3, "h":0, "rbi":0, "r":1, "hr":0}],"Francisco Cordova":[{"game":"19990405_MON@PIT", "ab":1, "h":1, "rbi":0, "r":1, "hr":0}],"Al Martin":[{"game":"19990405_MON@PIT", "ab":1, "h":0, "rbi":0, "r":0, "hr":0},{"game":"19990406_MON@PIT", "ab":1, "h":0, "rbi":0, "r":0, "hr":0},{"game":"19990407_MON@PIT", "ab":3, "h":0, "rbi":0, "r":0, "hr":0}],"Turner Ward":[{"game":"19990405_MON@PIT", "ab":1, "h":0, "rbi":0, "r":0, "hr":0},{"game":"19990406_MON@PIT", "ab":1, "h":0, "rbi":0, "r":0, "hr":0},{"game":"19990407_MON@PIT", "ab":1, "h":0, "rbi":0, "r":0, "hr":0}],"Adrian Brown":[{"game":"19990405_MON@PIT", "ab":1, "h":0, "rbi":0, "r":0, "hr":0},{"game":"19990405_MON@PIT", "ab":0, "h":0, "rbi":0, "r":0, "hr":0},{"game":"19990406_MON@PIT", "ab":0, "h":0, "rbi":0, "r":0, "hr":0},{"game":"19990407_MON@PIT", "ab":1, "h":1, "rbi":1, "r":0, "hr":0}],"Scott Sauerbeck":[{"game":"19990405_MON@PIT", "ab":0, "h":0, "rbi":0, "r":0, "hr":0}],"Rich Loiselle":[{"game":"19990405_MON@PIT", "ab":0, "h":0, "rbi":0, "r":0, "hr":0},{"game":"19990407_MON@PIT", "ab":0, "h":0, "rbi":0, "r":0, "hr":0}],"Jason Phillips":[{"game":"19990405_MON@PIT", "ab":0, "h":0, "rbi":0, "r":0, "hr":0},{"game":"19990407_MON@PIT", "ab":0, "h":0, "rbi":0, "r":0, "hr":0}],"Mike Williams":[{"game":"19990405_MON@PIT", "ab":0, "h":0, "rbi":0, "r":0, "hr":0},{"game":"19990406_MON@PIT", "ab":0, "h":0, "rbi":0, "r":0, "hr":0}],"Carl Pavano":[{"game":"19990406_MON@PIT", "ab":2, "h":1, "rbi":0, "r":1, "hr":0}],"Mike Maddux":[{"game":"19990406_MON@PIT", "ab":0, "h":0, "rbi":0, "r":0, "hr":0},{"game":"19990407_MON@PIT", "ab":0, "h":0, "rbi":0, "r":0, "hr":0}],"Jason Schmidt":[{"game":"19990406_MON@PIT", "ab":1, "h":0, "rbi":0, "r":1, "hr":0}],"Jason Christiansen":[{"game":"19990406_MON@PIT", "ab":0, "h":0, "rbi":0, "r":0, "hr":0}],"Javier Vazquez":[{"game":"19990407_MON@PIT", "ab":3, "h":1, "rbi":0, "r":1, "hr":0}],"Ugueth Urbina":[{"game":"19990407_MON@PIT", "ab":0, "h":0, "rbi":0, "r":0, "hr":0}],"Abraham Nunez":[{"game":"19990407_MON@PIT", "ab":0, "h":0, "rbi":0, "r":1, "hr":0}],"Pete Schourek":[{"game":"19990407_MON@PIT", "ab":1, "h":0, "rbi":0, "r":0, "hr":0}],"Chris Peters":[{"game":"19990407_MON@PIT", "ab":0, "h":0, "rbi":0, "r":0, "hr":0}],"Marvin Benard":[{"game":"19990405_SF@CIN", "ab":3, "h":1, "rbi":0, "r":1, "hr":0},{"game":"19990406_SF@CIN", "ab":5, "h":2, "rbi":2, "r":1, "hr":1},{"game":"19990407_SF@CIN", "ab":1, "h":0, "rbi":0, "r":0, "hr":0}],"Bill Mueller":[{"game":"19990405_SF@CIN", "ab":4, "h":1, "rbi":1, "r":1, "hr":0}],"Barry Bonds":[{"game":"19990405_SF@CIN", "ab":2, "h":1, "rbi":1, "r":2, "hr":1},{"game":"19990406_SF@CIN", "ab":3, "h":0, "rbi":0, "r":2, "hr":0},{"game":"19990407_SF@CIN", "ab":2, "h":1, "rbi":0, "r":2, "hr":0}],"Jeff Kent":[{"game":"19990405_SF@CIN", "ab":4, "h":1, "rbi":1, "r":1, "hr":0},{"game":"19990406_SF@CIN", "ab":5, "h":0, "rbi":0, "r":0, "hr":0},{"game":"19990407_SF@CIN", "ab":4, "h":1, "rbi":3, "r":1, "hr":1}],"J.T. Snow":[{"game":"19990405_SF@CIN", "ab":4, "h":2, "rbi":2, "r":0, "hr":0},{"game":"19990406_SF@CIN", "ab":5, "h":3, "rbi":1, "r":3, "hr":0},{"game":"19990407_SF@CIN", "ab":5, "h":2, "rbi":2, "r":0, "hr":0}],"Ellis Burks":[{"game":"19990405_SF@CIN", "ab":3, "h":0, "rbi":0, "r":0, "hr":0},{"game":"19990406_SF@CIN", "ab":4, "h":1, "rbi":0, "r":1, "hr":0},{"game":"19990407_SF@CIN", "ab":1, "h":0, "rbi":0, "r":0, "hr":0}],"Brent Mayne":[{"game":"19990405_SF@CIN", "ab":4, "h":0, "rbi":0, "r":0, "hr":0},{"game":"19990406_SF@CIN", "ab":3, "h":2, "rbi":2, "r":0, "hr":0}],"Rich Aurilia":[{"game":"19990405_SF@CIN", "ab":3, "h":0, "rbi":0, "r":0, "hr":0},{"game":"19990406_SF@CIN", "ab":2, "h":0, "rbi":1, "r":1, "hr":0},{"game":"19990407_SF@CIN", "ab":5, "h":2, "rbi":0, "r":0, "hr":0}],"Mark Gardner":[{"game":"19990405_SF@CIN", "ab":3, "h":1, "rbi":0, "r":0, "hr":0}],"Stan Javier":[{"game":"19990405_SF@CIN", "ab":1, "h":0, "rbi":0, "r":0, "hr":0},{"game":"19990407_SF@CIN", "ab":4, "h":0, "rbi":0, "r":0, "hr":0}],"Alan Embree":[{"game":"19990405_SF@CIN", "ab":0, "h":0, "rbi":0, "r":0, "hr":0},{"game":"19990407_SF@CIN", "ab":0, "h":0, "rbi":0, "r":0, "hr":0}],"John Johnstone":[{"game":"19990405_SF@CIN", "ab":0, "h":0, "rbi":0, "r":0, "hr":0},{"game":"19990407_SF@CIN", "ab":0, "h":0, "rbi":0, "r":0, "hr":0}],"Mike Cameron":[{"game":"19990405_SF@CIN", "ab":4, "h":1, "rbi":0, "r":0, "hr":0},{"game":"19990406_SF@CIN", "ab":4, "h":1, "rbi":0, "r":0, "hr":0},{"game":"19990407_SF@CIN", "ab":4, "h":0, "rbi":0, "r":0, "hr":0}],"Barry Larkin":[{"game":"19990405_SF@CIN", "ab":4, "h":1, "rbi":0, "r":0, "hr":0},{"game":"19990406_SF@CIN", "ab":4, "h":0, "rbi":0, "r":0, "hr":0},{"game":"19990407_SF@CIN", "ab":4, "h":2, "rbi":1, "r":0, "hr":0}],"Sean Casey":[{"game":"19990405_SF@CIN", "ab":3, "h":0, "rbi":0, "r":0, "hr":0},{"game":"19990406_SF@CIN", "ab":4, "h":1, "rbi":0, "r":0, "hr":0},{"game":"19990407_SF@CIN", "ab":3, "h":0, "rbi":0, "r":0, "hr":0}],"Greg Vaughn":[{"game":"19990405_SF@CIN", "ab":4, "h":0, "rbi":0, "r":0, "hr":0},{"game":"19990406_SF@CIN", "ab":3, "h":0, "rbi":0, "r":0, "hr":0},{"game":"19990407_SF@CIN", "ab":3, "h":0, "rbi":0, "r":0, "hr":0}],"Dmitri Young":[{"game":"19990405_SF@CIN", "ab":4, "h":0, "rbi":0, "r":0, "hr":0},{"game":"19990406_SF@CIN", "ab":4, "h":0, "rbi":0, "r":0, "hr":0},{"game":"19990407_SF@CIN", "ab":4, "h":0, "rbi":0, "r":0, "hr":0}],"Ed Taubensee":[{"game":"19990405_SF@CIN", "ab":4, "h":2, "rbi":1, "r":1, "hr":1},{"game":"19990407_SF@CIN", "ab":2, "h":1, "rbi":0, "r":0, "hr":0}],"Aaron Boone":[{"game":"19990405_SF@CIN", "ab":3, "h":1, "rbi":0, "r":0, "hr":0},{"game":"19990406_SF@CIN", "ab":3, "h":2, "rbi":1, "r":1, "hr":1},{"game":"19990407_SF@CIN", "ab":2, "h":1, "rbi":0, "r":0, "hr":0}],"Pokey Reese":[{"game":"19990405_SF@CIN", "ab":2, "h":0, "rbi":0, "r":0, "hr":0},{"game":"19990406_SF@CIN", "ab":2, "h":0, "rbi":0, "r":0, "hr":0},{"game":"19990407_SF@CIN", "ab":3, "h":1, "rbi":0, "r":1, "hr":0}],"Brett Tomko":[{"game":"19990405_SF@CIN", "ab":1, "h":0, "rbi":0, "r":0, "hr":0}],"Mark Sweeney":[{"game":"19990405_SF@CIN", "ab":1, "h":0, "rbi":0, "r":0, "hr":0},{"game":"19990407_SF@CIN", "ab":1, "h":0, "rbi":0, "r":0, "hr":0}],"Dennys Reyes":[{"game":"19990405_SF@CIN", "ab":0, "h":0, "rbi":0, "r":0, "hr":0}],"Scott Sullivan":[{"game":"19990405_SF@CIN", "ab":0, "h":0, "rbi":0, "r":0, "hr":0},{"game":"19990407_SF@CIN", "ab":0, "h":0, "rbi":0, "r":0, "hr":0}],"Scott Williamson":[{"game":"19990405_SF@CIN", "ab":0, "h":0, "rbi":0, "r":0, "hr":0},{"game":"19990406_SF@CIN", "ab":0, "h":0, "rbi":0, "r":0, "hr":0}],"Charlie Hayes":[{"game":"19990406_SF@CIN", "ab":2, "h":1, "rbi":2, "r":1, "hr":0},{"game":"19990407_SF@CIN", "ab":4, "h":0, "rbi":0, "r":0, "hr":0}],"Kirk Rueter":[{"game":"19990406_SF@CIN", "ab":3, "h":0, "rbi":0, "r":0, "hr":0}],"Julian Tavarez":[{"game":"19990406_SF@CIN", "ab":0, "h":0, "rbi":0, "r":0, "hr":0},{"game":"19990407_SF@CIN", "ab":0, "h":0, "rbi":0, "r":0, "hr":0}],"Brian Johnson":[{"game":"19990406_SF@CIN", "ab":3, "h":2, "rbi":0, "r":0, "hr":0}],"Jason Bere":[{"game":"19990406_SF@CIN", "ab":1, "h":0, "rbi":0, "r":0, "hr":0}],"Jeffrey Hammonds":[{"game":"19990406_SF@CIN", "ab":1, "h":0, "rbi":0, "r":0, "hr":0}],"Chris Stynes":[{"game":"19990406_SF@CIN", "ab":1, "h":0, "rbi":0, "r":0, "hr":0}],"Gabe White":[{"game":"19990406_SF@CIN", "ab":0, "h":0, "rbi":0, "r":0, "hr":0},{"game":"19990407_SF@CIN", "ab":0, "h":0, "rbi":0, "r":0, "hr":0}],"John Hudek":[{"game":"19990406_SF@CIN", "ab":0, "h":0, "rbi":0, "r":0, "hr":0}],"F.P. Santangelo":[{"game":"19990407_SF@CIN", "ab":5, "h":2, "rbi":1, "r":2, "hr":0}],"Scott Servais":[{"game":"19990407_SF@CIN", "ab":3, "h":1, "rbi":0, "r":0, "hr":0}],"Russ Ortiz":[{"game":"19990407_SF@CIN", "ab":2, "h":1, "rbi":0, "r":1, "hr":0}],"Robb Nen":[{"game":"19990407_SF@CIN", "ab":0, "h":0, "rbi":0, "r":0, "hr":0}],"Mark Lewis":[{"game":"19990407_SF@CIN", "ab":3, "h":0, "rbi":0, "r":0, "hr":0}],"Hal Morris":[{"game":"19990407_SF@CIN", "ab":1, "h":0, "rbi":0, "r":0, "hr":0}],"Steve Avery":[{"game":"19990407_SF@CIN", "ab":1, "h":0, "rbi":0, "r":0, "hr":0}],"Danny Graves":[{"game":"19990407_SF@CIN", "ab":0, "h":0, "rbi":0, "r":0, "hr":0}],"Fernando Vina":[{"game":"19990405_MIL@STL", "ab":4, "h":2, "rbi":0, "r":0, "hr":0},{"game":"19990407_MIL@STL", "ab":4, "h":2, "rbi":1, "r":1, "hr":0},{"game":"19990408_MIL@STL", "ab":6, "h":2, "rbi":0, "r":1, "hr":0}],"Marquis Grissom":[{"game":"19990405_MIL@STL", "ab":3, "h":0, "rbi":0, "r":0, "hr":0},{"game":"19990407_MIL@STL", "ab":4, "h":0, "rbi":1, "r":0, "hr":0},{"game":"19990408_MIL@STL", "ab":6, "h":4, "rbi":2, "r":0, "hr":0}],"Jeff Cirillo":[{"game":"19990405_MIL@STL", "ab":4, "h":0, "rbi":0, "r":0, "hr":0},{"game":"19990407_MIL@STL", "ab":4, "h":1, "rbi":0, "r":0, "hr":0},{"game":"19990408_MIL@STL", "ab":4, "h":0, "rbi":0, "r":0, "hr":0}],"Jeromy Burnitz":[{"game":"19990405_MIL@STL", "ab":3, "h":0, "rbi":0, "r":0, "hr":0},{"game":"19990407_MIL@STL", "ab":4, "h":2, "rbi":2, "r":1, "hr":1},{"game":"19990408_MIL@STL", "ab":5, "h":0, "rbi":0, "r":0, "hr":0}],"Sean Berry":[{"game":"19990405_MIL@STL", "ab":3, "h":2, "rbi":0, "r":0, "hr":0},{"game":"19990407_MIL@STL", "ab":5, "h":1, "rbi":0, "r":0, "hr":0},{"game":"19990408_MIL@STL", "ab":5, "h":3, "rbi":0, "r":2, "hr":0}],"Dave Nilsson":[{"game":"19990405_MIL@STL", "ab":3, "h":1, "rbi":0, "r":0, "hr":0},{"game":"19990407_MIL@STL", "ab":5, "h":0, "rbi":0, "r":2, "hr":0},{"game":"19990408_MIL@STL", "ab":1, "h":0, "rbi":0, "r":0, "hr":0},{"game":"19990408_MIL@STL", "ab":0, "h":0, "rbi":0, "r":0, "hr":0}],"Mark Loretta":[{"game":"19990405_MIL@STL", "ab":3, "h":1, "rbi":0, "r":0, "hr":0},{"game":"19990408_MIL@STL", "ab":5, "h":4, "rbi":1, "r":0, "hr":0}],"Rich Becker":[{"game":"19990405_MIL@STL", "ab":1, "h":0, "rbi":0, "r":0, "hr":0}],"Geoff Jenkins":[{"game":"19990405_MIL@STL", "ab":3, "h":0, "rbi":0, "r":0, "hr":0},{"game":"19990407_MIL@STL", "ab":3, "h":0, "rbi":0, "r":0, "hr":0}],"Rafael Roque":[{"game":"19990405_MIL@STL", "ab":0, "h":0, "rbi":0, "r":0, "hr":0}],"Brian Banks":[{"game":"19990405_MIL@STL", "ab":1, "h":0, "rbi":0, "r":0, "hr":0},{"game":"19990407_MIL@STL", "ab":1, "h":0, "rbi":0, "r":0, "hr":0},{"game":"19990408_MIL@STL", "ab":1, "h":0, "rbi":0, "r":0, "hr":0}],"Alex Ochoa":[{"game":"19990405_MIL@STL", "ab":1, "h":0, "rbi":0, "r":0, "hr":0},{"game":"19990407_MIL@STL", "ab":0, "h":0, "rbi":0, "r":0, "hr":0},{"game":"19990408_MIL@STL", "ab":4, "h":1, "rbi":1, "r":1, "hr":0}],"Jose Valentin":[{"game":"19990405_MIL@STL", "ab":1, "h":0, "rbi":0, "r":0, "hr":0},{"game":"19990407_MIL@STL", "ab":3, "h":1, "rbi":0, "r":0, "hr":0},{"game":"19990408_MIL@STL", "ab":1, "h":0, "rbi":0, "r":0, "hr":0}],"David Weathers":[{"game":"19990405_MIL@STL", "ab":0, "h":0, "rbi":0, "r":0, "hr":0},{"game":"19990408_MIL@STL", "ab":0, "h":0, "rbi":0, "r":0, "hr":0}],"Chad Fox":[{"game":"19990405_MIL@STL", "ab":0, "h":0, "rbi":0, "r":0, "hr":0},{"game":"19990407_MIL@STL", "ab":0, "h":0, "rbi":0, "r":0, "hr":0}],"Mike Myers":[{"game":"19990405_MIL@STL", "ab":0, "h":0, "rbi":0, "r":0, "hr":0},{"game":"19990408_MIL@STL", "ab":0, "h":0, "rbi":0, "r":0, "hr":0}],"Eric Plunk":[{"game":"19990405_MIL@STL", "ab":0, "h":0, "rbi":0, "r":0, "hr":0},{"game":"19990407_MIL@STL", "ab":0, "h":0, "rbi":0, "r":0, "hr":0},{"game":"19990408_MIL@STL", "ab":0, "h":0, "rbi":0, "r":0, "hr":0}],"Bob Wickman":[{"game":"19990405_MIL@STL", "ab":0, "h":0, "rbi":0, "r":0, "hr":0},{"game":"19990408_MIL@STL", "ab":0, "h":0, "rbi":0, "r":0, "hr":0}],"Edgar Renteria":[{"game":"19990405_MIL@STL", "ab":3, "h":0, "rbi":0, "r":1, "hr":0},{"game":"19990407_MIL@STL", "ab":5, "h":2, "rbi":0, "r":0, "hr":0},{"game":"19990408_MIL@STL", "ab":0, "h":0, "rbi":0, "r":0, "hr":0},{"game":"19990408_MIL@STL", "ab":0, "h":0, "rbi":0, "r":0, "hr":0}],"Luis Ordaz":[{"game":"19990405_MIL@STL", "ab":1, "h":0, "rbi":0, "r":0, "hr":0},{"game":"19990408_MIL@STL", "ab":1, "h":0, "rbi":0, "r":0, "hr":0}],"J.D. Drew":[{"game":"19990405_MIL@STL", "ab":4, "h":0, "rbi":0, "r":0, "hr":0},{"game":"19990407_MIL@STL", "ab":4, "h":1, "rbi":0, "r":1, "hr":0},{"game":"19990408_MIL@STL", "ab":0, "h":0, "rbi":0, "r":0, "hr":0},{"game":"19990408_MIL@STL", "ab":0, "h":0, "rbi":0, "r":0, "hr":0}],"Alberto Castillo":[{"game":"19990405_MIL@STL", "ab":1, "h":1, "rbi":0, "r":1, "hr":0},{"game":"19990405_MIL@STL", "ab":0, "h":0, "rbi":0, "r":0, "hr":0},{"game":"19990408_MIL@STL", "ab":5, "h":1, "rbi":0, "r":1, "hr":0}],"Mark McGwire":[{"game":"19990405_MIL@STL", "ab":4, "h":1, "rbi":0, "r":1, "hr":0},{"game":"19990407_MIL@STL", "ab":3, "h":2, "rbi":4, "r":2, "hr":2},{"game":"19990408_MIL@STL", "ab":3, "h":0, "rbi":1, "r":0, "hr":0}],"Eric Davis":[{"game":"19990405_MIL@STL", "ab":3, "h":2, "rbi":0, "r":2, "hr":0},{"game":"19990407_MIL@STL", "ab":4, "h":2, "rbi":0, "r":1, "hr":0},{"game":"19990408_MIL@STL", "ab":4, "h":0, "rbi":0, "r":0, "hr":0}],"Fernando Tatis":[{"game":"19990405_MIL@STL", "ab":4, "h":2, "rbi":5, "r":3, "hr":2},{"game":"19990407_MIL@STL", "ab":4, "h":0, "rbi":0, "r":0, "hr":0},{"game":"19990408_MIL@STL", "ab":5, "h":1, "rbi":1, "r":1, "hr":1}],"Shawon Dunston":[{"game":"19990405_MIL@STL", "ab":3, "h":3, "rbi":0, "r":2, "hr":0},{"game":"19990405_MIL@STL", "ab":1, "h":0, "rbi":1, "r":0, "hr":0},{"game":"19990407_MIL@STL", "ab":1, "h":0, "rbi":0, "r":0, "hr":0},{"game":"19990408_MIL@STL", "ab":5, "h":1, "rbi":1, "r":0, "hr":0}],"Eli Marrero":[{"game":"19990405_MIL@STL", "ab":5, "h":2, "rbi":0, "r":2, "hr":0},{"game":"19990407_MIL@STL", "ab":4, "h":0, "rbi":0, "r":0, "hr":0},{"game":"19990408_MIL@STL", "ab":1, "h":0, "rbi":0, "r":0, "hr":0}],"Placido Polanco":[{"game":"19990405_MIL@STL", "ab":5, "h":3, "rbi":4, "r":0, "hr":0},{"game":"19990407_MIL@STL", "ab":4, "h":1, "rbi":0, "r":0, "hr":0},{"game":"19990408_MIL@STL", "ab":0, "h":0, "rbi":0, "r":1, "hr":0}],"Donovan Osborne":[{"game":"19990405_MIL@STL", "ab":1, "h":0, "rbi":0, "r":0, "hr":0}],"Joe McEwing":[{"game":"19990405_MIL@STL", "ab":1, "h":0, "rbi":0, "r":0, "hr":0},{"game":"19990407_MIL@STL", "ab":1, "h":1, "rbi":0, "r":1, "hr":0},{"game":"19990408_MIL@STL", "ab":2, "h":0, "rbi":0, "r":1, "hr":0}],"Darren Bragg":[{"game":"19990405_MIL@STL", "ab":1, "h":0, "rbi":0, "r":0, "hr":0},{"game":"19990407_MIL@STL", "ab":4, "h":2, "rbi":2, "r":1, "hr":1},{"game":"19990408_MIL@STL", "ab":3, "h":1, "rbi":1, "r":0, "hr":0}],"Willie McGee":[{"game":"19990405_MIL@STL", "ab":1, "h":0, "rbi":1, "r":0, "hr":0},{"game":"19990405_MIL@STL", "ab":0, "h":0, "rbi":0, "r":0, "hr":0},{"game":"19990408_MIL@STL", "ab":5, "h":1, "rbi":0, "r":0, "hr":0}],"Mike Busby":[{"game":"19990405_MIL@STL", "ab":0, "h":0, "rbi":0, "r":0, "hr":0}],"Scott Radinsky":[{"game":"19990405_MIL@STL", "ab":0, "h":0, "rbi":0, "r":0, "hr":0}],"Manny Aybar":[{"game":"19990405_MIL@STL", "ab":0, "h":0, "rbi":0, "r":0, "hr":0},{"game":"19990408_MIL@STL", "ab":0, "h":0, "rbi":0, "r":0, "hr":0}],"Ricky Bottalico":[{"game":"19990405_MIL@STL", "ab":0, "h":0, "rbi":0, "r":0, "hr":0},{"game":"19990407_MIL@STL", "ab":0, "h":0, "rbi":0, "r":0, "hr":0}],"Juan Acevedo":[{"game":"19990405_MIL@STL", "ab":0, "h":0, "rbi":0, "r":0, "hr":0},{"game":"19990407_MIL@STL", "ab":0, "h":0, "rbi":0, "r":0, "hr":0},{"game":"19990408_MIL@STL", "ab":0, "h":0, "rbi":0, "r":0, "hr":0}],"Steve Woodard":[{"game":"19990407_MIL@STL", "ab":1, "h":0, "rbi":0, "r":0, "hr":0}],"Kent Bottenfield":[{"game":"19990407_MIL@STL", "ab":2, "h":0, "rbi":0, "r":0, "hr":0}],"Lance Painter":[{"game":"19990407_MIL@STL", "ab":0, "h":0, "rbi":0, "r":0, "hr":0},{"game":"19990408_MIL@STL", "ab":0, "h":0, "rbi":0, "r":0, "hr":0}],"Bobby Hughes":[{"game":"19990408_MIL@STL", "ab":3, "h":0, "rbi":1, "r":0, "hr":0}],"Jim Abbott":[{"game":"19990408_MIL@STL", "ab":2, "h":0, "rbi":0, "r":0, "hr":0}],"Valerio de los Santos":[{"game":"19990408_MIL@STL", "ab":0, "h":0, "rbi":0, "r":0, "hr":0}],"Kent Mercker":[{"game":"19990408_MIL@STL", "ab":1, "h":0, "rbi":0, "r":0, "hr":0}]}